Workbook

Sheet Conferences
A1: # | B1: Acronym | C1: Year | D1: Edition | E1: Full Title | F1: Category | G1: Relevance | H1: Priority | I1: Publisher | J1: Indexing | K1: Cost (as verified) | L1: Fee | M1: Currency | N1: Abstract Deadline | O1: Submission Deadline | P1: Notification | Q1: Camera-Ready | R1: Registration Deadline | S1: Event Dates | T1: Event Start | U1: Event End | V1: Location / Venue | W1: Format | X1: Days to Deadline | Y1: Submission Status | Z1: Submission System | AA1: Paper Length | AB1: Website | AC1: Available Resources | AD1: Contact | AE1: Last Verified | AF1: Verification Notes | AG1: Added to List
A2: 1 | B2: CSAM | C2: 2026 | D2: XI | E2: XI International Scientific Conference “Computer Science and Applied Mathematics” | F2: Conference | G2: High | H2: =IF($G2="High",1,IF($G2="Mediocre",2,3)) -> 1 | I2: Academic Journal | J2: Conference collection; best presentations forwarded to Bulletin of KazNU (Mathematics, Mechanics, Computer Science), Problems of Computer Science (Siberian Branch RAS) and other Scopus / Web of Science journals | K2: Not published on the site | O2: 46280 | P2: 46295 | Q2: 46305 | S2: 07–11 Oct 2026 | T2: 46302 | U2: 46306 | V2: Al-Farabi Kazakh National University & Institute of Information and Computational Technologies, Al-Farabi Ave 71, Almaty, Kazakhstan | W2: In-person | X2: =IF(O2="","",INT(O2)-TODAY()) -> 11 | Y2: =IF($G2="Finished","Expired",IF(AND(O2<>"",INT(O2)>=TODAY()),IF(INT(O2)-TODAY()<=30,"Open - closing soon","Open"),IF(AND(T2<>"",U2<>"",INT(T2)<=TODAY(),INT(U2)>=TODAY()),"Event in progress",IF(AND(O2="",R2<>"",INT(R2)>=TODAY()),"Registration due",IF(AND(O2="",U2<>"",INT(U2)>=TODAY()),"Deadline not published",IF(AND(O2<>"",Q2<>"",INT(Q2)>=TODAY()),"Camera-ready due",IF(AND(O2<>"",R2<>"",INT(R2)>=TODAY()),"Registration due",IF(AND(U2<>"",INT(U2)>=TODAY()),"Submissions closed - event ahead","Expired")))))))) -> Open - closing soon | Z2: Google Form (forms.gle/rysdTmshMxarg2je7); separate registration form forms.gle/ZHTzheKQF4qgrDVu8 | AA2: Not published on the site | AB2: https://csam.kaznu.kz/en | AC2: Website; Submission; Registration | AD2: opcs2026sc@gmail.com; +7 708-354-21-65, +7 702-322-29-99, +7 707-933-88-90, +7 708-961-48-78, +7 707-375-22-96 (organising committee Mon-Fri 09:00-18:00, Almaty time UTC+6) | AE2: 46269 | AF2: RE-READ 04.09.2026, ALL THREE DEADLINES CONFIRMED on the Important Dates block: submission 15.09.2026 (11 days out), notification 30.09.2026, camera-ready 10.10.2026; event 07-11.10.2026. ADDED the organising-committee e-mail opcs2026sc@gmail.com and the four further phone numbers, and separated the two Google Forms: papers go to forms.gle/rysdTmshMxarg2je7, participant registration to forms.gle/ZHTzheKQF4qgrDVu8. The "Microsoft CMT" line in the page footer is CMT's standard acknowledgement boilerplate, NOT the submission route. The footer phone "+7 707 123 4567" is placeholder text; the Contacts page carries the real numbers. Still no fee published and no online-participation option. XI International Scientific Conference "Computer Science and Applied Mathematics", also styled the 11th International Conference "Informatics and Applied Mathematics"; organised by the Institute of Information and Computational Technologies, Al-Farabi KazNU, Lublin University of Technology and Turan University. Four tracks. NOT a CEUR venue - CEUR Vol-3922 is a different conference (IAM, Guelma, Algeria). | AG2: 46269
A3: 2 | B3: AISTDS | C3: 2026 | D3: 10th (inferred) | E3: Applied Information Systems and Technologies in the Digital Society | F3: Workshop | G3: High | H3: =IF($G3="High",1,IF($G3="Mediocre",2,3)) -> 1 | I3: CEUR.org | J3: DBLP, Scopus, Google Scholar | K3: 500 UAH registration fee (covers participation, publication, programme and the electronic proceedings) | L3: 500 | M3: UAH | O3: 46292 | R3: 46292 | S3: 01 Oct 2026, 10:00 | T3: 46296 | U3: 46296 | V3: Department of Applied Information Systems, Faculty of Information Technology, Taras Shevchenko National University of Kyiv, 24 Bohdan Hawrylyshyn Str, 4th floor, room 401, Kyiv, Ukraine | W3: Online (Zoom) | X3: =IF(O3="","",INT(O3)-TODAY()) -> 23 | Y3: =IF($G3="Finished","Expired",IF(AND(O3<>"",INT(O3)>=TODAY()),IF(INT(O3)-TODAY()<=30,"Open - closing soon","Open"),IF(AND(T3<>"",U3<>"",INT(T3)<=TODAY(),INT(U3)>=TODAY()),"Event in progress",IF(AND(O3="",R3<>"",INT(R3)>=TODAY()),"Registration due",IF(AND(O3="",U3<>"",INT(U3)>=TODAY()),"Deadline not published",IF(AND(O3<>"",Q3<>"",INT(Q3)>=TODAY()),"Camera-ready due",IF(AND(O3<>"",R3<>"",INT(R3)>=TODAY()),"Registration due",IF(AND(U3<>"",INT(U3)>=TODAY()),"Submissions closed - event ahead","Expired")))))))) -> Open - closing soon | Z3: E-mail to the organising committee | AA3: At least 10 pages, English, PDF, Microsoft Word CEUR template; max 4 authors (5 by exception) | AB3: https://aistis.knu.ua/how-to-submit/ | AC3: Website | AD3: aistis.conference@gmail.com; +38 (044) 481 44 82 | AE3: 46269 | AF3: OPEN - 23 days to the deadline. Submission AND payment both 27.09.2026, confirmed on /how-to-submit/ and /terms-and-fees/; 500 UAH covers participation, publication, the programme and the electronic collection. FORMAT CORRECTED from "Not stated": the home page says the conference is "held online with the use of Zoom platform". VENUE made specific (Dept of Applied Information Systems, 24 Bohdan Hawrylyshyn Str, room 401) and the committee phone added. EDITION FILLED as 10th by inference, not by statement: CEUR shows AISTDS 2024 = 8th (Vol-3942, 01.10.2024) and AISTDS 2025 = 9th (Vol-4133, 01.10.2025), so 2026 is the tenth - confirm with the organisers. Notification and camera-ready are still given only as "October 2026", with no day. Papers reviewed by at least two independent reviewers. Payment is styled a charitable contribution to Yevhenii Topolskov. | AG3: 45730
A4: 3 | B4: ATRIC | C4: 2026 | D4: — | E4: International Conference on Advanced Trends in Radioelectronics and Infocommunications | F4: Workshop | G4: High | H4: =IF($G4="High",1,IF($G4="Mediocre",2,3)) -> 1 | I4: Conference website (electronic proceedings) | J4: Not indexed - proceedings recommended by the Organising Committee are published electronically on the conference website after the event, following independent review | K4: Free — "The conference is free of organizational fees" (accommodation and meals at participants' own cost) | L4: 0 | M4: — | O4: 46295 | P4: 46305 | R4: 46295 | S4: 15–17 Oct 2026 | T4: 46310 | U4: 46312 | V4: Lviv Polytechnic National University, S. Bandera Str., building 12, Lviv 79013, Ukraine (organising committee: Department of Software and Hardware Systems of Infocommunications, Professorska Str. 2, Lviv 79013) | W4: Hybrid (on-site and videoconference) | X4: =IF(O4="","",INT(O4)-TODAY()) -> 26 | Y4: =IF($G4="Finished","Expired",IF(AND(O4<>"",INT(O4)>=TODAY()),IF(INT(O4)-TODAY()<=30,"Open - closing soon","Open"),IF(AND(T4<>"",U4<>"",INT(T4)<=TODAY(),INT(U4)>=TODAY()),"Event in progress",IF(AND(O4="",R4<>"",INT(R4)>=TODAY()),"Registration due",IF(AND(O4="",U4<>"",INT(U4)>=TODAY()),"Deadline not published",IF(AND(O4<>"",Q4<>"",INT(Q4)>=TODAY()),"Camera-ready due",IF(AND(O4<>"",R4<>"",INT(R4)>=TODAY()),"Registration due",IF(AND(U4<>"",INT(U4)>=TODAY()),"Submissions closed - event ahead","Expired")))))))) -> Open - closing soon | Z4: Google Forms registration + e-mail | AA4: Abstracts 2-4 full A5 pages, Times New Roman 11pt, line spacing 1.2, margins 1.5 cm all round, Ukrainian or English, MS Word | AB4: https://science.lpnu.ua/atric-2026 | AC4: Website | AD4: atric.conference@lpnu.ua; +38(032)2582156, +380985864516 (conference secretary Ivan Maksymiv) | AE4: 46269 | AF4: OPEN - 26 days out. The dates block reads exactly: 30.09.2026 18:00 submission of applications and the full text of report materials; 10.10.2026 18:00 Organising Committee confirmation of acceptance and inclusion in the programme; 15.10.2026 10:00 opening and plenary session. Event 15-17.10.2026. FREE of organisational fees confirmed on the Organizational Fee page (accommodation and meals at participants' own cost; hotel requests to the committee by 12.10.2026). ADDED the contact block and the full venue. PUBLISHER CORRECTED from "Not specified": there is no external publisher - proceedings appear on the conference site after the event. Working languages Ukrainian and English. Marks the 100th anniversary of the Lviv amateur radio movement, supported by the NGO "Lviv HF Amateur Radio Club". | AG4: 45778
A5: 4 | B5: CITI | C5: 2026 | D5: 4th | E5: The 4th International Conference on “Computer Information Technologies in Industry 4.0” | F5: Workshop | G5: High | H5: =IF($G5="High",1,IF($G5="Mediocre",2,3)) -> 1 | I5: CEUR.org | J5: Scopus (planned) | K5: Free — "Participation and publication are free of charge!" | L5: 0 | M5: — | O5: 46295 | P5: 46316 | Q5: 46325 | S5: 04–06 Nov 2026 | T5: 46330 | U5: 46332 | V5: Ternopil Ivan Puluj National Technical University, Ternopil, Ukraine (hybrid, jointly with Warsaw, Poland) | W5: Hybrid | X5: =IF(O5="","",INT(O5)-TODAY()) -> 26 | Y5: =IF($G5="Finished","Expired",IF(AND(O5<>"",INT(O5)>=TODAY()),IF(INT(O5)-TODAY()<=30,"Open - closing soon","Open"),IF(AND(T5<>"",U5<>"",INT(T5)<=TODAY(),INT(U5)>=TODAY()),"Event in progress",IF(AND(O5="",R5<>"",INT(R5)>=TODAY()),"Registration due",IF(AND(O5="",U5<>"",INT(U5)>=TODAY()),"Deadline not published",IF(AND(O5<>"",Q5<>"",INT(Q5)>=TODAY()),"Camera-ready due",IF(AND(O5<>"",R5<>"",INT(R5)>=TODAY()),"Registration due",IF(AND(U5<>"",INT(U5)>=TODAY()),"Submissions closed - event ahead","Expired")))))))) -> Open - closing soon | Z5: Microsoft CMT (cmt3.research.microsoft.com/CITI2026) | AA5: Regular papers 10-20 full pages, short papers 5-9 full pages; English, proofread; CEUR-ART one-column LibreOffice ODT template with the Libertinus font family (cloud editors and Word/Microsoft365 discouraged); max 5 co-authors; max 2 papers per author; title up to 13 words; references mostly not older than 5-8 years | AB5: https://citi.tntu.edu.ua/ | AC5: Website; Submission; CMT | AD5: citiconf@tntu.edu.ua | AE5: 46269 | AF5: OPEN - 26 days out. Deadlines confirmed verbatim: papers before 30.09.2026, notification on 21.10.2026, camera-ready before 30.10.2026; event 04-06.11.2026. "Participation and publication are free of charge!" confirmed. SUBMISSION SYSTEM CORRECTED: the previous pass recorded EasyChair, but /submission/ names Microsoft CMT at cmt3.research.microsoft.com/CITI2026. PAPER LENGTH AND FORMATTING FILLED IN (were blank) and the contact e-mail added. Venue is hybrid TNTU Ternopil with Warsaw, Poland. Proceedings to CEUR-WS, "planned to be indexed in Scopus". | AG5: 45608
A6: 5 | B6: BAITmp | C6: 2026 | D6: 3rd | E6: The 3rd International Workshop on Bioinformatics and Applied Information Technologies for Medical Purpose | F6: Workshop | G6: High | H6: =IF($G6="High",1,IF($G6="Mediocre",2,3)) -> 1 | I6: CEUR.org | J6: Scopus & Web of Science (planned) | K6: Free — "Participate for FREE ₴0" | L6: 0 | M6: — | O6: 46296 | P6: 46327 | Q6: 46334 | S6: 11–13 Nov 2026 | T6: 46337 | U6: 46339 | V6: Mohammed VI Polytechnic University, Benguerir, Morocco & Ternopil Ivan Puluj NTU, Ukraine | W6: Online presentations | X6: =IF(O6="","",INT(O6)-TODAY()) -> 27 | Y6: =IF($G6="Finished","Expired",IF(AND(O6<>"",INT(O6)>=TODAY()),IF(INT(O6)-TODAY()<=30,"Open - closing soon","Open"),IF(AND(T6<>"",U6<>"",INT(T6)<=TODAY(),INT(U6)>=TODAY()),"Event in progress",IF(AND(O6="",R6<>"",INT(R6)>=TODAY()),"Registration due",IF(AND(O6="",U6<>"",INT(U6)>=TODAY()),"Deadline not published",IF(AND(O6<>"",Q6<>"",INT(Q6)>=TODAY()),"Camera-ready due",IF(AND(O6<>"",R6<>"",INT(R6)>=TODAY()),"Registration due",IF(AND(U6<>"",INT(U6)>=TODAY()),"Submissions closed - event ahead","Expired")))))))) -> Open - closing soon | Z6: EasyChair (easychair.org/conferences?conf=bait2025 - the link still carries the 2025 slug) | AA6: Regular papers 10-20 full pages, short papers 5-9 full pages; English; CEUR-ART one-column LibreOffice ODT template with the Libertinus font family; PDF plus ODT/LaTeX source; max 5 co-authors; max 2 papers per author; each paper needs at least one author with at least 5 papers in DBLP; signed Author Agreement required | AB6: https://bait.tntu.edu.ua/ | AC6: Website; Submission; EasyChair | AD6: baitconf@tntu.edu.ua | AE6: 46269 | AF6: OPEN - 27 days out. Deadlines confirmed: paper 01.10.2026, notification 01.11.2026, camera-ready 08.11.2026. Free ("Participate for FREE"). ADDED paper length, formatting, the DBLP condition and the contact e-mail. SUBMISSION SYSTEM identified as EasyChair, but the live link still points at conf=bait2025 - verify with the organisers before submitting. THE SITE CONTRADICTS ITSELF ON THE EVENT DATES, three ways on one page: the banner says "November 16-18, 2026", the dates-box header says "November 12-13, 2026", and "November 11-13, 2026" appears twice in the body. 11-13.11.2026 is the reading kept here because it is the one repeated in the call itself, but confirm with the organisers. Held jointly with Mohammed VI Polytechnic University, Benguerir, Morocco; online presentations; proceedings to CEUR-WS, planned for Scopus and Web of Science. 3rd edition (the site writes "3nd"). | AG6: 45620
A7: 6 | B7: ICTM | C7: 2026 | D7: — | E7: Integrated Computer Technologies in Mechanical Engineering – Synergetic Engineering | F7: Conference + Workshop | G7: High | H7: =IF($G7="High",1,IF($G7="Mediocre",2,3)) -> 1 | I7: Springer.org | J7: Springer Science+Business Media book chapter; partnership option with the journal "Computation"; peer review by at least three scholars; free submission for students and PhD candidates | K7: Not published | O7: 46296 | P7: 46327 | S7: 18–20 Nov 2026 | T7: 46344 | U7: 46346 | V7: National Aerospace University "KhAI", Vadyma Manka st. 17, Kharkiv 61070, Ukraine | W7: Not stated | X7: =IF(O7="","",INT(O7)-TODAY()) -> 27 | Y7: =IF($G7="Finished","Expired",IF(AND(O7<>"",INT(O7)>=TODAY()),IF(INT(O7)-TODAY()<=30,"Open - closing soon","Open"),IF(AND(T7<>"",U7<>"",INT(T7)<=TODAY(),INT(U7)>=TODAY()),"Event in progress",IF(AND(O7="",R7<>"",INT(R7)>=TODAY()),"Registration due",IF(AND(O7="",U7<>"",INT(U7)>=TODAY()),"Deadline not published",IF(AND(O7<>"",Q7<>"",INT(Q7)>=TODAY()),"Camera-ready due",IF(AND(O7<>"",R7<>"",INT(R7)>=TODAY()),"Registration due",IF(AND(U7<>"",INT(U7)>=TODAY()),"Submissions closed - event ahead","Expired")))))))) -> Open - closing soon | Z7: E-mail to the organising committee (no online system; the submission page still shows the 2020 conference dates) | AA7: At least 10 and not more than 12 pages for the Springer book; Springer splnproc template (splnproc1703.zip) | AB7: https://ictm.khai.edu/ | AC7: Website; EasyChair | AD7: ictm2024@khai.edu; +380577884105 (chair Prof. Volodymyr Pavlikov; publication chair Assoc. Prof. Dmytro Kritskiy; secretary Assoc. Prof. Tetiana Starovoit) | AE7: 46269 | AF7: OPEN - 27 days out. Submission 01.10.2026 and notification 01.11.2026 confirmed; event 18-20.11.2026 at Kharkiv, Vadyma Manka st. 17 (the Contacts page still uses the street's former name, Chkalova 17 - same address). ADDED paper length (10-12 pages, Springer template), the publisher detail and the contact block; the site's e-mail is Cloudflare-obfuscated and decodes to ictm2024@khai.edu, an address still carrying the 2024 year. No camera-ready date, no fee and no indexing statement are published for 2026, and the submission page is stale (it still prints "29-30 October 2020"), so treat the submission route as e-mail and confirm with the committee. | AG7: 44779
A8: 7 | B8: DOORS | C8: 2027 | D8: 7th | E8: 7th Edge Computing Workshop | F8: Conference | G8: High | H8: =IF($G8="High",1,IF($G8="Mediocre",2,3)) -> 1 | I8: ACM Digital Library | J8: ACM ICPS; post-proceedings in the Journal of Edge Computing | K8: Not published | O8: 46367 | P8: 46389 | Q8: 46399 | R8: 46467 | S8: 02 Apr 2027 | T8: 46479 | U8: 46479 | V8: Zhytomyr Polytechnic State University, Department of Software Engineering, Zhytomyr, Ukraine | W8: Not stated | X8: =IF(O8="","",INT(O8)-TODAY()) -> 98 | Y8: =IF($G8="Finished","Expired",IF(AND(O8<>"",INT(O8)>=TODAY()),IF(INT(O8)-TODAY()<=30,"Open - closing soon","Open"),IF(AND(T8<>"",U8<>"",INT(T8)<=TODAY(),INT(U8)>=TODAY()),"Event in progress",IF(AND(O8="",R8<>"",INT(R8)>=TODAY()),"Registration due",IF(AND(O8="",U8<>"",INT(U8)>=TODAY()),"Deadline not published",IF(AND(O8<>"",Q8<>"",INT(Q8)>=TODAY()),"Camera-ready due",IF(AND(O8<>"",R8<>"",INT(R8)>=TODAY()),"Registration due",IF(AND(U8<>"",INT(U8)>=TODAY()),"Submissions closed - event ahead","Expired")))))))) -> Open | Z8: HotCRP | AA8: Full papers, at least 10 pages, LaTeX-generated PDF | AB8: https://edge.easyscience.education/2027/ | AC8: Website; Submission | AD8: tetianavakaliuk@acnsci.org; +380-96-065-3099 (Tetiana Vakaliuk) | AE8: 46269 | AF8: All four dates confirmed: submission 11.12.2026, notification 02.01.2027, camera-ready 12.01.2027, registration 21.03.2027; event 02.04.2027. ADDED the venue detail (Zhytomyr Polytechnic State University, Department of Software Engineering) and the chair's contact. Full papers at least 10 pages, LaTeX-generated PDF, submitted through HotCRP. Proceedings published online; selected papers eligible for the Journal of Edge Computing after a secondary review. No fee published. | AG8: 45581
A9: 8 | B9: SCIA | C9: 2027 | D9: — | E9: Scandinavian Conference on Image Analysis | F9: Conference | G9: High | H9: =IF($G9="High",1,IF($G9="Mediocre",2,3)) -> 1 | I9: Springer.org | J9: Springer LNCS | K9: Not published (early-bird registration deadline TBA) | N9: 46446 | O9: 46413 | P9: 46462 | Q9: 46488 | S9: 09–11 Jun 2027 (tutorials & workshops 08 Jun) | T9: 46547 | U9: 46549 | V9: Norwegian University of Science and Technology, Gjøvik, Norway | W9: Not stated | X9: =IF(O9="","",INT(O9)-TODAY()) -> 144 | Y9: =IF($G9="Finished","Expired",IF(AND(O9<>"",INT(O9)>=TODAY()),IF(INT(O9)-TODAY()<=30,"Open - closing soon","Open"),IF(AND(T9<>"",U9<>"",INT(T9)<=TODAY(),INT(U9)>=TODAY()),"Event in progress",IF(AND(O9="",R9<>"",INT(R9)>=TODAY()),"Registration due",IF(AND(O9="",U9<>"",INT(U9)>=TODAY()),"Deadline not published",IF(AND(O9<>"",Q9<>"",INT(Q9)>=TODAY()),"Camera-ready due",IF(AND(O9<>"",R9<>"",INT(R9)>=TODAY()),"Registration due",IF(AND(U9<>"",INT(U9)>=TODAY()),"Submissions closed - event ahead","Expired")))))))) -> Open | Z9: Not stated | AA9: Not published on the site | AB9: https://scia2027.org/ | AC9: Website | AD9: scia2027@idi.ntnu.no | AE9: 46269 | AF9: Dates confirmed and they really are in this order: paper submission opens 01.12.2026 and closes 26.01.2027; the separate ABSTRACT window opens 12.02.2027 and closes 28.02.2027 - the abstract deadline falls AFTER the paper deadline because they are different tracks, so this is not a transcription error. Notification 16.03.2027, camera-ready 11.04.2027. Event 09-11.06.2027 with tutorials and workshops on 08.06.2027, at NTNU Gjovik. ADDED the contact address. Springer LNCS branding is on the site but no page limits, fees or submission-system URL are published yet (early-bird registration still TBA). | AG9: 45674
A10: 9 | B10: IDAACS | C10: 2027 | D10: 14th | E10: The 14th IEEE International Conference on Intelligent Data Acquisition and Advanced Computing Systems: Technology and Applications | F10: Conference | G10: High | H10: =IF($G10="High",1,IF($G10="Mediocre",2,3)) -> 1 | I10: IEEE.org | J10: IEEE Xplore; Scopus, DBLP, WoS CPCI expected | K10: Not published for 2027 | N10: 46446 | O10: 46446 | P10: 46477 | Q10: 46507 | R10: 46538 | S10: 22–25 Sep 2027 | T10: 46652 | U10: 46655 | V10: Hellenic Army Academy, Athens, Greece | W10: Not stated | X10: =IF(O10="","",INT(O10)-TODAY()) -> 177 | Y10: =IF($G10="Finished","Expired",IF(AND(O10<>"",INT(O10)>=TODAY()),IF(INT(O10)-TODAY()<=30,"Open - closing soon","Open"),IF(AND(T10<>"",U10<>"",INT(T10)<=TODAY(),INT(U10)>=TODAY()),"Event in progress",IF(AND(O10="",R10<>"",INT(R10)>=TODAY()),"Registration due",IF(AND(O10="",U10<>"",INT(U10)>=TODAY()),"Deadline not published",IF(AND(O10<>"",Q10<>"",INT(Q10)>=TODAY()),"Camera-ready due",IF(AND(O10<>"",R10<>"",INT(R10)>=TODAY()),"Registration due",IF(AND(U10<>"",INT(U10)>=TODAY()),"Submissions closed - event ahead","Expired")))))))) -> Open | Z10: Microsoft CMT (cmt3.research.microsoft.com/IDAACS2027) | AA10: Not published on the site | AB10: https://www.idaacs.net/2027 | AC10: Website; CAP | AD10: orgcom@idaacs.net | AE10: 46269 | AF10: Dates confirmed: extended-abstract submission 28.02.2027 (this is the only submission deadline the site publishes, which is why the abstract and submission columns carry the same date), notification 31.03.2027, camera-ready 30.04.2027. REGISTRATION refined: early registration runs 02.04-31.05.2027, and late registration OPENS 01.06.2027 - 31.05.2027 is therefore the early-bird cut-off, not an absolute close. Event 22-25.09.2027, Hellenic Army Academy, Athens. Submission through Microsoft CMT. Accepted papers go to the conference proceedings and are submitted to IEEE Xplore; Scopus, DBLP and WoS CPCI expected. No 2027 fee published; no author page limit published yet. | AG10: 45723
A11: 10 | B11: ACIT | C11: 2027 | D11: 17th | E11: IEEE 17th International Conference on Advanced Computer Information Technologies | F11: Conference | G11: High | H11: =IF($G11="High",1,IF($G11="Mediocre",2,3)) -> 1 | I11: IEEE.org | J11: IEEE Xplore; registered Scopus periodical "Proceedings - International Conference on Advanced Computer Information Technologies (ACIT)"; Google Scholar, Web of Science, DBLP, SCImago; Online ISSN 2770-5226, Print ISSN 2770-5218; 2026 acceptance rate 46.92% | K11: Not published for 2027 - the shared Payments page still shows the ACIT'2026 schedule (on-site 350 EUR non-IEEE / 300 EUR IEEE member or PhD student / 250 EUR IEEE PhD student; online 120 / 90 / 70 EUR; accompanying person 200 EUR; free for single-author student papers; +20 EUR per page above 4; one registration covers up to two accepted papers) with payment due 30.06.2026 | M11: EUR | O11: 46481 | P11: 46530 | Q11: 46551 | R11: 46568 | S11: 13–15 Sep 2027 | T11: 46643 | U11: 46645 | V11: Constantine the Philosopher University, Tr. A. Hlinku 1, 949 01 Nitra, Slovakia | W11: Hybrid | X11: =IF(O11="","",INT(O11)-TODAY()) -> 212 | Y11: =IF($G11="Finished","Expired",IF(AND(O11<>"",INT(O11)>=TODAY()),IF(INT(O11)-TODAY()<=30,"Open - closing soon","Open"),IF(AND(T11<>"",U11<>"",INT(T11)<=TODAY(),INT(U11)>=TODAY()),"Event in progress",IF(AND(O11="",R11<>"",INT(R11)>=TODAY()),"Registration due",IF(AND(O11="",U11<>"",INT(U11)>=TODAY()),"Deadline not published",IF(AND(O11<>"",Q11<>"",INT(Q11)>=TODAY()),"Camera-ready due",IF(AND(O11<>"",R11<>"",INT(R11)>=TODAY()),"Registration due",IF(AND(U11<>"",INT(U11)>=TODAY()),"Submissions closed - event ahead","Expired")))))))) -> Open | Z11: Microsoft CMT (cmt3.research.microsoft.com/ACIT2027) | AA11: Final paper 4–10 pages, IEEE Proceedings format, DOC or LaTeX, max 6 co-authors | AB11: https://acit.tech/index.php/acit2027 | AC11: Website; Call for Papers (PDF); CMT | AD11: workshopACIT@gmail.com; +380977761442 (Faculty of Computer Information Technologies, West Ukrainian National University, 8 Oleny Teligy str., Ternopil, Ukraine) | AE11: 46269 | AF11: Dates confirmed on the ACIT'2027 page: paper 04.04.2027, notification 23.05.2027, camera-ready 13.06.2027, online registration AND fee payment 30.06.2027. COST CORRECTED - this was the main error here. The euro figures the tracker carried are the ACIT'2026 schedule: /payments and /venue are shared pages that still describe ACIT'2026 in Zlin, Czech Republic, with payment by 30.06.2026. No 2027 fee has been published, so the numeric Fee cell has been cleared (it read 0, which wrongly implied a free conference). ACIT'2027 itself is in Nitra, Slovakia, hosted by Constantine the Philosopher University, in hybrid format; ignore the Zlin address that the shared pages still show. Papers 4-10 pages, IEEE Proceedings format, max 6 co-authors, through Microsoft CMT. Indexing expanded with both ISSNs and the 2026 acceptance rate. | AG11: 43964
A12: 11 | B12: FedCSIS | C12: 2027 | D12: 22nd | E12: 22nd Conference on Computer Science and Intelligence Systems | F12: Conference | G12: High | H12: =IF($G12="High",1,IF($G12="Mediocre",2,3)) -> 1 | I12: IEEE.org | J12: Annals of Computer Science and Information Systems; IEEE catalogue TBA | K12: TBA — the conference fees page reads "TBA" | O12: 46521 | P12: 46566 | Q12: 46583 | R12: 46599 | S12: 12–15 Sep 2027 | T12: 46642 | U12: 46645 | V12: Gdynia, Poland | W12: Not stated | X12: =IF(O12="","",INT(O12)-TODAY()) -> 252 | Y12: =IF($G12="Finished","Expired",IF(AND(O12<>"",INT(O12)>=TODAY()),IF(INT(O12)-TODAY()<=30,"Open - closing soon","Open"),IF(AND(T12<>"",U12<>"",INT(T12)<=TODAY(),INT(U12)>=TODAY()),"Event in progress",IF(AND(O12="",R12<>"",INT(R12)>=TODAY()),"Registration due",IF(AND(O12="",U12<>"",INT(U12)>=TODAY()),"Deadline not published",IF(AND(O12<>"",Q12<>"",INT(Q12)>=TODAY()),"Camera-ready due",IF(AND(O12<>"",R12<>"",INT(R12)>=TODAY()),"Registration due",IF(AND(U12<>"",INT(U12)>=TODAY()),"Submissions closed - event ahead","Expired")))))))) -> Open | Z12: Not stated | AA12: Not published on the site | AB12: https://2027.fedcsis.org/ | AC12: Website | AD12: Not published on the site | AE12: 46269 | AF12: Dates confirmed: paper 14.05.2027, notification 28.06.2027, final paper 15.07.2027, early-registration discount ends 31.07.2027. FURTHER MILESTONES the tracker did not hold: position-paper submission 11.06.2027; thematic-session proposals 01.12.2026; summer-school proposals 01.03.2027; industrial-track proposals 25.06.2027. Event 12-15.09.2027, Gdynia, Poland. Fees still read TBA on the conference-fees page, and no submission-system URL, page limit or contact e-mail is published yet - only a generic /contact form. Proceedings in the Annals of Computer Science and Information Systems; IEEE catalogue number TBA. | AG12: 44732
A13: 12 | B13: MoMLeT&DS | C13: 2027 | D13: — | E13: Modern Machine Learning Technologies and Data Science | F13: Conference + Workshop | G13: High | H13: =IF($G13="High",1,IF($G13="Mediocre",2,3)) -> 1 | I13: CEUR.org | J13: CEUR-WS.org; Scopus, DBLP, Google Scholar | K13: Not published | O13: 46521 | P13: 46532 | Q13: 46537 | S13: 07 Jun 2027 | T13: 46545 | U13: 46545 | V13: Not stated - online event; run inside the "Mathematics. Information Technologies. Education" framework. Co-organised by the Leiden Institute of Advanced Computer Science (Netherlands), University of Jyvaskyla (Finland), Lviv Polytechnic National University, University Institute of Lisbon (Portugal), De Montfort University (UK), Politechnika Slaska (Poland) and Ivano-Frankivsk NTU of Oil and Gas | W13: Online (Zoom) | X13: =IF(O13="","",INT(O13)-TODAY()) -> 252 | Y13: =IF($G13="Finished","Expired",IF(AND(O13<>"",INT(O13)>=TODAY()),IF(INT(O13)-TODAY()<=30,"Open - closing soon","Open"),IF(AND(T13<>"",U13<>"",INT(T13)<=TODAY(),INT(U13)>=TODAY()),"Event in progress",IF(AND(O13="",R13<>"",INT(R13)>=TODAY()),"Registration due",IF(AND(O13="",U13<>"",INT(U13)>=TODAY()),"Deadline not published",IF(AND(O13<>"",Q13<>"",INT(Q13)>=TODAY()),"Camera-ready due",IF(AND(O13<>"",R13<>"",INT(R13)>=TODAY()),"Registration due",IF(AND(U13<>"",INT(U13)>=TODAY()),"Submissions closed - event ahead","Expired")))))))) -> Open | Z13: Not stated | AA13: Regular papers at least 10 pages | AB13: https://momlet.in.ua/important-dates/ | AC13: Website; EasyChair | AD13: momlet.in.ua@gmail.com; dmytro.h.dosyn@lpnu.ua | AE13: 46269 | AF13: Dates confirmed on /important-dates/: paper 14.05.2027, acceptance 25.05.2027, camera-ready 30.05.2027, workshop 07.06.2027. FILLED IN from /about-momlet/, which the previous pass did not read: FORMAT is "expected on-line participation using Zoom platform" (was "Not stated"); INDEXING is CEUR-WS.org with Scopus, DBLP and Google Scholar (was "Not stated"); PAPER LENGTH at least 10 pages; and two contact addresses. The Travel and Venue page is still empty, consistent with an online event. No fee published. | AG13: 44281
A14: 13 | B14: AI4Cyber | C14: 2026 | D14: — | E14: Workshop on Artificial Intelligence for Cybersecurity (AIC) | F14: Workshop | G14: High | H14: =IF($G14="High",1,IF($G14="Mediocre",2,3)) -> 1 | I14: CEUR.org | J14: CEUR-WS planned | K14: Not published | O14: 46272 | P14: 46275 | R14: 46272 | S14: 24–25 Sep 2026 | T14: 46289 | U14: 46290 | V14: University of the National Education Commission, Krakow, Poland (inside SMICS-2026) | W14: On-site | X14: =IF(O14="","",INT(O14)-TODAY()) -> 3 | Y14: =IF($G14="Finished","Expired",IF(AND(O14<>"",INT(O14)>=TODAY()),IF(INT(O14)-TODAY()<=30,"Open - closing soon","Open"),IF(AND(T14<>"",U14<>"",INT(T14)<=TODAY(),INT(U14)>=TODAY()),"Event in progress",IF(AND(O14="",R14<>"",INT(R14)>=TODAY()),"Registration due",IF(AND(O14="",U14<>"",INT(U14)>=TODAY()),"Deadline not published",IF(AND(O14<>"",Q14<>"",INT(Q14)>=TODAY()),"Camera-ready due",IF(AND(O14<>"",R14<>"",INT(R14)>=TODAY()),"Registration due",IF(AND(U14<>"",INT(U14)>=TODAY()),"Submissions closed - event ahead","Expired")))))))) -> Open - closing soon | Z14: Microsoft CMT (cmt3.research.microsoft.com/SMICS2026), subject area "AI for Cybersecurity" | AA14: More than 9 A4 pages; CEUR-WS ODT (LibreOffice) or LaTeX template, Libertinus font required, Word/Microsoft365 strongly discouraged; the FIRST author must have at least 5 papers indexed in DBLP; three files with fixed names - PDF, source, and a hand-signed scanned Author Agreement (NTP or TP variant) | AB14: https://smics.lnu.edu.ua/ | AC14: Website | AD14: ai_smics@lnu.edu.ua (workshop); smics@lnu.edu.ua (conference) | AE14: 46269 | AF14: OPEN - 3 days to the 07.09.2026 deadline. Dates FILLED IN from /en/dates, which the previous pass missed: 07.09.2026 is the "Deadline for Submission of Registration Forms - registration form submission closes for abstracts and workshop papers", so it is the SUBMISSION deadline as well as the registration deadline; notification of paper acceptance 10.09.2026; formal invitations and schedule guidelines 15.09.2026; conference days 24-25.09.2026. FORMAT CORRECTED from "Not stated" to on-site presentations at the University of the National Education Commission in Krakow. Nine-plus co-organisers across Ukraine, Poland, Sweden and the USA; 3 main tracks, 3 working languages; registration form forms.gle/wxu2zhuXg4vcPUCk8. No fee published. The workshop's official name on the site is "Artificial Intelligence for Cybersecurity (AIC)". ADDED its own paper specification and its own contact address, ai_smics@lnu.edu.ua. No prior CEUR volume was found, so this looks like a first edition - treat the scope as provisional. | AG14: 46269
A15: 14 | B15: SMICS | C15: 2026 | D15: — | E15: International Conference “Security of Modern Information and Communication Systems” | F15: Conference | G15: High | H15: =IF($G15="High",1,IF($G15="Mediocre",2,3)) -> 1 | I15: CEUR.org | J15: Two CEUR-WS workshop volumes planned | K15: Not published | O15: 46272 | P15: 46275 | R15: 46272 | S15: 24–25 Sep 2026 | T15: 46289 | U15: 46290 | V15: University of the National Education Commission, Krakow, Poland | W15: On-site | X15: =IF(O15="","",INT(O15)-TODAY()) -> 3 | Y15: =IF($G15="Finished","Expired",IF(AND(O15<>"",INT(O15)>=TODAY()),IF(INT(O15)-TODAY()<=30,"Open - closing soon","Open"),IF(AND(T15<>"",U15<>"",INT(T15)<=TODAY(),INT(U15)>=TODAY()),"Event in progress",IF(AND(O15="",R15<>"",INT(R15)>=TODAY()),"Registration due",IF(AND(O15="",U15<>"",INT(U15)>=TODAY()),"Deadline not published",IF(AND(O15<>"",Q15<>"",INT(Q15)>=TODAY()),"Camera-ready due",IF(AND(O15<>"",R15<>"",INT(R15)>=TODAY()),"Registration due",IF(AND(U15<>"",INT(U15)>=TODAY()),"Submissions closed - event ahead","Expired")))))))) -> Open - closing soon | Z15: E-mail for conference abstracts; Microsoft CMT (cmt3.research.microsoft.com/SMICS2026) for the two CEUR-WS workshops | AA15: Conference abstracts exactly 3-5 full A4 pages, LibreOffice ODT template with the Libertinus font, proper English, not edited by the organisers; max 2 abstracts per author and max 5 authors per paper; self-citation must not exceed 30% of references; mandatory sections - problem statement, novelty against known work, proposed solution, conclusions | AB15: https://smics.lnu.edu.ua/ | AC15: Website; Registration; CMT | AD15: smics@lnu.edu.ua; ai_smics@lnu.edu.ua (AI workshop); crypt_smics@lnu.edu.ua (cryptology workshop) | AE15: 46269 | AF15: OPEN - 3 days to the 07.09.2026 deadline. Dates FILLED IN from /en/dates, which the previous pass missed: 07.09.2026 is the "Deadline for Submission of Registration Forms - registration form submission closes for abstracts and workshop papers", so it is the SUBMISSION deadline as well as the registration deadline; notification of paper acceptance 10.09.2026; formal invitations and schedule guidelines 15.09.2026; conference days 24-25.09.2026. FORMAT CORRECTED from "Not stated" to on-site presentations at the University of the National Education Commission in Krakow. Nine-plus co-organisers across Ukraine, Poland, Sweden and the USA; 3 main tracks, 3 working languages; registration form forms.gle/wxu2zhuXg4vcPUCk8. No fee published. ADDED the main-proceedings abstract specification (3-5 A4 pages, ODT template, authorship and self-citation caps), which the previous pass left blank, and both workshop contact addresses. The two CEUR-WS workshops are "Artificial Intelligence for Cybersecurity" and "Cryptology and Data Security". Organised by the Department of Cybersecurity, Ivan Franko National University of Lviv. | AG15: 46269
A16: 15 | B16: WCDS | C16: 2026 | D16: — | E16: Workshop on Cryptology and Data Security (CDS) | F16: Workshop | G16: High | H16: =IF($G16="High",1,IF($G16="Mediocre",2,3)) -> 1 | I16: CEUR.org | J16: CEUR-WS planned for 2026; 2025 edition is Vol-4191 | K16: Not published | O16: 46272 | P16: 46275 | R16: 46272 | S16: 24–25 Sep 2026 | T16: 46289 | U16: 46290 | V16: University of the National Education Commission, Krakow, Poland (inside SMICS-2026) | W16: On-site | X16: =IF(O16="","",INT(O16)-TODAY()) -> 3 | Y16: =IF($G16="Finished","Expired",IF(AND(O16<>"",INT(O16)>=TODAY()),IF(INT(O16)-TODAY()<=30,"Open - closing soon","Open"),IF(AND(T16<>"",U16<>"",INT(T16)<=TODAY(),INT(U16)>=TODAY()),"Event in progress",IF(AND(O16="",R16<>"",INT(R16)>=TODAY()),"Registration due",IF(AND(O16="",U16<>"",INT(U16)>=TODAY()),"Deadline not published",IF(AND(O16<>"",Q16<>"",INT(Q16)>=TODAY()),"Camera-ready due",IF(AND(O16<>"",R16<>"",INT(R16)>=TODAY()),"Registration due",IF(AND(U16<>"",INT(U16)>=TODAY()),"Submissions closed - event ahead","Expired")))))))) -> Open - closing soon | Z16: Microsoft CMT (cmt3.research.microsoft.com/SMICS2026), subject area "Cryptology and Data Security" | AA16: More than 9 A4 pages; CEUR-WS ODT (LibreOffice) or LaTeX template, Libertinus font required, Word/Microsoft365 strongly discouraged; the FIRST author must have at least 5 papers indexed in DBLP; three files with fixed names - PDF, source, and a hand-signed scanned Author Agreement (NTP or TP variant) | AB16: https://smics.lnu.edu.ua/ | AC16: Website; CEUR volume | AD16: crypt_smics@lnu.edu.ua (workshop); smics@lnu.edu.ua (conference) | AE16: 46269 | AF16: OPEN - 3 days to the 07.09.2026 deadline. Dates FILLED IN from /en/dates, which the previous pass missed: 07.09.2026 is the "Deadline for Submission of Registration Forms - registration form submission closes for abstracts and workshop papers", so it is the SUBMISSION deadline as well as the registration deadline; notification of paper acceptance 10.09.2026; formal invitations and schedule guidelines 15.09.2026; conference days 24-25.09.2026. FORMAT CORRECTED from "Not stated" to on-site presentations at the University of the National Education Commission in Krakow. Nine-plus co-organisers across Ukraine, Poland, Sweden and the USA; 3 main tracks, 3 working languages; registration form forms.gle/wxu2zhuXg4vcPUCk8. No fee published. On the 2026 site the workshop is styled "Cryptology and Data Security (CDS)"; the acronym WCDS kept here is the one CEUR used for the 2025 edition (Vol-4191, co-located with SMICS 2025, Lviv, 16-18.10.2025, edited by Petro Venherskyi, Serhii Yevseiev, Oleg Gutik, Valeriy Trushevskyy and Mykhailo Viachalo of Ivan Franko NU of Lviv). ADDED its own paper specification and its own contact address, crypt_smics@lnu.edu.ua. | AG16: 46269
A17: 16 | B17: ICTERI | C17: 2026 | D17: 21st | E17: 21st International Conference on ICT in Education, Research and Industrial Applications | F17: Conference + Workshop | G17: Mediocre | H17: =IF($G17="High",1,IF($G17="Mediocre",2,3)) -> 2 | I17: Springer.org | J17: Springer CCIS; indexed by DBLP, EI-Compendex, Mathematical Reviews, SCImago and Scopus | K17: Free — "ICTERI 2026 does not charge any conference fee" | L17: 0 | M17: — | N17: 46132 | O17: 46160 | P17: 46202 | Q17: 46265 | R17: 46265 | S17: 15–18 Sep 2026 | T17: 46280 | U17: 46283 | V17: Yuriy Fedkovych Chernivtsi National University, Chernivtsi, Ukraine | W17: Hybrid | X17: =IF(O17="","",INT(O17)-TODAY()) -> -109 | Y17: =IF($G17="Finished","Expired",IF(AND(O17<>"",INT(O17)>=TODAY()),IF(INT(O17)-TODAY()<=30,"Open - closing soon","Open"),IF(AND(T17<>"",U17<>"",INT(T17)<=TODAY(),INT(U17)>=TODAY()),"Event in progress",IF(AND(O17="",R17<>"",INT(R17)>=TODAY()),"Registration due",IF(AND(O17="",U17<>"",INT(U17)>=TODAY()),"Deadline not published",IF(AND(O17<>"",Q17<>"",INT(Q17)>=TODAY()),"Camera-ready due",IF(AND(O17<>"",R17<>"",INT(R17)>=TODAY()),"Registration due",IF(AND(U17<>"",INT(U17)>=TODAY()),"Submissions closed - event ahead","Expired")))))))) -> Submissions closed - event ahead | Z17: Not stated | AA17: Not published on the site | AB17: https://icteri.org/icteri-2026/important-dates/ | AC17: Website | AD17: Not published on the site | AE17: 46269 | AF17: EVENT STARTS IN 11 DAYS. Dates re-confirmed on /important-dates/: abstract 20.04.2026, paper 04.05.2026 extended to 18.05.2026, notification 29.06.2026, camera-ready AND registration 31.08.2026, event 15-18.09.2026. ALSO on the page: workshop proposals 09.03.2026 with notification 16.03.2026. All deadlines are Anywhere-on-Earth (23:59 Hawaii). VENUE made specific - the host is Yuriy Fedkovych Chernivtsi National University. INDEXING corrected from "Springer CCIS (2025 approval pending)" to what the site actually claims: Springer CCIS indexed by DBLP, EI-Compendex, Mathematical Reviews, SCImago and Scopus. Free: "ICTERI 2026 does not charge any conference fee." Hybrid, with a stated preference for physical attendance and virtual participation by negotiation. No submission-system URL, page limit or contact e-mail is published. | AG17: 44294
A18: 17 | B18: KhPIW | C18: 2026 | D18: 7th | E18: IEEE 7th KhPI Week on Advanced Technology | F18: Conference | G18: Mediocre | H18: =IF($G18="High",1,IF($G18="Mediocre",2,3)) -> 2 | I18: IEEE.org | J18: IEEE; ISSN 3064-9560 (print), 3064-9579 (online), IEEE Conference Record #61439 | K18: Online/hybrid 250 EUR IEEE member, 300 EUR non-member, 150 EUR IEEE student, 200 EUR student non-member (VAT incl.); DISCOUNTS UP TO 95% for participants from Ukraine where foreign authors are 50% or fewer | L18: 150 | M18: EUR | O18: 46188 | P18: 46251 | Q18: 46264 | R18: 46285 | S18: 05–09 Oct 2026 | T18: 46300 | U18: 46304 | V18: National Technical University "Kharkiv Polytechnic Institute" (NTU "KhPI"), Kharkiv, Ukraine | W18: Online / hybrid | X18: =IF(O18="","",INT(O18)-TODAY()) -> -81 | Y18: =IF($G18="Finished","Expired",IF(AND(O18<>"",INT(O18)>=TODAY()),IF(INT(O18)-TODAY()<=30,"Open - closing soon","Open"),IF(AND(T18<>"",U18<>"",INT(T18)<=TODAY(),INT(U18)>=TODAY()),"Event in progress",IF(AND(O18="",R18<>"",INT(R18)>=TODAY()),"Registration due",IF(AND(O18="",U18<>"",INT(U18)>=TODAY()),"Deadline not published",IF(AND(O18<>"",Q18<>"",INT(Q18)>=TODAY()),"Camera-ready due",IF(AND(O18<>"",R18<>"",INT(R18)>=TODAY()),"Registration due",IF(AND(U18<>"",INT(U18)>=TODAY()),"Submissions closed - event ahead","Expired")))))))) -> Registration due | Z18: Not stated | AA18: Max 3 papers per author; +50% fee for a second paper, +75% for a third | AB18: https://khpiweek.ieee.org.ua/ | AC18: Website | AD18: Not published on the site | AE18: 46269 | AF18: REGISTRATION DEADLINE ADDED - 16 days out: the site's dates block gives "Final Payment Fees 20.09.2026", which the previous pass left blank. Other dates confirmed: paper 15.06.2026, acceptance 17.08.2026, final revision 30.08.2026; the conference programme is announced 07.09.2026; event 05-09.10.2026 at NTU "KhPI", Kharkiv. Fees 150-300 EUR with discounts up to 95% for participants from Ukraine where foreign authors are 50% or fewer; cashless payment only, no refunds; students and IEEE members must show proof. Proceedings ISSN 3064-9560 (print) / 3064-9579 (online), IEEE Conference Record #61439. No submission-system URL or contact e-mail is published on the site. | AG18: 44730
A19: 18 | B19: IS | C19: 2026 | D19: 13th | E19: IEEE 13th International Conference on Intelligent Systems | F19: Conference | G19: Mediocre | H19: =IF($G19="High",1,IF($G19="Mediocre",2,3)) -> 2 | I19: IEEE.org | J19: IEEE Xplore Digital Library; Scopus; Clarivate Web of Science | K19: Early (to 15 Aug) / late: IEEE members 400/450 EUR, non-members 450/500 EUR, students 300/350 EUR | L19: 300 | M19: EUR | O19: 46208 | P19: 46234 | Q19: 46244 | R19: 46269 | S19: 03–05 Sep 2026 | T19: 46268 | U19: 46270 | V19: Hotel Cherno More, Boulevard Slivnitsa 33, Varna, Bulgaria | W19: Hybrid | X19: =IF(O19="","",INT(O19)-TODAY()) -> -61 | Y19: =IF($G19="Finished","Expired",IF(AND(O19<>"",INT(O19)>=TODAY()),IF(INT(O19)-TODAY()<=30,"Open - closing soon","Open"),IF(AND(T19<>"",U19<>"",INT(T19)<=TODAY(),INT(U19)>=TODAY()),"Event in progress",IF(AND(O19="",R19<>"",INT(R19)>=TODAY()),"Registration due",IF(AND(O19="",U19<>"",INT(U19)>=TODAY()),"Deadline not published",IF(AND(O19<>"",Q19<>"",INT(Q19)>=TODAY()),"Camera-ready due",IF(AND(O19<>"",R19<>"",INT(R19)>=TODAY()),"Registration due",IF(AND(U19<>"",INT(U19)>=TODAY()),"Submissions closed - event ahead","Expired")))))))) -> Event in progress | Z19: EasyChair (easychair.org/conferences/?conf=is26) | AA19: 8 pages standard, IEEE two-column conference template, English, PDF only; EUR 50 per excess page; EUR 100 discount on a second paper by the same author | AB19: https://ieee-is-2026.blockchain2.uni-plovdiv.net/ | AC19: Website | AD19: ieee-is@bas.bg | AE19: 46269 | AF19: EVENT RUNNING NOW (03-05.09.2026). The news log confirms every extension: submission 08.06 to 22.06 to 05.07.2026; notification 20.07 to 31.07.2026; camera-ready 10.08.2026; early registration 03.08 to 07.08 to 15.08.2026. REGISTRATION DEADLINE CORRECTED from 25.08.2026: late registration closes 25.08.2026 for ONLINE participants but 04.09.2026 for in-person participants, so the last date is 04.09.2026 - today. MP4 uploads followed the same split (25.08 online, 04.09 in person). ADDED the EasyChair route, the 8-page IEEE two-column specification with the 50 EUR excess-page charge and the 100 EUR second-paper discount, the contact address, the full venue address and Web of Science to the indexing line. Fees: early/late IEEE 400/450 EUR, non-members 450/500 EUR, students 300/350 EUR, with the early/late line drawn at 15.08.2026. | AG19: 45345
A20: 19 | B20: ADT-ISMDDC | C20: 2026 | D20: — | E20: International Scientific and Practical Workshop “Advanced Digital Technologies: Intelligent Systems, Modeling, and Data-Driven Control” | F20: Workshop | G20: Mediocre | H20: =IF($G20="High",1,IF($G20="Mediocre",2,3)) -> 2 | I20: CEUR.org | J20: Scopus and DBLP; selected papers expanded into a collective monograph with ISBN, DOI, UDC and BBK | K20: Free — "Participation ... is free of charge" | L20: 0 | M20: — | O20: 46218 | P20: 46275 | R20: 46218 | S20: 22–24 Sep 2026 | T20: 46287 | U20: 46289 | V20: Odesa Polytechnic National University, Shevchenko ave. 1, 65044 Odesa, Ukraine (co-located with ICST-2026) | W20: Not stated | X20: =IF(O20="","",INT(O20)-TODAY()) -> -51 | Y20: =IF($G20="Finished","Expired",IF(AND(O20<>"",INT(O20)>=TODAY()),IF(INT(O20)-TODAY()<=30,"Open - closing soon","Open"),IF(AND(T20<>"",U20<>"",INT(T20)<=TODAY(),INT(U20)>=TODAY()),"Event in progress",IF(AND(O20="",R20<>"",INT(R20)>=TODAY()),"Registration due",IF(AND(O20="",U20<>"",INT(U20)>=TODAY()),"Deadline not published",IF(AND(O20<>"",Q20<>"",INT(Q20)>=TODAY()),"Camera-ready due",IF(AND(O20<>"",R20<>"",INT(R20)>=TODAY()),"Registration due",IF(AND(U20<>"",INT(U20)>=TODAY()),"Submissions closed - event ahead","Expired")))))))) -> Submissions closed - event ahead | Z20: EasyChair (easychair.org/cfp/adtismddc2026) plus a Google Forms registration form | AA20: CEUR article 10-15 pages in the new one-column CEUR ODT format; max 4 authors, at least one holding a PhD/DrSc with at least 4 DBLP-indexed papers | AB20: https://icst-conf.com/ | AC20: Website; EasyChair | AD20: icst_nuop@ukr.net; 126.ist.onpu@gmail.com; +38 (048) 705-85-69 (Chesnova Natalia Igorivna, business days 10:00-14:00) | AE20: 46269 | AF20: SUBMISSIONS CLOSED, EVENT AHEAD (18 days). Dates confirmed on the ICST-ODESA-2026 pages: applications and articles both 15.07.2026, preliminary acceptance with reviewer comments 30.08.2026, final acceptance 10.09.2026, event 22-24.09.2026. FURTHER MILESTONES now recorded: thesis-abstract submission 30.08.2026 (also the theses payment date), monograph applications close 20.09.2026 and monograph articles 30.09.2026 (also the monograph payment date). ADDED the paper specification (the workshop publishes through the same CEUR route as ICST: 10-15 pages, one-column CEUR ODT, max 4 authors with a qualified first author), the full venue address and the contact block - all three were blank. Participation in the workshop is free of charge. Selected papers are expanded into a collective monograph with ISBN, DOI, UDC and BBK. | AG20: 46269
A21: 20 | B21: ICST | C21: 2026 | D21: XIV | E21: Information Control Systems and Technologies | F21: Conference | G21: Mediocre | H21: =IF($G21="High",1,IF($G21="Mediocre",2,3)) -> 2 | I21: CEUR.org | J21: CEUR (Aachen, ISSN 1613-0073), Scopus and DBLP | K21: Free — participation in ICST-2026 is free of charge. Optional printed editions (Ukraine / abroad): electronic thesis 190 UAH / 35 USD, paper thesis 300 UAH / 70 USD, paper monograph 950 UAH | L21: 0 | M21: — | O21: 46218 | P21: 46275 | R21: 46218 | S21: 22–24 Sep 2026 | T21: 46287 | U21: 46289 | V21: Odesa Polytechnic National University, Shevchenko ave. 1, 65044 Odesa, Ukraine | W21: Not stated | X21: =IF(O21="","",INT(O21)-TODAY()) -> -51 | Y21: =IF($G21="Finished","Expired",IF(AND(O21<>"",INT(O21)>=TODAY()),IF(INT(O21)-TODAY()<=30,"Open - closing soon","Open"),IF(AND(T21<>"",U21<>"",INT(T21)<=TODAY(),INT(U21)>=TODAY()),"Event in progress",IF(AND(O21="",R21<>"",INT(R21)>=TODAY()),"Registration due",IF(AND(O21="",U21<>"",INT(U21)>=TODAY()),"Deadline not published",IF(AND(O21<>"",Q21<>"",INT(Q21)>=TODAY()),"Camera-ready due",IF(AND(O21<>"",R21<>"",INT(R21)>=TODAY()),"Registration due",IF(AND(U21<>"",INT(U21)>=TODAY()),"Submissions closed - event ahead","Expired")))))))) -> Submissions closed - event ahead | Z21: EasyChair (easychair.org/cfp/adtismddc2026) plus a Google Forms registration form | AA21: CEUR article 10-15 pages in the new one-column CEUR ODT format, max 4 authors with at least one holding a PhD/DrSc and at least 4 DBLP-indexed papers; thesis abstract 1-3 full A4 pages, Times New Roman 14pt, 1.5 line spacing; monograph article 16-24 pages, Times New Roman 12pt, 1.5 line spacing | AB21: https://icst-conf.com/ | AC21: Website; EasyChair | AD21: icst_nuop@ukr.net; 126.ist.onpu@gmail.com; +38 (048) 705-85-69 (Chesnova Natalia Igorivna, business days 10:00-14:00) | AE21: 46269 | AF21: SUBMISSIONS CLOSED, EVENT AHEAD (18 days). Dates confirmed on the ICST-ODESA-2026 pages: applications and articles both 15.07.2026, preliminary acceptance with reviewer comments 30.08.2026, final acceptance 10.09.2026, event 22-24.09.2026. FURTHER MILESTONES now recorded: thesis-abstract submission 30.08.2026 (also the theses payment date), monograph applications close 20.09.2026 and monograph articles 30.09.2026 (also the monograph payment date). ADDED the full venue address and the contact block, and extended the paper specification with the monograph track (16-24 pages, TNR 12pt). Costs confirmed: participation free; optional printed editions Ukraine/abroad - electronic thesis 190 UAH / 35 USD, paper thesis 300 UAH / 70 USD, paper monograph 950 UAH. Proceedings in CEUR (Aachen, ISSN 1613-0073), Scopus and DBLP. XIV edition. | AG21: 44730
A22: 21 | B22: XAI.it | C22: 2026 | D22: — | E22: Italian Workshop on Explainable AI, Generative and Agentic Systems: Trust, Transparency and Human Oversight | F22: Workshop | G22: Mediocre | H22: =IF($G22="High",1,IF($G22="Mediocre",2,3)) -> 2 | I22: CEUR.org | J22: CEUR AIxIA series; selected papers invited to Intelligenza Artificiale (IOS Press) | K22: Not published | O22: 46230 | P22: 46258 | Q22: 46279 | S22: 08–09 Oct 2026 | T22: 46303 | U22: 46304 | V22: Perugia, Italy - co-located with AI*IA 2026, the 24th International Conference of the Italian Association for Artificial Intelligence | W22: Not stated | X22: =IF(O22="","",INT(O22)-TODAY()) -> -39 | Y22: =IF($G22="Finished","Expired",IF(AND(O22<>"",INT(O22)>=TODAY()),IF(INT(O22)-TODAY()<=30,"Open - closing soon","Open"),IF(AND(T22<>"",U22<>"",INT(T22)<=TODAY(),INT(U22)>=TODAY()),"Event in progress",IF(AND(O22="",R22<>"",INT(R22)>=TODAY()),"Registration due",IF(AND(O22="",U22<>"",INT(U22)>=TODAY()),"Deadline not published",IF(AND(O22<>"",Q22<>"",INT(Q22)>=TODAY()),"Camera-ready due",IF(AND(O22<>"",R22<>"",INT(R22)>=TODAY()),"Registration due",IF(AND(U22<>"",INT(U22)>=TODAY()),"Submissions closed - event ahead","Expired")))))))) -> Camera-ready due | Z22: EasyChair (easychair.org/conferences/?conf=xaiit2026) | AA22: Regular papers 7-12 pages plus references; short and position papers 4-6 pages plus references; one-column CEUR-WS format | AB22: https://xai-it.github.io/call.html | AC22: Website; EasyChair | AD22: marco.polignano@uniba.it | AE22: 46269 | AF22: SUBMISSIONS CLOSED, EVENT AHEAD (34 days). Dates confirmed: paper 27.07.2026, notification to authors 24.08.2026, camera-ready 14.09.2026; event 08-09.10.2026. ADDED the EasyChair submission URL, the page limits and the contact address, and named the host conference - AI*IA 2026, the 24th conference of the Italian Association for AI, in Perugia. Published in the AIxIA series of CEUR-WS; best papers invited to "Intelligenza Artificiale" (IOS Press), indexed in Scopus and the Emerging Sources Citation Index. No registration deadline or fee published. | AG22: 45620
A23: 22 | B23: MCEME | C23: 2026 | D23: III | E23: III International Scientific and Theoretical Conference “Modeling and Computer Engineering in Mechanical Engineering: Theory, Practice, and Innovation” | F23: Workshop | G23: Mediocre | H23: =IF($G23="High",1,IF($G23="Mediocre",2,3)) -> 2 | I23: Academic Journal | J23: Papers are directed to the Lviv Polytechnic journal "Ukrainian Journal of Mechanical Engineering and Materials Science" and the interdepartmental collection "Automation of Industrial Processes in Mechanical Engineering and Instrumentation"; all publications go through double peer review | K23: Free — "There is no registration fee for participation in the conference" | L23: 0 | M23: — | O23: 46234 | Q23: 46254 | S23: 07–12 Sep 2026 (opening 08 Sep, 10:00) | T23: 46272 | U23: 46277 | V23: Lviv Polytechnic National University, 12 S. Bandera Street, Lviv 79013, Ukraine | W23: Hybrid | X23: =IF(O23="","",INT(O23)-TODAY()) -> -35 | Y23: =IF($G23="Finished","Expired",IF(AND(O23<>"",INT(O23)>=TODAY()),IF(INT(O23)-TODAY()<=30,"Open - closing soon","Open"),IF(AND(T23<>"",U23<>"",INT(T23)<=TODAY(),INT(U23)>=TODAY()),"Event in progress",IF(AND(O23="",R23<>"",INT(R23)>=TODAY()),"Registration due",IF(AND(O23="",U23<>"",INT(U23)>=TODAY()),"Deadline not published",IF(AND(O23<>"",Q23<>"",INT(Q23)>=TODAY()),"Camera-ready due",IF(AND(O23<>"",R23<>"",INT(R23)>=TODAY()),"Registration due",IF(AND(U23<>"",INT(U23)>=TODAY()),"Submissions closed - event ahead","Expired")))))))) -> Submissions closed - event ahead | Z23: Not stated | AA23: Not published on the site | AB23: https://science.lpnu.ua/mceme-2026 | AC23: Website | AD23: vasyl.t.dmytriv@lpnu.ua; +38(032)2582155, +380503724275 (chair Vasyl Dmytriv, Department of Design Machine and Automotive Engineering) | AE23: 46269 | AF23: EVENT RUNNING NOW (07-12.09.2026). Dates confirmed verbatim: 31.07.2026 18:00 applications and full text of report materials; 20.08.2026 18:00 full version of the article; 08.09.2026 10:00 opening and plenary session. Venue confirmed as Lviv Polytechnic National University, 12 S. Bandera Street, Lviv 79013 (organising committee at 1 Prof. Street, building 14). No registration fee, hotel requests by 20.08.2026. PUBLISHER CORRECTED from "Springer.org": the 2026 site routes papers to two Lviv Polytechnic outlets - the "Ukrainian Journal of Mechanical Engineering and Materials Science" and "Automation of Industrial Processes in Mechanical Engineering and Instrumentation" - with double peer review, and mentions no Springer volume. ADDED the chair's contact block. Working languages Ukrainian and English. No notification date is published. | AG23: 44728
A24: 23 | B24: ITTAP | C24: 2026 | D24: 6th | E24: The 6th International Conference on Information Technologies: Theoretical and Applied Problems | F24: Conference + Workshop | G24: Mediocre | H24: =IF($G24="High",1,IF($G24="Mediocre",2,3)) -> 2 | I24: CEUR.org | J24: DBLP and Scopus (planned) | K24: Free — remote participation and publication in the proceedings are free of charge | L24: 0 | M24: — | O24: 46237 | P24: 46275 | Q24: 46280 | S24: 19–21 Oct 2026 | T24: 46314 | U24: 46316 | V24: Ternopil Ivan Puluj National Technical University, Ternopil, Ukraine | W24: Hybrid (remote participation available) | X24: =IF(O24="","",INT(O24)-TODAY()) -> -32 | Y24: =IF($G24="Finished","Expired",IF(AND(O24<>"",INT(O24)>=TODAY()),IF(INT(O24)-TODAY()<=30,"Open - closing soon","Open"),IF(AND(T24<>"",U24<>"",INT(T24)<=TODAY(),INT(U24)>=TODAY()),"Event in progress",IF(AND(O24="",R24<>"",INT(R24)>=TODAY()),"Registration due",IF(AND(O24="",U24<>"",INT(U24)>=TODAY()),"Deadline not published",IF(AND(O24<>"",Q24<>"",INT(Q24)>=TODAY()),"Camera-ready due",IF(AND(O24<>"",R24<>"",INT(R24)>=TODAY()),"Registration due",IF(AND(U24<>"",INT(U24)>=TODAY()),"Submissions closed - event ahead","Expired")))))))) -> Camera-ready due | Z24: Microsoft CMT (cmt3.research.microsoft.com/ITTAP2026) | AA24: Regular papers 10-20 pages or short papers 5-9 pages, English; CEUR-ART template in .odt; max 5 co-authors; max 2 submissions per author (Programme and Organising Committee members 1) | AB24: https://ittap.tntu.edu.ua/ | AC24: Website; Submission; CMT | AD24: ittapua@gmail.com | AE24: 46269 | AF24: SUBMISSIONS CLOSED, EVENT AHEAD (45 days). The site shows each date twice, original and extended: paper 27.07 extended to 03.08.2026; REVISED PAPER 24.08 extended to 31.08.2026 (a milestone the tracker did not hold); notification 03.09 extended to 10.09.2026; camera-ready 15.09.2026; event 19-21.10.2026. SUBMISSION SYSTEM CORRECTED: the previous pass recorded EasyChair, but the site names Microsoft CMT at cmt3.research.microsoft.com/ITTAP2026. FORMAT refined to hybrid, and the contact e-mail and author limits added. Remote participation and publication are free; special journal publication fees apply only to papers selected for a journal. Three independent workshops run inside the conference. Proceedings to CEUR-WS, indexed in DBLP and Scopus. | AG24: 44406
A25: 24 | B25: HC@AIxIA | C25: 2026 | D25: 5th | E25: 5th International AIxIA Workshop on Artificial Intelligence for Healthcare | F25: Conference + Workshop | G25: Mediocre | H25: =IF($G25="High",1,IF($G25="Mediocre",2,3)) -> 2 | I25: Not yet announced | J25: Publication venue TBA - the organisers state it "will be unveiled later"; a journal special issue or a post-proceedings volume is possible | K25: Authors must register for AIxIA 2026 (workshop fee not published separately) | N25: 46238 | O25: 46238 | P25: 46261 | Q25: 46280 | R25: 46269 | S25: 06–09 Oct 2026 | T25: 46301 | U25: 46304 | V25: Perugia, Italy | W25: In-person (oral presentations; includes the annual AIxIA Healthcare Working Group meeting) | X25: =IF(O25="","",INT(O25)-TODAY()) -> -31 | Y25: =IF($G25="Finished","Expired",IF(AND(O25<>"",INT(O25)>=TODAY()),IF(INT(O25)-TODAY()<=30,"Open - closing soon","Open"),IF(AND(T25<>"",U25<>"",INT(T25)<=TODAY(),INT(U25)>=TODAY()),"Event in progress",IF(AND(O25="",R25<>"",INT(R25)>=TODAY()),"Registration due",IF(AND(O25="",U25<>"",INT(U25)>=TODAY()),"Deadline not published",IF(AND(O25<>"",Q25<>"",INT(Q25)>=TODAY()),"Camera-ready due",IF(AND(O25<>"",R25<>"",INT(R25)>=TODAY()),"Registration due",IF(AND(U25<>"",INT(U25)>=TODAY()),"Submissions closed - event ahead","Expired")))))))) -> Camera-ready due | Z25: ChairingTool (chairingtool.com/conferences/aixia2026/main-track?role=author) | AA25: Full papers max 15 pages including bibliography; short, position and discussion papers max 7 pages; no page limit for non-original contributions; Springer LNCS formatting guidelines | AB25: https://hcaixia2026.unical.it/call-for-papers/ | AC25: Website | AD25: hc-aixia@googlegroups.com | AE25: 46269 | AF25: SUBMISSIONS CLOSED, EVENT AHEAD (32 days). THREE DATES ADDED that the previous pass left blank: notification of acceptance 27.08.2026, camera-ready 15.09.2026, early registration 04.09.2026 - today. Abstract and paper submission both 04.08.2026 (extended) confirmed. PUBLISHER CORRECTED from "CEUR.org": the call says only "The publication venue for the proceedings is TBA, and will be unveiled later", with a journal special issue or post-proceedings volume as possibilities, so CEUR is not confirmed for this edition. Submission runs through ChairingTool on the AIxIA 2026 main track, not a CEUR-style system. ADDED the LNCS formatting note and the mailing-list contact. 5th edition, Perugia, Italy, inside AIxIA 2026, 06-09.10.2026; authors must register for AIxIA 2026 and no separate workshop fee is published. | AG25: 45609
A26: 25 | B26: DESSERT | C26: 2026 | D26: 16th | E26: 16th International IEEE Conference Dependable Systems, Services and Technologies | F26: Conference | G26: Mediocre | H26: =IF($G26="High",1,IF($G26="Mediocre",2,3)) -> 2 | I26: IEEE.org | J26: IEEE Xplore Digital Library, indexed by Scopus; authors of selected papers invited to extend into Web of Science / Scopus journals | K26: Full registration 300 EUR non-IEEE member / 260 EUR IEEE member; students presenting a single-author paper 240 EUR non-IEEE / 200 EUR IEEE; accompanying person or participation without paper/presentation 150 EUR; online presentation for Ukrainian participants 70 EUR non-IEEE / 50 EUR IEEE | L26: 50 | M26: EUR | O26: 46246 | P26: 46267 | Q26: 46274 | R26: 46277 | S26: 02–04 Oct 2026 | T26: 46297 | U26: 46299 | V26: Corfu (Kerkyra), Greece - organising committee: Department 503, National Aerospace University "KhAI", Vadym Manko str. 17, Kharkiv 61070, Ukraine | W26: Hybrid (remote audio/video support and as an in-person event) | X26: =IF(O26="","",INT(O26)-TODAY()) -> -23 | Y26: =IF($G26="Finished","Expired",IF(AND(O26<>"",INT(O26)>=TODAY()),IF(INT(O26)-TODAY()<=30,"Open - closing soon","Open"),IF(AND(T26<>"",U26<>"",INT(T26)<=TODAY(),INT(U26)>=TODAY()),"Event in progress",IF(AND(O26="",R26<>"",INT(R26)>=TODAY()),"Registration due",IF(AND(O26="",U26<>"",INT(U26)>=TODAY()),"Deadline not published",IF(AND(O26<>"",Q26<>"",INT(Q26)>=TODAY()),"Camera-ready due",IF(AND(O26<>"",R26<>"",INT(R26)>=TODAY()),"Registration due",IF(AND(U26<>"",INT(U26)>=TODAY()),"Submissions closed - event ahead","Expired")))))))) -> Camera-ready due | Z26: Microsoft CMT (camera-ready papers submitted to the DESSERT'2026 subject area) | AA26: 5-8 pages, PDF, IEEE conference template; peer-reviewed by at least three independent reviewers; accepted papers must be presented by a co-author ("no-show" papers are dropped) | AB26: https://www.dessert-conf.org/dessert-2026/ | AC26: Website | AD26: dessert@csn.khai.edu; +38 (066) 5389293, +38 (096) 1305556 (Olena Surynovych) | AE26: 46269 | AF26: SUBMISSIONS CLOSED, EVENT AHEAD (28 days). Dates confirmed: paper 12.08.2026, notification 02.09.2026, final manuscript 09.09.2026, registration and payment 12.09.2026; event 02-04.10.2026. ALSO: workshop proposals 15.07.2026 with notification 17.07.2026, and the draft programme published 17.09.2026. COST CORRECTED - this was the main error here. The previous pass recorded "not published, the Registration fees page does not resolve"; the page does resolve and gives the full euro table now recorded, including a 70/50 EUR online rate for Ukrainian participants. ADDED the Microsoft CMT route, the 5-8 page IEEE-template specification, the contact block and the hybrid format, and expanded the indexing line with Scopus and the journal invitation. Two workshops run inside the conference: EI4Safe (2nd) and HMcCS (3rd). | AG26: 43964
A27: 26 | B27: CSIT | C27: 2026 | D27: 20th | E27: IEEE 20th International Conference on Computer Science and Information Technologies | F27: Conference | G27: Mediocre | H27: =IF($G27="High",1,IF($G27="Mediocre",2,3)) -> 2 | I27: IEEE.org | J27: IEEE Xplore Digital Library (Scopus and Web of Science indexation) | K27: 250 EUR IEEE member, 300 EUR non-member, 150 EUR IEEE student/life member, 200 EUR student non-member; DISCOUNTS UP TO 95% for participants from Ukraine where foreign authors are 50% or fewer | L27: 150 | M27: EUR | O27: 46254 | P27: 46290 | R27: 46291 | S27: 14–17 Oct 2026 | T27: 46309 | U27: 46312 | V27: Lviv, Ukraine - Lviv Polytechnic National University with the IEEE Ukraine Section | W27: Hybrid | X27: =IF(O27="","",INT(O27)-TODAY()) -> -15 | Y27: =IF($G27="Finished","Expired",IF(AND(O27<>"",INT(O27)>=TODAY()),IF(INT(O27)-TODAY()<=30,"Open - closing soon","Open"),IF(AND(T27<>"",U27<>"",INT(T27)<=TODAY(),INT(U27)>=TODAY()),"Event in progress",IF(AND(O27="",R27<>"",INT(R27)>=TODAY()),"Registration due",IF(AND(O27="",U27<>"",INT(U27)>=TODAY()),"Deadline not published",IF(AND(O27<>"",Q27<>"",INT(Q27)>=TODAY()),"Camera-ready due",IF(AND(O27<>"",R27<>"",INT(R27)>=TODAY()),"Registration due",IF(AND(U27<>"",INT(U27)>=TODAY()),"Submissions closed - event ahead","Expired")))))))) -> Registration due | Z27: Microsoft CMT (cmt3.research.microsoft.com/CSITC2026) | AA27: 4 to a maximum of 6 full pages, max 6 authors, IMRaD structure required, text similarity max 30% | AB27: https://csit.ieee.org.ua/call-for-papers/ | AC27: Website; Facebook | AD27: Not published on the site | AE27: 46269 | AF27: SUBMISSIONS CLOSED, EVENT AHEAD (40 days). Dates confirmed: paper 20.08.2026, acceptance 25.09.2026, conference fee payment 26.09.2026; event 14-17.10.2026 in Lviv. ONE MILESTONE ADDED to the record: a PRE-ACCEPTANCE notification on 20.09.2026 precedes the 25.09.2026 acceptance notification. ADDED the hybrid format, the Microsoft CMT submission URL and the full paper specification (4-6 pages, max 6 authors, IMRaD, 30% similarity cap), and expanded the indexing line from a bare "IEEE" to IEEE Xplore with Scopus and Web of Science indexation. Fees 150-300 EUR by IEEE membership and student status, +50% for an additional paper, discounts up to 95% for participants from Ukraine where foreign authors are 50% or fewer. No contact e-mail is published on either page. 20th edition, organised with the IEEE Ukraine Section. | AG27: 43964
A28: 27 | B28: IT&I | C28: 2026 | D28: XIII | E28: XIII International Conference “Information Technology and Implementation” | F28: Conference + Workshop | G28: Mediocre | H28: =IF($G28="High",1,IF($G28="Mediocre",2,3)) -> 2 | I28: Springer.org | J28: Springer CCIS; Scopus, SCImago, DBLP, EI-Compendex | K28: Not published | O28: 46266 | P28: 46295 | Q28: 46310 | S28: 19–20 Nov 2026 | T28: 46345 | U28: 46346 | V28: Taras Shevchenko National University of Kyiv, Faculty of Information Technology, 24 B. Havrylyshyna St., Kyiv, Ukraine | W28: Not stated | X28: =IF(O28="","",INT(O28)-TODAY()) -> -3 | Y28: =IF($G28="Finished","Expired",IF(AND(O28<>"",INT(O28)>=TODAY()),IF(INT(O28)-TODAY()<=30,"Open - closing soon","Open"),IF(AND(T28<>"",U28<>"",INT(T28)<=TODAY(),INT(U28)>=TODAY()),"Event in progress",IF(AND(O28="",R28<>"",INT(R28)>=TODAY()),"Registration due",IF(AND(O28="",U28<>"",INT(U28)>=TODAY()),"Deadline not published",IF(AND(O28<>"",Q28<>"",INT(Q28)>=TODAY()),"Camera-ready due",IF(AND(O28<>"",R28<>"",INT(R28)>=TODAY()),"Registration due",IF(AND(U28<>"",INT(U28)>=TODAY()),"Submissions closed - event ahead","Expired")))))))) -> Camera-ready due | Z28: Microsoft CMT (double-blind) | AA28: Full papers 12–15+ pages; short papers 6–11 pages; Springer CCIS Word template, English | AB28: http://iti.fit.univ.kiev.ua/en/home-2/ | AC28: Website; Submission; Facebook | AD28: iti.fit@knu.ua; +380 44 4814407 | AE28: 46269 | AF28: DEADLINE PASSED 3 DAYS AGO. Dates confirmed on the home page: paper submission 01.09.2026, notification 30.09.2026, camera-ready 15.10.2026; event 19-20.11.2026. ADDED the full venue address and the contact block. Submission through Microsoft CMT, double-blind, plagiarism-checked with Unicheck/iThenticate; full papers 12-15+ pages, short papers 6-11 pages, Springer CCIS Word template, English. Proceedings planned for Springer CCIS, indexed in Scopus, SCImago, DBLP and EI-Compendex. XIII edition, four tracks (AI and data science; cybersecurity; mathematical modelling; software engineering), co-organised with Florida State University, Igor Sikorsky KPI, the Glushkov Institute of Cybernetics, the Institute for Information Recording Problems and the Institute of Software Systems of the NAS of Ukraine. No fee published. NOTE the site is reachable only over plain HTTP - its certificate is issued for nuke.knu.ua, so HTTPS fails. | AG28: 44483
A29: 28 | B29: MEMSTECH | C29: 2027 | D29: 20th | E29: IEEE 20th International Conference Perspective Technologies and Methods in MEMS Design | F29: Conference | G29: Mediocre | H29: =IF($G29="High",1,IF($G29="Mediocre",2,3)) -> 2 | I29: IEEE.org | J29: IEEE Xplore Digital Library; Conference Proceedings ISSN 2573-5357; "no-show" papers are not submitted to IEEE Xplore | K29: Not published (the Fees page does not resolve) | P29: 46660 | Q29: 46614 | S29: 13–16 Oct 2027 | T29: 46673 | U29: 46676 | V29: Lviv Polytechnic National University, Lviv, Ukraine | W29: Hybrid (physical at Lviv Polytechnic National University plus virtual participation) | X29: =IF(O29="","",INT(O29)-TODAY()) | Y29: =IF($G29="Finished","Expired",IF(AND(O29<>"",INT(O29)>=TODAY()),IF(INT(O29)-TODAY()<=30,"Open - closing soon","Open"),IF(AND(T29<>"",U29<>"",INT(T29)<=TODAY(),INT(U29)>=TODAY()),"Event in progress",IF(AND(O29="",R29<>"",INT(R29)>=TODAY()),"Registration due",IF(AND(O29="",U29<>"",INT(U29)>=TODAY()),"Deadline not published",IF(AND(O29<>"",Q29<>"",INT(Q29)>=TODAY()),"Camera-ready due",IF(AND(O29<>"",R29<>"",INT(R29)>=TODAY()),"Registration due",IF(AND(U29<>"",INT(U29)>=TODAY()),"Submissions closed - event ahead","Expired")))))))) -> Deadline not published | Z29: Not stated | AA29: Not published; working language English | AB29: https://memstech.ieee.org.ua/ | AC29: Website | AD29: Not published on the site | AE29: 46269 | AF29: LOCATION AND FORMAT CORRECTED - both read "Not stated" before, yet the site's masthead says plainly "Lviv Polytechnic National University, Ukraine, 13 - 16 October, 2027" and the welcome text says "in a hybrid format, combining both physical (Lviv Polytechnic National University, Ukraine) and virtual participation". CAUTION ON THE TWO DATES: the site's own Important dates block lists camera-ready papers on 15.08.2027 BEFORE notification of paper acceptance on 30.09.2027, and publishes no paper-submission deadline at all. That ordering is what the organisers printed, not a transcription slip, but it cannot be right as stated - treat both dates as unreliable and confirm with the organisers. Indexing expanded with the proceedings ISSN and the no-show rule. Still no fee, no submission system and no contact e-mail anywhere on the site; the Fees page does not resolve. 20th edition, organised by the IEEE Ukraine Section with Lviv Polytechnic. | AG29: 44779
A30: 29 | B30: DAO-XAI | C30: 2024 | D30: 4th | E30: Data meets Ontologies in Explainable AI 2024 | F30: Workshop | G30: Finished | H30: =IF($G30="High",1,IF($G30="Mediocre",2,3)) -> 3 | I30: CEUR.org | J30: Not stated | K30: Not published | O30: 45457 | S30: 19 Oct 2024 | T30: 45584 | U30: 45584 | V30: Not stated (an ECAI 2024 workshop) | W30: Not stated | X30: =IF(O30="","",INT(O30)-TODAY()) -> -812 | Y30: =IF($G30="Finished","Expired",IF(AND(O30<>"",INT(O30)>=TODAY()),IF(INT(O30)-TODAY()<=30,"Open - closing soon","Open"),IF(AND(T30<>"",U30<>"",INT(T30)<=TODAY(),INT(U30)>=TODAY()),"Event in progress",IF(AND(O30="",R30<>"",INT(R30)>=TODAY()),"Registration due",IF(AND(O30="",U30<>"",INT(U30)>=TODAY()),"Deadline not published",IF(AND(O30<>"",Q30<>"",INT(Q30)>=TODAY()),"Camera-ready due",IF(AND(O30<>"",R30<>"",INT(R30)>=TODAY()),"Registration due",IF(AND(U30<>"",INT(U30)>=TODAY()),"Submissions closed - event ahead","Expired")))))))) -> Expired | Z30: EasyChair (conf=daoxai2024) | AA30: Not published on the site | AB30: https://sites.google.com/view/daoxai2024 | AC30: Website | AD30: roberto.confalonieri@unipd.it; oliver.kutz@unibz.it | AE30: 46269 | AF30: ARCHIVED. Submission 14.06.2024 and the 19.10.2024 workshop day stand; the site publishes no notification, camera-ready or registration date and no fee, and it never named a venue beyond being an ECAI 2024 workshop. ADDED the two organiser contacts, which were blank. A late second chance existed: authors of papers rejected elsewhere could request consideration by 11.07.2024 through forms.gle/QPav5rHVMCuSMhFZ. Submission through EasyChair (conf=daoxai2024). | AG30: 45723
A31: 30 | B31: DTER | C31: 2024 | D31: 1st | E31: 1st International Workshop on Digital Technologies for Enhancing Resilience | F31: Conference | G31: Finished | H31: =IF($G31="High",1,IF($G31="Mediocre",2,3)) -> 3 | I31: Elsevier | J31: Not stated | K31: 500 EUR (tracker figure, not restated on the site) | L31: 500 | M31: EUR | O31: 45520 | P31: 45543 | Q31: 45562 | S31: 28–30 Oct 2024 | T31: 45593 | U31: 45595 | V31: Leuven, Belgium | W31: Not stated | X31: =IF(O31="","",INT(O31)-TODAY()) -> -749 | Y31: =IF($G31="Finished","Expired",IF(AND(O31<>"",INT(O31)>=TODAY()),IF(INT(O31)-TODAY()<=30,"Open - closing soon","Open"),IF(AND(T31<>"",U31<>"",INT(T31)<=TODAY(),INT(U31)>=TODAY()),"Event in progress",IF(AND(O31="",R31<>"",INT(R31)>=TODAY()),"Registration due",IF(AND(O31="",U31<>"",INT(U31)>=TODAY()),"Deadline not published",IF(AND(O31<>"",Q31<>"",INT(Q31)>=TODAY()),"Camera-ready due",IF(AND(O31<>"",R31<>"",INT(R31)>=TODAY()),"Registration due",IF(AND(U31<>"",INT(U31)>=TODAY()),"Submissions closed - event ahead","Expired")))))))) -> Expired | Z31: Not stated | AA31: Not published on the site | AB31: https://science.lpnu.ua/dter-2024 | AC31: Website | AD31: Not published on the site | AE31: 46269 | AF31: ARCHIVED, ALL DATES CONFIRMED verbatim on the LPNU dates block: 16.08.2024 23:00 papers submission due, 08.09.2024 23:00 authors notifications, 27.09.2024 23:00 camera-ready, 28.10.2024 23:00 opening. Event 28-30.10.2024, Leuven, Belgium. Held in conjunction with a 15th International Conference on Emerging (title truncated on the page). No separate registration deadline was ever published - the fourth date in the block is the opening, not a registration cut-off, so that cell is correctly left empty. No page limit or contact e-mail published. | AG31: 45666
A32: 31 | B32: ATIT | C32: 2024 | D32: 5th | E32: IEEE 5th International Conference on Advanced Trends in Information Theory | F32: Conference | G32: Finished | H32: =IF($G32="High",1,IF($G32="Mediocre",2,3)) -> 3 | I32: IEEE.org | J32: IEEE Xplore Digital Library | K32: Free | L32: 0 | M32: — | O32: 45545 | P32: 45590 | R32: 45595 | S32: 21–23 Nov 2024 | T32: 45617 | U32: 45619 | V32: Ivan Franko National University of Lviv, Lviv, Ukraine | W32: In-person | X32: =IF(O32="","",INT(O32)-TODAY()) -> -724 | Y32: =IF($G32="Finished","Expired",IF(AND(O32<>"",INT(O32)>=TODAY()),IF(INT(O32)-TODAY()<=30,"Open - closing soon","Open"),IF(AND(T32<>"",U32<>"",INT(T32)<=TODAY(),INT(U32)>=TODAY()),"Event in progress",IF(AND(O32="",R32<>"",INT(R32)>=TODAY()),"Registration due",IF(AND(O32="",U32<>"",INT(U32)>=TODAY()),"Deadline not published",IF(AND(O32<>"",Q32<>"",INT(Q32)>=TODAY()),"Camera-ready due",IF(AND(O32<>"",R32<>"",INT(R32)>=TODAY()),"Registration due",IF(AND(U32<>"",INT(U32)>=TODAY()),"Submissions closed - event ahead","Expired")))))))) -> Expired | Z32: Not stated | AA32: Not published on the site | AB32: https://atit.ieee.org.ua/ | AC32: Website | AD32: Not published on the site | AE32: 46269 | AF32: ARCHIVED. TWO FIELDS CORRECTED. VENUE was "Not stated", but the site says the conference "will be held at Ivan Franko National University of Lviv on November 21 - 23, 2024". REGISTRATION DEADLINE ADDED: the dates block gives 30.10.2024 as "Final Registration for Participation". Other dates confirmed: paper submission opened 01.06.2024 and was due 10.09.2024; final acceptance notification 25.10.2024; a further 05.11.2024 milestone appears in the block. IEEE Conference Valid Registration #64324. The site notes the proceedings and review process were placed under quality control with a re-review pending. Free of charge. No camera-ready date, page limit or contact e-mail published. | AG32: 44928
A33: 32 | B33: CSITIC | C33: 2024 | D33: 7th | E33: 7th International Scientific and Technical Conference COMPUTER AND INFORMATIONAL SYSTEMS AND TECHNOLOGIES | F33: Conference | G33: Finished | H33: =IF($G33="High",1,IF($G33="Mediocre",2,3)) -> 3 | I33: Not specified | J33: Journal-style proceedings portal (OJS) | K33: 100 UAH (2024 tracker figure) | L33: 100 | M33: UAH | O33: 45556 | S33: 26 Sep 2024 | T33: 45561 | U33: 45561 | V33: Kharkiv National University of Radio Electronics, Kharkiv, Ukraine | W33: Not stated | X33: =IF(O33="","",INT(O33)-TODAY()) -> -713 | Y33: =IF($G33="Finished","Expired",IF(AND(O33<>"",INT(O33)>=TODAY()),IF(INT(O33)-TODAY()<=30,"Open - closing soon","Open"),IF(AND(T33<>"",U33<>"",INT(T33)<=TODAY(),INT(U33)>=TODAY()),"Event in progress",IF(AND(O33="",R33<>"",INT(R33)>=TODAY()),"Registration due",IF(AND(O33="",U33<>"",INT(U33)>=TODAY()),"Deadline not published",IF(AND(O33<>"",Q33<>"",INT(Q33)>=TODAY()),"Camera-ready due",IF(AND(O33<>"",R33<>"",INT(R33)>=TODAY()),"Registration due",IF(AND(U33<>"",INT(U33)>=TODAY()),"Submissions closed - event ahead","Expired")))))))) -> Expired | Z33: OJS portal | AA33: Not published on the site | AB33: https://csitic.nure.ua/ | AC33: Website | AD33: iryna.perova@nure.ua (Nelia Miroshnichenko) | AE33: 46269 | AF33: ARCHIVED and NO LONGER VERIFIABLE IN FULL: csitic.nure.ua no longer carries the 2024 programme, so the 21.09.2024 submission date and the 26.09.2024 event day could not be re-confirmed from the source and are retained from the earlier pass. ADDED the contact address recovered from the current site. 100 UAH, OJS portal submission, Kharkiv National University of Radio Electronics. Treat the dates as unverified. | AG33: 44281
A34: 33 | B34: BEWARE | C34: 2024 | D34: — | E34: Bias, Risk, Explainability, Ethical AI and the role of Logic and Logic Programming 2024 | F34: Workshop | G34: Finished | H34: =IF($G34="High",1,IF($G34="Mediocre",2,3)) -> 3 | I34: CEUR.org | J34: CEUR-WS Vol-3881 | K34: Not published | O34: 45565 | P34: 45585 | Q34: 45600 | S34: 26 Nov 2024 | T34: 45622 | U34: 45622 | V34: Bolzano, Italy | W34: Not stated | X34: =IF(O34="","",INT(O34)-TODAY()) -> -704 | Y34: =IF($G34="Finished","Expired",IF(AND(O34<>"",INT(O34)>=TODAY()),IF(INT(O34)-TODAY()<=30,"Open - closing soon","Open"),IF(AND(T34<>"",U34<>"",INT(T34)<=TODAY(),INT(U34)>=TODAY()),"Event in progress",IF(AND(O34="",R34<>"",INT(R34)>=TODAY()),"Registration due",IF(AND(O34="",U34<>"",INT(U34)>=TODAY()),"Deadline not published",IF(AND(O34<>"",Q34<>"",INT(Q34)>=TODAY()),"Camera-ready due",IF(AND(O34<>"",R34<>"",INT(R34)>=TODAY()),"Registration due",IF(AND(U34<>"",INT(U34)>=TODAY()),"Submissions closed - event ahead","Expired")))))))) -> Expired | Z34: Not stated | AA34: Not published on the site | AB34: https://sites.google.com/view/beware2024 | AC34: Website | AD34: Not published on the site | AE34: 46269 | AF34: ARCHIVED, ALL DATES CONFIRMED verbatim: "Submission deadline: 30 September 2024", "Notification: 20 October 2024", "Camera-ready: 4 November 2024", "Workshop dates: 26 November 2024". Bolzano, Italy. No registration deadline, fee, page limit or contact address is published on the site. | AG34: 45674
A35: 34 | B35: ADP | C35: 2024 | D35: — | E35: Algorithms of Data Processing 2024 | F35: Not tagged | G35: Finished | H35: =IF($G35="High",1,IF($G35="Mediocre",2,3)) -> 3 | I35: CEUR.org | J35: CEUR-WS Vol-3895 | K35: Free — "Participation is Free of charge" | L35: 0 | M35: — | O35: 45566 | P35: 45575 | Q35: 45585 | R35: 45585 | S35: 05 Nov 2024 | T35: 45601 | U35: 45601 | V35: Kyiv, Ukraine | W35: In-person (virtual option for participants at risk or abroad) | X35: =IF(O35="","",INT(O35)-TODAY()) -> -703 | Y35: =IF($G35="Finished","Expired",IF(AND(O35<>"",INT(O35)>=TODAY()),IF(INT(O35)-TODAY()<=30,"Open - closing soon","Open"),IF(AND(T35<>"",U35<>"",INT(T35)<=TODAY(),INT(U35)>=TODAY()),"Event in progress",IF(AND(O35="",R35<>"",INT(R35)>=TODAY()),"Registration due",IF(AND(O35="",U35<>"",INT(U35)>=TODAY()),"Deadline not published",IF(AND(O35<>"",Q35<>"",INT(Q35)>=TODAY()),"Camera-ready due",IF(AND(O35<>"",R35<>"",INT(R35)>=TODAY()),"Registration due",IF(AND(U35<>"",INT(U35)>=TODAY()),"Submissions closed - event ahead","Expired")))))))) -> Expired | Z35: Not stated | AA35: Not published on the site | AB35: https://ans.kai.edu.ua/adp/ | AC35: Website | AD35: Maksym.Zaliskyi@npp.nau.edu.ua | AE35: 46269 | AF35: ARCHIVED, ALL DATES CONFIRMED: paper submission 01.10.2024, acceptance notification 10.10.2024, revised-paper submission 20.10.2024 (this is the date recorded as camera-ready), registration 20.10.2024, workshop 05.11.2024. ADDED the contact address, which was blank. Free, Kyiv, in-person with a virtual option. No page limit published. | AG35: 45674
A36: 35 | B36: RECI | C36: 2024 | D36: 3rd | E36: The 3rd International Workshop on Reliability Engineering and Computational Intelligence | F36: Conference + Workshop | G36: Finished | H36: =IF($G36="High",1,IF($G36="Mediocre",2,3)) -> 3 | I36: Springer.org | J36: Springer Studies in Computational Intelligence; also the CERES journal | K36: Online participation without any fee; in-person fee not published | L36: 0 | M36: — | N36: 45590 | O36: 45590 | P36: 45595 | Q36: 45688 | R36: 45601 | S36: 06–08 Nov 2024 | T36: 45602 | U36: 45604 | V36: University of Zilina, Zilina, Slovakia | W36: Hybrid | X36: =IF(O36="","",INT(O36)-TODAY()) -> -679 | Y36: =IF($G36="Finished","Expired",IF(AND(O36<>"",INT(O36)>=TODAY()),IF(INT(O36)-TODAY()<=30,"Open - closing soon","Open"),IF(AND(T36<>"",U36<>"",INT(T36)<=TODAY(),INT(U36)>=TODAY()),"Event in progress",IF(AND(O36="",R36<>"",INT(R36)>=TODAY()),"Registration due",IF(AND(O36="",U36<>"",INT(U36)>=TODAY()),"Deadline not published",IF(AND(O36<>"",Q36<>"",INT(Q36)>=TODAY()),"Camera-ready due",IF(AND(O36<>"",R36<>"",INT(R36)>=TODAY()),"Registration due",IF(AND(U36<>"",INT(U36)>=TODAY()),"Submissions closed - event ahead","Expired")))))))) -> Expired | Z36: Not stated | AA36: Not published on the site | AB36: https://reci.fri.uniza.sk/ | AC36: Website; Call for paper | AD36: Not published on the site | AE36: 46269 | AF36: ARCHIVED, ALL DATES CONFIRMED including the unusual one: abstract submission 25.10.2024, notification of acceptance of abstracts 30.10.2024, registration 05.11.2024, workshop 06-08.11.2024, and camera-ready 31.01.2025 - the camera-ready really does fall after the event, because RECI publishes post-proceedings. ONE MILESTONE ADDED to the record: notification of acceptance FOR PUBLICATION on 06.12.2024, between the workshop and the camera-ready date. University of Zilina, Slovakia; free online, 200 EUR in person. No page limit or contact address published. | AG36: 44728
A37: 36 | B37: C&D | C37: 2024 | D37: 4th | E37: 4TH INTERNATIONAL ONLINE CONFERENCE ‘CORPORA AND DISCOURSE’ | F37: Conference | G37: Finished | H37: =IF($G37="High",1,IF($G37="Mediocre",2,3)) -> 3 | I37: Not specified | J37: Short abstracts published in the conference proceedings | K37: Free — "The conference is free to attend, present and publish short abstracts" | L37: 0 | M37: — | N37: 45607 | O37: 45607 | R37: 45607 | S37: 26 Nov 2024 | T37: 45622 | U37: 45622 | V37: Igor Sikorsky Kyiv Polytechnic Institute, Ukraine (online) | W37: Online | X37: =IF(O37="","",INT(O37)-TODAY()) -> -662 | Y37: =IF($G37="Finished","Expired",IF(AND(O37<>"",INT(O37)>=TODAY()),IF(INT(O37)-TODAY()<=30,"Open - closing soon","Open"),IF(AND(T37<>"",U37<>"",INT(T37)<=TODAY(),INT(U37)>=TODAY()),"Event in progress",IF(AND(O37="",R37<>"",INT(R37)>=TODAY()),"Registration due",IF(AND(O37="",U37<>"",INT(U37)>=TODAY()),"Deadline not published",IF(AND(O37<>"",Q37<>"",INT(Q37)>=TODAY()),"Camera-ready due",IF(AND(O37<>"",R37<>"",INT(R37)>=TODAY()),"Registration due",IF(AND(U37<>"",INT(U37)>=TODAY()),"Submissions closed - event ahead","Expired")))))))) -> Expired | Z37: Application form + abstract by e-mail | AA37: Short abstracts in Word | AB37: https://corpora.kamts1.kpi.ua/cad | AC37: Website | AD37: corporadiscourse.kpi@gmail.com | AE37: 46269 | AF37: ARCHIVED. "Final submission: November 11, 2024" confirmed, and it doubles as the registration date; the conference ran online on 26.11.2024 at Igor Sikorsky Kyiv Polytechnic Institute. The site publishes no notification and no camera-ready date, so those cells are correctly empty. Abstracts went by e-mail in Word to corporadiscourse.kpi@gmail.com. No fee published. | AG37: 44731
A38: 37 | B38: WDA | C38: 2025 | D38: — | E38: Workshop on Data Analytics 2025 | F38: Workshop | G38: Finished | H38: =IF($G38="High",1,IF($G38="Mediocre",2,3)) -> 3 | I38: CEUR.org | J38: Not stated | K38: Free — "Participation is Free of charge" | L38: 0 | M38: — | O38: 45621 | P38: 45635 | Q38: 45642 | R38: 45642 | S38: 06 Jan 2025 | T38: 45663 | U38: 45663 | V38: Kyiv, Ukraine | W38: Virtual option offered | X38: =IF(O38="","",INT(O38)-TODAY()) -> -648 | Y38: =IF($G38="Finished","Expired",IF(AND(O38<>"",INT(O38)>=TODAY()),IF(INT(O38)-TODAY()<=30,"Open - closing soon","Open"),IF(AND(T38<>"",U38<>"",INT(T38)<=TODAY(),INT(U38)>=TODAY()),"Event in progress",IF(AND(O38="",R38<>"",INT(R38)>=TODAY()),"Registration due",IF(AND(O38="",U38<>"",INT(U38)>=TODAY()),"Deadline not published",IF(AND(O38<>"",Q38<>"",INT(Q38)>=TODAY()),"Camera-ready due",IF(AND(O38<>"",R38<>"",INT(R38)>=TODAY()),"Registration due",IF(AND(U38<>"",INT(U38)>=TODAY()),"Submissions closed - event ahead","Expired")))))))) -> Expired | Z38: Not stated | AA38: Not published on the site | AB38: https://ans.kai.edu.ua/wda/ | AC38: Website | AD38: vany@kai.edu.ua | AE38: 46269 | AF38: ARCHIVED, ALL DATES CONFIRMED: paper submission 25.11.2024, acceptance notification 09.12.2024, revised-paper submission 16.12.2024 (recorded as camera-ready), registration 16.12.2024, workshop 06.01.2025. ADDED the contact address. Free, Kyiv, virtual option offered. No page limit published. | AG38: 45723
A39: 38 | B39: SAIC | C39: 2025 | D39: — | E39: IEEE International Conference on System Analysis & Intelligent Computing (SAIC) | F39: Conference | G39: Finished | H39: =IF($G39="High",1,IF($G39="Mediocre",2,3)) -> 3 | I39: IEEE.org | J39: IEEE (conference registration pending, application #65508) | K39: 50 UAH... 50 EUR (2025 figure from the tracker, not restated on the site) | L39: 50 | M39: EUR | N39: 45659 | O39: 45659 | S39: Never confirmed | V39: Not stated | W39: Not stated | X39: =IF(O39="","",INT(O39)-TODAY()) -> -610 | Y39: =IF($G39="Finished","Expired",IF(AND(O39<>"",INT(O39)>=TODAY()),IF(INT(O39)-TODAY()<=30,"Open - closing soon","Open"),IF(AND(T39<>"",U39<>"",INT(T39)<=TODAY(),INT(U39)>=TODAY()),"Event in progress",IF(AND(O39="",R39<>"",INT(R39)>=TODAY()),"Registration due",IF(AND(O39="",U39<>"",INT(U39)>=TODAY()),"Deadline not published",IF(AND(O39<>"",Q39<>"",INT(Q39)>=TODAY()),"Camera-ready due",IF(AND(O39<>"",R39<>"",INT(R39)>=TODAY()),"Registration due",IF(AND(U39<>"",INT(U39)>=TODAY()),"Submissions closed - event ahead","Expired")))))))) -> Expired | Z39: Not stated | AA39: Not published on the site | AB39: http://saic.ieee.org.ua/ | AC39: Website | AD39: Not published on the site | AE39: 46269 | AF39: ARCHIVED and NOT PROPERLY VERIFIABLE: saic.ieee.org.ua is still largely an unfilled template. Alongside "Submission Deadline is January 2nd!" (no year) the page carries obvious placeholder copy such as "December 12th at 8pm, ABC Hall", plus a leftover "SAIC Pre-Conference Workshop Schedule (not a conference) 8 - 10 October 2024". No conference dates, venue, notification, camera-ready or registration date were ever published, which is why those cells stay empty and Event Dates reads "Never confirmed". The 50 EUR figure is carried from the earlier tracker. Treat this entry as unconfirmed. | AG39: 44731
A40: 39 | B40: BESD | C40: 2025 | D40: — | E40: International Scientific and Practical Conference Business Ecosystems: Sustainable Development 2025 | F40: Conference | G40: Finished | H40: =IF($G40="High",1,IF($G40="Mediocre",2,3)) -> 3 | I40: Springer.org | J40: Not verified | K40: Free (2025 tracker figure, not verified) | L40: 0 | M40: — | O40: 45677 | S40: 03 Feb 2025 | T40: 45691 | U40: 45691 | V40: Not stated | W40: Not stated | X40: =IF(O40="","",INT(O40)-TODAY()) -> -592 | Y40: =IF($G40="Finished","Expired",IF(AND(O40<>"",INT(O40)>=TODAY()),IF(INT(O40)-TODAY()<=30,"Open - closing soon","Open"),IF(AND(T40<>"",U40<>"",INT(T40)<=TODAY(),INT(U40)>=TODAY()),"Event in progress",IF(AND(O40="",R40<>"",INT(R40)>=TODAY()),"Registration due",IF(AND(O40="",U40<>"",INT(U40)>=TODAY()),"Deadline not published",IF(AND(O40<>"",Q40<>"",INT(Q40)>=TODAY()),"Camera-ready due",IF(AND(O40<>"",R40<>"",INT(R40)>=TODAY()),"Registration due",IF(AND(U40<>"",INT(U40)>=TODAY()),"Submissions closed - event ahead","Expired")))))))) -> Expired | Z40: Not stated | AA40: Not published on the site | AB40: https://be-sd.org/ | AC40: Website | AD40: olena.vasilyeva@gmail.com (coordinator) | AE40: 46269 | AF40: ARCHIVED, but the site has MOVED ON TO A NEW EDITION and no longer describes the 2025 one, so the 20.01.2025 submission date and the 03.02.2025 event day could not be re-confirmed and are retained from the earlier pass. WORTH YOUR ATTENTION: be-sd.org now advertises BESD 2026 on 24-25 September 2026, with submission deadline 10 August 2026 (already past) and acceptance notification 25 August 2026, followed by staged milestones on 1-10 September, 11-15 September, 1-15 October, 15-25 October and 31 October 2026. Consider adding it as its own row. ADDED the coordinator contact. | AG40: 45713
A41: 40 | B41: ICSF | C41: 2025 | D41: 6th | E41: The 6th International Conference on Sustainable Futures: Environmental, Technological, Social and Economic Matters | F41: Conference | G41: Finished | H41: =IF($G41="High",1,IF($G41="Mediocre",2,3)) -> 3 | I41: IOP Publishing | J41: Publisher APC applies to accepted and declined articles alike | K41: Free for corresponding authors based in or affiliated with Ukrainian institutions; 60 EUR otherwise (presentation & publication); audience free | L41: 0 | M41: — | O41: 45688 | P41: 45748 | Q41: 45778 | R41: 45788 | S41: 21–23 May 2025 (workshop day 20 May) | T41: 45798 | U41: 45800 | V41: Kryvyi Rih, Ukraine | W41: Not stated | X41: =IF(O41="","",INT(O41)-TODAY()) -> -581 | Y41: =IF($G41="Finished","Expired",IF(AND(O41<>"",INT(O41)>=TODAY()),IF(INT(O41)-TODAY()<=30,"Open - closing soon","Open"),IF(AND(T41<>"",U41<>"",INT(T41)<=TODAY(),INT(U41)>=TODAY()),"Event in progress",IF(AND(O41="",R41<>"",INT(R41)>=TODAY()),"Registration due",IF(AND(O41="",U41<>"",INT(U41)>=TODAY()),"Deadline not published",IF(AND(O41<>"",Q41<>"",INT(Q41)>=TODAY()),"Camera-ready due",IF(AND(O41<>"",R41<>"",INT(R41)>=TODAY()),"Registration due",IF(AND(U41<>"",INT(U41)>=TODAY()),"Submissions closed - event ahead","Expired")))))))) -> Expired | Z41: Morressier (morressier.com/call-for-papers/6501c5b1cd3f7d001924450d) - the page labels the link "HotCRP" | AA41: Full original research papers, 6+ pages | AB41: https://icsf.easyscience.education/2025/ | AC41: Website | AD41: ak24avo@gmail.com, +380979157215 (Volodymyr Artemchuk); semerikov@gmail.com (Serhiy Semerikov); bondarenko.olga@kdpu.edu.ua, +380676053756; iasei@easyscience.education, +380661083907; s.v.klimov@nuwm.edu.ua, +380980539790; budfac@gmail.com, +380672694385 | AE41: 46269 | AF41: ARCHIVED, ALL DATES CONFIRMED: submission 31.01.2025, notification 01.04.2025, camera-ready 01.05.2025, registration 11.05.2025; event 21-23.05.2025 with a workshop day on 20.05.2025, Kryvyi Rih. SUBMISSION SYSTEM CORRECTED: the page calls the link "HotCRP" but it actually points at Morressier (morressier.com/call-for-papers/6501c5b1cd3f7d001924450d). ADDED the six-strong organiser contact list, which was blank. Fee refined by the source: free for corresponding authors in Ukraine or at a Ukrainian institution, 60 EUR otherwise (presentation and publication). Published by IOP Publishing. | AG41: 43978
A42: 41 | B42: DECaT | C42: 2025 | D42: — | E42: Digital Economy Concepts and Technologies Workshop | F42: Workshop | G42: Finished | H42: =IF($G42="High",1,IF($G42="Mediocre",2,3)) -> 3 | I42: CEUR.org | J42: Not stated | K42: Free — "Registration fee: free" | L42: 0 | M42: — | O42: 45724 | P42: 45731 | Q42: 45738 | S42: 04 Apr 2025 | T42: 45751 | U42: 45751 | V42: Not stated | W42: Not stated | X42: =IF(O42="","",INT(O42)-TODAY()) -> -545 | Y42: =IF($G42="Finished","Expired",IF(AND(O42<>"",INT(O42)>=TODAY()),IF(INT(O42)-TODAY()<=30,"Open - closing soon","Open"),IF(AND(T42<>"",U42<>"",INT(T42)<=TODAY(),INT(U42)>=TODAY()),"Event in progress",IF(AND(O42="",R42<>"",INT(R42)>=TODAY()),"Registration due",IF(AND(O42="",U42<>"",INT(U42)>=TODAY()),"Deadline not published",IF(AND(O42<>"",Q42<>"",INT(Q42)>=TODAY()),"Camera-ready due",IF(AND(O42<>"",R42<>"",INT(R42)>=TODAY()),"Registration due",IF(AND(U42<>"",INT(U42)>=TODAY()),"Submissions closed - event ahead","Expired")))))))) -> Expired | Z42: Not stated | AA42: Short papers 5–9 CEUR-WS pages; regular papers at least 10 pages | AB42: https://decat.eae.com.ua/ | AC42: Website | AD42: decat@kubg.edu.ua | AE42: 46269 | AF42: ARCHIVED, ALL DATES CONFIRMED verbatim: "Paper submission deadline: March 8, 2025", "Notification of acceptance: March 15, 2025", "Camera-ready submission: March 22, 2025"; workshop 04.04.2025. ADDED the contact address. Free. The site also shows the previous edition's volume, CEUR-WS Vol. 3665 of 04.04.2024. No registration deadline is published. | AG42: 45609
A43: 42 | B43: IntSol | C43: 2025 | D43: IV | E43: IV International Scientific Symposium “Intelligent Solutions” | F43: Workshop | G43: Finished | H43: =IF($G43="High",1,IF($G43="Mediocre",2,3)) -> 3 | I43: CEUR.org | J43: CEUR-WS, ISSN 1613-0073 | K43: Not published (a Terms & Fees page is linked) | O43: 45748 | P43: 45757 | Q43: 45762 | S43: 01–05 May 2025 | T43: 45778 | U43: 45782 | V43: Not stated | W43: Not stated | X43: =IF(O43="","",INT(O43)-TODAY()) -> -521 | Y43: =IF($G43="Finished","Expired",IF(AND(O43<>"",INT(O43)>=TODAY()),IF(INT(O43)-TODAY()<=30,"Open - closing soon","Open"),IF(AND(T43<>"",U43<>"",INT(T43)<=TODAY(),INT(U43)>=TODAY()),"Event in progress",IF(AND(O43="",R43<>"",INT(R43)>=TODAY()),"Registration due",IF(AND(O43="",U43<>"",INT(U43)>=TODAY()),"Deadline not published",IF(AND(O43<>"",Q43<>"",INT(Q43)>=TODAY()),"Camera-ready due",IF(AND(O43<>"",R43<>"",INT(R43)>=TODAY()),"Registration due",IF(AND(U43<>"",INT(U43)>=TODAY()),"Submissions closed - event ahead","Expired")))))))) -> Expired | Z43: Not stated | AA43: Not published on the site | AB43: https://intsol.knu.ua/ | AC43: Website | AD43: Not published on the site | AE43: 46269 | AF43: ARCHIVED, ALL DATES CONFIRMED: "Paper Submission deadline: 01 April 2025", "Notification of acceptance: 10 April 2025", "Notification for camera-ready: 15 April 2025". The event dates 01-05.05.2025 are corroborated independently by CEUR Vol-4035, which places the co-located IWSCI workshop at "Kyiv-Uzhhorod, Ukraine, May 01-05, 2025" and names the parent as the IV International Scientific Symposium "Intelligent Solutions". No registration deadline, page limit, fee or contact address is published on the site. | AG43: 44732
A44: 43 | B44: AREdu | C44: 2025 | D44: 8th | E44: The 8th International Workshop on Augmented Reality in Education | F44: Workshop | G44: Finished | H44: =IF($G44="High",1,IF($G44="Mediocre",2,3)) -> 3 | I44: CEUR.org | J44: CEUR-WS Vol-4060 | K44: Not published | O44: 45757 | P44: 45783 | Q44: 45797 | R44: 45787 | S44: 13 May 2025 | T44: 45790 | U44: 45790 | V44: Kryvyi Rih, Ukraine | W44: Not stated | X44: =IF(O44="","",INT(O44)-TODAY()) -> -512 | Y44: =IF($G44="Finished","Expired",IF(AND(O44<>"",INT(O44)>=TODAY()),IF(INT(O44)-TODAY()<=30,"Open - closing soon","Open"),IF(AND(T44<>"",U44<>"",INT(T44)<=TODAY(),INT(U44)>=TODAY()),"Event in progress",IF(AND(O44="",R44<>"",INT(R44)>=TODAY()),"Registration due",IF(AND(O44="",U44<>"",INT(U44)>=TODAY()),"Deadline not published",IF(AND(O44<>"",Q44<>"",INT(Q44)>=TODAY()),"Camera-ready due",IF(AND(O44<>"",R44<>"",INT(R44)>=TODAY()),"Registration due",IF(AND(U44<>"",INT(U44)>=TODAY()),"Submissions closed - event ahead","Expired")))))))) -> Expired | Z44: HotCRP | AA44: Full papers, at least 10 pages, one-column CEURART style | AB44: https://aredu.easyscience.education/aredu2025/ | AC44: Website | AD44: andrey.n.stryuk@gmail.com, +380-68-9030013 (Andrii Striuk) | AE44: 46269 | AF44: ARCHIVED. Submission 10.04.2025, notification 06.05.2025, registration 10.05.2025, camera-ready 20.05.2025 and the 13.05.2025 workshop day are retained; the current page confirms the organiser contact but no longer displays the dates block. ADDED the contact, which was blank. 8th edition, Kryvyi Rih, HotCRP submission, CEUR proceedings. No fee published. | AG44: 45674
A45: 44 | B45: UkrPROG | C45: 2025 | D45: 15th | E45: The 15th International Scientific and Practical Conference on Programming | F45: Conference | G45: Finished | H45: =IF($G45="High",1,IF($G45="Mediocre",2,3)) -> 3 | I45: CEUR.org | J45: Not verified | K45: 900 UAH + 100 UAH per page beyond 9 pages (2025 tracker figure, not verified) | L45: 900 | M45: UAH | O45: 45758 | S45: 13-14 May 2025 | T45: 45790 | U45: 45791 | V45: Institute of Software Systems, NAS of Ukraine, Kyiv | W45: Not stated | X45: =IF(O45="","",INT(O45)-TODAY()) -> -511 | Y45: =IF($G45="Finished","Expired",IF(AND(O45<>"",INT(O45)>=TODAY()),IF(INT(O45)-TODAY()<=30,"Open - closing soon","Open"),IF(AND(T45<>"",U45<>"",INT(T45)<=TODAY(),INT(U45)>=TODAY()),"Event in progress",IF(AND(O45="",R45<>"",INT(R45)>=TODAY()),"Registration due",IF(AND(O45="",U45<>"",INT(U45)>=TODAY()),"Deadline not published",IF(AND(O45<>"",Q45<>"",INT(Q45)>=TODAY()),"Camera-ready due",IF(AND(O45<>"",R45<>"",INT(R45)>=TODAY()),"Registration due",IF(AND(U45<>"",INT(U45)>=TODAY()),"Submissions closed - event ahead","Expired")))))))) -> Expired | Z45: Not stated | AA45: Not published on the site | AB45: https://iss.nas.gov.ua/ | AC45: Website | AD45: iss@isofts.kiev.ua | AE45: 46269 | AF45: ARCHIVED. EVENT DATES CORRECTED from a single day to 13-14.05.2025: CEUR Vol-4049 records its co-located workshop as "at the 15th International Scientific and Practical Programming Conference (UkrPROG 2025), Kyiv, Ukraine, May 13-14, 2025", so the conference itself ran two days. ADDED the institute contact. NOTE the recorded URL is the Institute of Software Systems' general events page, not a stable conference page - it now lists 2026 dates (29.05, 16.06, 03.07, 04.07, 20.07.2026), so the 11.04.2025 submission date could not be re-confirmed from the source. Fee 900 UAH plus 100 UAH per page beyond 9. No notification or camera-ready date was ever published. | AG45: 44732
A46: 45 | B46: CMSE | C46: 2025 | D46: — | E46: Computational Methods in Systems Engineering | F46: Workshop | G46: Finished | H46: =IF($G46="High",1,IF($G46="Mediocre",2,3)) -> 3 | I46: CEUR.org | J46: Not stated | K46: Free | L46: 0 | M46: — | O46: 45761 | P46: 45782 | Q46: 45796 | R46: 45803 | S46: 12 Jun 2025 | T46: 45820 | U46: 45820 | V46: Kyiv, Ukraine | W46: In-person | X46: =IF(O46="","",INT(O46)-TODAY()) -> -508 | Y46: =IF($G46="Finished","Expired",IF(AND(O46<>"",INT(O46)>=TODAY()),IF(INT(O46)-TODAY()<=30,"Open - closing soon","Open"),IF(AND(T46<>"",U46<>"",INT(T46)<=TODAY(),INT(U46)>=TODAY()),"Event in progress",IF(AND(O46="",R46<>"",INT(R46)>=TODAY()),"Registration due",IF(AND(O46="",U46<>"",INT(U46)>=TODAY()),"Deadline not published",IF(AND(O46<>"",Q46<>"",INT(Q46)>=TODAY()),"Camera-ready due",IF(AND(O46<>"",R46<>"",INT(R46)>=TODAY()),"Registration due",IF(AND(U46<>"",INT(U46)>=TODAY()),"Submissions closed - event ahead","Expired")))))))) -> Expired | Z46: Not stated | AA46: Not published on the site | AB46: https://ans.kai.edu.ua/cmse/ | AC46: Website | AD46: volianskyi.roman@lll.kpi.ua | AE46: 46269 | AF46: ARCHIVED, ALL DATES CONFIRMED: paper submission 14.04.2025, acceptance notification 05.05.2025, revised-paper submission 19.05.2025 (recorded as camera-ready), registration 26.05.2025, workshop 12.06.2025. ADDED the contact address. Free, Kyiv, in-person. Note the acronym-year: the tracker previously carried this as CMSE 2024 with a June 2024 event; the site's own schedule is the 2025 one now recorded. No page limit published. | AG46: 45608
A47: 46 | B47: ISDMCI | C47: 2025 | D47: — | E47: Intellectual Decision-Making Systems and Problems of Computational Intelligence - International Scientific Conference | F47: Conference | G47: Finished | H47: =IF($G47="High",1,IF($G47="Mediocre",2,3)) -> 3 | I47: Springer.org | J47: Springer Lecture Notes in Data Engineering, Computational Intelligence and Decision-Making | K47: 20 EUR (2025 tracker figure, not verified) | L47: 20 | M47: EUR | O47: 45777 | Q47: 45827 | S47: Not published | V47: Not stated | W47: Not stated | X47: =IF(O47="","",INT(O47)-TODAY()) -> -492 | Y47: =IF($G47="Finished","Expired",IF(AND(O47<>"",INT(O47)>=TODAY()),IF(INT(O47)-TODAY()<=30,"Open - closing soon","Open"),IF(AND(T47<>"",U47<>"",INT(T47)<=TODAY(),INT(U47)>=TODAY()),"Event in progress",IF(AND(O47="",R47<>"",INT(R47)>=TODAY()),"Registration due",IF(AND(O47="",U47<>"",INT(U47)>=TODAY()),"Deadline not published",IF(AND(O47<>"",Q47<>"",INT(Q47)>=TODAY()),"Camera-ready due",IF(AND(O47<>"",R47<>"",INT(R47)>=TODAY()),"Registration due",IF(AND(U47<>"",INT(U47)>=TODAY()),"Submissions closed - event ahead","Expired")))))))) -> Expired | Z47: Not stated | AA47: Not published on the site | AB47: https://www.isdmci.ks.ua/ | AC47: Website; Publication | AD47: Not published on the site | AE47: 46269 | AF47: ARCHIVED and NOT VERIFIABLE: https://www.isdmci.ks.ua/ returns HTTP 404 and the bare domain isdmci.ks.ua 404s as well, so the site is gone. The 30.04.2025 submission date, the 19.06.2025 camera-ready date, the 20 EUR fee and the Springer route are all retained from the earlier pass and could not be re-checked on 04.09.2026. Event dates were never published. Treat the whole entry as unverified. | AG47: 44256
A48: 47 | B48: AEQUITAS | C48: 2025 | D48: 3rd | E48: Fairness and Bias in AI | F48: Workshop | G48: Finished | H48: =IF($G48="High",1,IF($G48="Mediocre",2,3)) -> 3 | I48: CEUR.org | J48: Not stated | K48: Not published | O48: 45834 | P48: 45858 | Q48: 45908 | S48: 25–30 Oct 2025 (within ECAI 2025) | T48: 45955 | U48: 45960 | V48: Bologna, Italy | W48: Not stated | X48: =IF(O48="","",INT(O48)-TODAY()) -> -435 | Y48: =IF($G48="Finished","Expired",IF(AND(O48<>"",INT(O48)>=TODAY()),IF(INT(O48)-TODAY()<=30,"Open - closing soon","Open"),IF(AND(T48<>"",U48<>"",INT(T48)<=TODAY(),INT(U48)>=TODAY()),"Event in progress",IF(AND(O48="",R48<>"",INT(R48)>=TODAY()),"Registration due",IF(AND(O48="",U48<>"",INT(U48)>=TODAY()),"Deadline not published",IF(AND(O48<>"",Q48<>"",INT(Q48)>=TODAY()),"Camera-ready due",IF(AND(O48<>"",R48<>"",INT(R48)>=TODAY()),"Registration due",IF(AND(U48<>"",INT(U48)>=TODAY()),"Submissions closed - event ahead","Expired")))))))) -> Expired | Z48: Not stated | AA48: Not published on the site | AB48: https://aequitas-aod.github.io/aequitas-ecai25.github.io/dates.html | AC48: Website | AD48: Not published on the site | AE48: 46269 | AF48: ARCHIVED. Dates confirmed with one caveat: submission 15.05.2025 extended to 26.06.2025, notification 20.07.2025, and camera-ready 08.09.2025 - but the source page actually prints "Camera-Ready submission: September 8th, 2024", a year typo by the organisers, since the workshop ran in October 2025. The 2025 reading recorded here is the only coherent one. Event 25-30.10.2025 within ECAI 2025, Bologna. No registration deadline, fee, page limit or contact address published. | AG48: 45723
A49: 48 | B49: CSDP | C49: 2025 | D49: — | E49: Cyber Security and Data Protection 2024 | F49: Workshop | G49: Finished | H49: =IF($G49="High",1,IF($G49="Mediocre",2,3)) -> 3 | I49: CEUR.org | J49: Not verified | K49: Free (2025 tracker figure, not verified) | L49: 0 | M49: — | O49: 45858 | S49: 31 Jul 2025 | T49: 45869 | U49: 45869 | V49: Lviv Polytechnic National University, Ukraine | W49: Not stated | X49: =IF(O49="","",INT(O49)-TODAY()) -> -411 | Y49: =IF($G49="Finished","Expired",IF(AND(O49<>"",INT(O49)>=TODAY()),IF(INT(O49)-TODAY()<=30,"Open - closing soon","Open"),IF(AND(T49<>"",U49<>"",INT(T49)<=TODAY(),INT(U49)>=TODAY()),"Event in progress",IF(AND(O49="",R49<>"",INT(R49)>=TODAY()),"Registration due",IF(AND(O49="",U49<>"",INT(U49)>=TODAY()),"Deadline not published",IF(AND(O49<>"",Q49<>"",INT(Q49)>=TODAY()),"Camera-ready due",IF(AND(O49<>"",R49<>"",INT(R49)>=TODAY()),"Registration due",IF(AND(U49<>"",INT(U49)>=TODAY()),"Submissions closed - event ahead","Expired")))))))) -> Expired | Z49: Not stated | AA49: Not published on the site | AB49: https://csdp.lpnu.ua/ | AC49: Website | AD49: Not published on the site | AE49: 46269 | AF49: ARCHIVED and NOT VERIFIABLE: https://csdp.lpnu.ua/ returns HTTP 522 (the origin server is down), so nothing could be re-read on 04.09.2026. The 20.07.2025 submission date, the 31.07.2025 event day, the free-participation note and the CEUR route are retained from the earlier pass; no notification, camera-ready or registration date was ever recorded. Treat the entry as unverified. | AG49: 45608
A50: 49 | B50: ArgXAI | C50: 2025 | D50: — | E50: Argumentation for eXplainable AI 2025 | F50: Workshop | G50: Finished | H50: =IF($G50="High",1,IF($G50="Mediocre",2,3)) -> 3 | I50: CEUR.org | J50: CEUR-WS (proceedings online) | K50: Not published | O50: 45860 | P50: 45910 | Q50: 45931 | S50: 26 Oct 2025 | T50: 45956 | U50: 45956 | V50: Bologna, Italy | W50: Not stated | X50: =IF(O50="","",INT(O50)-TODAY()) -> -409 | Y50: =IF($G50="Finished","Expired",IF(AND(O50<>"",INT(O50)>=TODAY()),IF(INT(O50)-TODAY()<=30,"Open - closing soon","Open"),IF(AND(T50<>"",U50<>"",INT(T50)<=TODAY(),INT(U50)>=TODAY()),"Event in progress",IF(AND(O50="",R50<>"",INT(R50)>=TODAY()),"Registration due",IF(AND(O50="",U50<>"",INT(U50)>=TODAY()),"Deadline not published",IF(AND(O50<>"",Q50<>"",INT(Q50)>=TODAY()),"Camera-ready due",IF(AND(O50<>"",R50<>"",INT(R50)>=TODAY()),"Registration due",IF(AND(U50<>"",INT(U50)>=TODAY()),"Submissions closed - event ahead","Expired")))))))) -> Expired | Z50: Not stated | AA50: CEUR-WS template | AB50: https://people.cs.umu.se/tkampik/argxai/2025.html | AC50: Website | AD50: Not published on the site | AE50: 46269 | AF50: ARCHIVED, ALL DATES CONFIRMED: "Paper submission deadline: 15 July 2025 22 July 2025 (AoE)" - extended to 22.07.2025 - notification 10.09.2025, camera-ready 01.10.2025. The workshop day 26.10.2025 sits inside ECAI 2025 in Bologna; note the page prints the ECAI window as "25-20 October 2025", a typo for 25-30 October. No registration deadline, fee or published contact (the only address on the page, argxai24@easychair.org, is inside an HTML comment and carries the 2024 year, so it is not recorded here). | AG50: 45723
A51: 50 | B51: DigiTransfEd | C51: 2025 | D51: 4th | E51: 4th Workshop on Digital Transformation of Education | F51: Workshop | G51: Finished | H51: =IF($G51="High",1,IF($G51="Mediocre",2,3)) -> 3 | I51: CEUR.org | J51: CEUR-WS Vol-4096 | K51: Free | L51: 0 | M51: — | O51: 45869 | P51: 45899 | Q51: 45914 | R51: 45918 | S51: 24 Sep 2025 | T51: 45924 | U51: 45924 | V51: Kyiv, Ukraine | W51: Not stated | X51: =IF(O51="","",INT(O51)-TODAY()) -> -400 | Y51: =IF($G51="Finished","Expired",IF(AND(O51<>"",INT(O51)>=TODAY()),IF(INT(O51)-TODAY()<=30,"Open - closing soon","Open"),IF(AND(T51<>"",U51<>"",INT(T51)<=TODAY(),INT(U51)>=TODAY()),"Event in progress",IF(AND(O51="",R51<>"",INT(R51)>=TODAY()),"Registration due",IF(AND(O51="",U51<>"",INT(U51)>=TODAY()),"Deadline not published",IF(AND(O51<>"",Q51<>"",INT(Q51)>=TODAY()),"Camera-ready due",IF(AND(O51<>"",R51<>"",INT(R51)>=TODAY()),"Registration due",IF(AND(U51<>"",INT(U51)>=TODAY()),"Submissions closed - event ahead","Expired")))))))) -> Expired | Z51: Microsoft CMT | AA51: Full papers, at least 6 pages | AB51: https://digitransfed.ztu.edu.ua/ | AC51: Website | AD51: tetianavakaliuk@acnsci.org, +380-96-065-3099 (Tetiana Vakaliuk) | AE51: 46269 | AF51: ARCHIVED. Submission 31.07.2025, notification 30.08.2025, camera-ready 14.09.2025, registration 18.09.2025 and the 24.09.2025 workshop day are retained; the current page confirms the organiser contact but no longer shows the dates block. ADDED the contact, which was blank. Microsoft CMT submission, CEUR proceedings, free. | AG51: 45609
A52: 51 | B52: SCIA-SKID | C52: 2025 | D52: 4th | E52: 4th International Workshop on Social Communication and Information Activity in Digital Humanities 2025 | F52: Workshop | G52: Finished | H52: =IF($G52="High",1,IF($G52="Mediocre",2,3)) -> 3 | I52: CEUR.org | J52: CEUR Workshop Proceedings | K52: Free | L52: 0 | M52: — | O52: 45901 | P52: 45944 | Q52: 45951 | S52: 30 Oct 2025 | T52: 45960 | U52: 45960 | V52: Lviv Polytechnic National University (SKID department), Ukraine | W52: Not stated | X52: =IF(O52="","",INT(O52)-TODAY()) -> -368 | Y52: =IF($G52="Finished","Expired",IF(AND(O52<>"",INT(O52)>=TODAY()),IF(INT(O52)-TODAY()<=30,"Open - closing soon","Open"),IF(AND(T52<>"",U52<>"",INT(T52)<=TODAY(),INT(U52)>=TODAY()),"Event in progress",IF(AND(O52="",R52<>"",INT(R52)>=TODAY()),"Registration due",IF(AND(O52="",U52<>"",INT(U52)>=TODAY()),"Deadline not published",IF(AND(O52<>"",Q52<>"",INT(Q52)>=TODAY()),"Camera-ready due",IF(AND(O52<>"",R52<>"",INT(R52)>=TODAY()),"Registration due",IF(AND(U52<>"",INT(U52)>=TODAY()),"Submissions closed - event ahead","Expired")))))))) -> Expired | Z52: Not stated | AA52: Not published on the site | AB52: https://skid.lpnu.ua/?page_id=220 | AC52: Website | AD52: Via the SKID department, Lviv Polytechnic National University (no e-mail published on the workshop page) | AE52: 46269 | AF52: ARCHIVED, ALL DATES CONFIRMED verbatim on the SKID page: "01.09.2025 - Paper submission deadline", "14.10.2025 - Notification of acceptance", "21.10.2025 - Camera ready submission deadline". The event day is corroborated by CEUR Vol-4107: "Proceedings of the 4th International Workshop on Social Communication and Information Activity in Digital Humanities (SCIA 2025), Lviv, Ukraine, October 30, 2025", edited by Pavlo Zhezhnych, Oleksandr Markovets, Alina Petrushka and Sergiy Gn... Free. No registration deadline or page limit published. | AG52: 45609
A53: 52 | B53: CIAW | C53: 2025 | D53: — | E53: Computational Intelligence Application Workshop | F53: Workshop | G53: Finished | H53: =IF($G53="High",1,IF($G53="Mediocre",2,3)) -> 3 | I53: CEUR.org | J53: CEUR-WS Vol-4110 (published 30.11.2025); DBLP, Scopus, Google Scholar | K53: Free | L53: 0 | M53: — | O53: 45910 | P53: 45915 | S53: 26-27 Sep 2025 (inside CISS-2025, 25-27 Sep) | T53: 45926 | U53: 45927 | V53: Lviv Polytechnic National University, Lviv, Ukraine | W53: Mixed (online/offline) | X53: =IF(O53="","",INT(O53)-TODAY()) -> -359 | Y53: =IF($G53="Finished","Expired",IF(AND(O53<>"",INT(O53)>=TODAY()),IF(INT(O53)-TODAY()<=30,"Open - closing soon","Open"),IF(AND(T53<>"",U53<>"",INT(T53)<=TODAY(),INT(U53)>=TODAY()),"Event in progress",IF(AND(O53="",R53<>"",INT(R53)>=TODAY()),"Registration due",IF(AND(O53="",U53<>"",INT(U53)>=TODAY()),"Deadline not published",IF(AND(O53<>"",Q53<>"",INT(Q53)>=TODAY()),"Camera-ready due",IF(AND(O53<>"",R53<>"",INT(R53)>=TODAY()),"Registration due",IF(AND(U53<>"",INT(U53)>=TODAY()),"Submissions closed - event ahead","Expired")))))))) -> Expired | Z53: E-mail to cissconference@lpnu.ua | AA53: CEURART style, LaTeX or ODT template | AB53: https://science.lpnu.ua/ciss-2025/workshop-ciaw-2025 | AC53: Website; CEUR volume (ceur-ws.org/Vol-4110/) | AD53: cissconference@lpnu.ua | AE53: 46269 | AF53: ARCHIVED. EVENT DATES CORRECTED from 25-27 to 26-27.09.2025: CEUR Vol-4110 records the workshop itself as "Lviv, Ukraine, September 26-27, 2025", edited by Vasyl Teslyuk, Natalia Kryvinska, Aneta Poniszewska-Maranda, Vasyl Lytvyn and Lyubomyr Chyrun. The parent conference CISS-2025 ran the full 25-27.09.2025. THE VOLUME IS PUBLISHED and now recorded: ceur-ws.org/Vol-4110/. Submission 10.09.2025 and notification 15.09.2025 follow the CISS-2025 dates block. ADDED the submission e-mail cissconference@lpnu.ua. CEURART style mandatory (LaTeX CEURART or LibreOffice ODT); papers must be computer-science related, with no footnotes or page numbers. Free, mixed online/offline. | AG53: 45656
A54: 53 | B54: CISS | C54: 2025 | D54: II | E54: II International Scientific and Practical Conference “Computational Intelligence and Smart Systems” | F54: Conference + Workshop | G54: Finished | H54: =IF($G54="High",1,IF($G54="Mediocre",2,3)) -> 3 | I54: CEUR.org | J54: Not stated | K54: Free | L54: 0 | M54: — | O54: 45910 | P54: 45915 | S54: 25–27 Sep 2025 | T54: 45925 | U54: 45927 | V54: Lviv Polytechnic National University, Lviv, Ukraine | W54: Mixed (online/offline) | X54: =IF(O54="","",INT(O54)-TODAY()) -> -359 | Y54: =IF($G54="Finished","Expired",IF(AND(O54<>"",INT(O54)>=TODAY()),IF(INT(O54)-TODAY()<=30,"Open - closing soon","Open"),IF(AND(T54<>"",U54<>"",INT(T54)<=TODAY(),INT(U54)>=TODAY()),"Event in progress",IF(AND(O54="",R54<>"",INT(R54)>=TODAY()),"Registration due",IF(AND(O54="",U54<>"",INT(U54)>=TODAY()),"Deadline not published",IF(AND(O54<>"",Q54<>"",INT(Q54)>=TODAY()),"Camera-ready due",IF(AND(O54<>"",R54<>"",INT(R54)>=TODAY()),"Registration due",IF(AND(U54<>"",INT(U54)>=TODAY()),"Submissions closed - event ahead","Expired")))))))) -> Expired | Z54: Not stated | AA54: CEURART style mandatory - LaTeX CEURART or the LibreOffice ODT template; the topic must be directly related to computer science, information systems or information technology; no footnotes and no page numbers; high-quality graphics | AB54: https://science.lpnu.ua/ciss-2025 | AC54: Website | AD54: cissconference@lpnu.ua | AE54: 46269 | AF54: ARCHIVED, ALL DATES CONFIRMED verbatim on the LPNU dates block: 10.09.2025 23:00 paper submission deadline, 15.09.2025 23:00 notification of acceptance, 25.09.2025 10:00 opening; event 25-27.09.2025 at Lviv Polytechnic. The site styles it the "2nd International Scientific and Practical Conference Computational Intelligence and Smart Systems CISS-2025". ADDED the submission e-mail and the CEURART formatting requirements, both blank before. Free, mixed online/offline. No camera-ready or registration date was published. Its CIAW-2025 workshop volume is CEUR Vol-4110; no separate CISS volume was found on CEUR. | AG54: 45666
A55: 54 | B55: SECS | C55: 2025 | D55: 4th | E55: 4th International Conference "Challenges and Reality of the IT-space: Software Engineering and Cybersecurity" | F55: Journal | G55: Finished | H55: =IF($G55="High",1,IF($G55="Mediocre",2,3)) -> 3 | I55: Academic Journal | J55: Not stated | K55: Free | L55: 0 | M55: — | O55: 45915 | P55: 45930 | S55: 23–24 Oct 2025 | T55: 45953 | U55: 45954 | V55: Kyiv, Ukraine (online) | W55: Online | X55: =IF(O55="","",INT(O55)-TODAY()) -> -354 | Y55: =IF($G55="Finished","Expired",IF(AND(O55<>"",INT(O55)>=TODAY()),IF(INT(O55)-TODAY()<=30,"Open - closing soon","Open"),IF(AND(T55<>"",U55<>"",INT(T55)<=TODAY(),INT(U55)>=TODAY()),"Event in progress",IF(AND(O55="",R55<>"",INT(R55)>=TODAY()),"Registration due",IF(AND(O55="",U55<>"",INT(U55)>=TODAY()),"Deadline not published",IF(AND(O55<>"",Q55<>"",INT(Q55)>=TODAY()),"Camera-ready due",IF(AND(O55<>"",R55<>"",INT(R55)>=TODAY()),"Registration due",IF(AND(U55<>"",INT(U55)>=TODAY()),"Submissions closed - event ahead","Expired")))))))) -> Expired | Z55: Microsoft CMT (SECS2025) | AA55: Conference paper template provided | AB55: https://secs.knute.edu.ua//2025/index.html | AC55: Website; CMT | AD55: conf_SECS@knute.edu.ua | AE55: 46269 | AF55: ARCHIVED. Event dates confirmed verbatim: "(SECS-2025) Thursday, 23 October 2025 - Friday, 24 October 2025". Submission 15.09.2025 and notification 30.09.2025 are retained from the earlier pass; the site publishes no camera-ready or registration date. Free, online, Kyiv; Microsoft CMT (SECS2025); contact conf_SECS@knute.edu.ua. 4th edition. | AG55: 45889
A56: 55 | B56: IDDM | C56: 2025 | D56: 8th | E56: 8th International Conference on Informatics & Data-Driven Medicine | F56: Conference + Workshop | G56: Finished | H56: =IF($G56="High",1,IF($G56="Mediocre",2,3)) -> 3 | I56: CEUR.org | J56: Not stated | K56: Free | L56: 0 | M56: — | O56: 45940 | P56: 45971 | Q56: 45978 | S56: 19–20 Nov 2025 | T56: 45980 | U56: 45981 | V56: Lviv Polytechnic National University, Ukraine; the site banner also names Comenius University Bratislava, Slovakia | W56: Not stated | X56: =IF(O56="","",INT(O56)-TODAY()) -> -329 | Y56: =IF($G56="Finished","Expired",IF(AND(O56<>"",INT(O56)>=TODAY()),IF(INT(O56)-TODAY()<=30,"Open - closing soon","Open"),IF(AND(T56<>"",U56<>"",INT(T56)<=TODAY(),INT(U56)>=TODAY()),"Event in progress",IF(AND(O56="",R56<>"",INT(R56)>=TODAY()),"Registration due",IF(AND(O56="",U56<>"",INT(U56)>=TODAY()),"Deadline not published",IF(AND(O56<>"",Q56<>"",INT(Q56)>=TODAY()),"Camera-ready due",IF(AND(O56<>"",R56<>"",INT(R56)>=TODAY()),"Registration due",IF(AND(U56<>"",INT(U56)>=TODAY()),"Submissions closed - event ahead","Expired")))))))) -> Expired | Z56: Not stated | AA56: CEURART style (LaTeX CEURART.zip or the LibreOffice ODT template) | AB56: https://science.lpnu.ua/iddm-2025 | AC56: Website; Submission | AD56: Not published on the site | AE56: 46269 | AF56: ARCHIVED, ALL DATES CONFIRMED verbatim on the LPNU dates block: 10.10.2025 23:59 paper submission, 10.11.2025 18:00 notification of acceptance, 17.11.2025 10:00 camera-ready, 19.11.2025 10:00 opening; event 19-20.11.2025 at Lviv Polytechnic. The site names it "The 8th International Conference on Informatics & Data-Driven Medicine (IDDM 2025)" and states the proceedings "shall be submitted to CEUR-WS.org for online publication". ADDED the CEURART formatting requirement. Free. No registration deadline or contact e-mail is published, and no IDDM 2025 volume was found on CEUR yet. | AG56: 44402
A57: 56 | B57: CS&SE@SW | C57: 2025 | D57: 8th | E57: 8th Workshop for Young Scientists in Computer Science & Software Engineering | F57: Conference + Workshop | G57: Finished | H57: =IF($G57="High",1,IF($G57="Mediocre",2,3)) -> 3 | I57: CEUR.org | J57: Not stated | K57: Not published | O57: 45942 | P57: 45974 | Q57: 45988 | R57: 45979 | S57: 21 Nov 2025 | T57: 45982 | U57: 45982 | V57: Kryvyi Rih, Ukraine | W57: Not stated | X57: =IF(O57="","",INT(O57)-TODAY()) -> -327 | Y57: =IF($G57="Finished","Expired",IF(AND(O57<>"",INT(O57)>=TODAY()),IF(INT(O57)-TODAY()<=30,"Open - closing soon","Open"),IF(AND(T57<>"",U57<>"",INT(T57)<=TODAY(),INT(U57)>=TODAY()),"Event in progress",IF(AND(O57="",R57<>"",INT(R57)>=TODAY()),"Registration due",IF(AND(O57="",U57<>"",INT(U57)>=TODAY()),"Deadline not published",IF(AND(O57<>"",Q57<>"",INT(Q57)>=TODAY()),"Camera-ready due",IF(AND(O57<>"",R57<>"",INT(R57)>=TODAY()),"Registration due",IF(AND(U57<>"",INT(U57)>=TODAY()),"Submissions closed - event ahead","Expired")))))))) -> Expired | Z57: HotCRP | AA57: Full papers, at least 10 pages | AB57: https://cssesw.easyscience.education/cssesw2025/ | AC57: Website | AD57: andrey.n.stryuk@gmail.com, +380-68-9030013 (Andrii Striuk) | AE57: 46269 | AF57: ARCHIVED. The submission deadline is confirmed verbatim: papers went "through the HotCRP (https://notso.easyscience.education/cssesw/2025/) by October 12, 2025". Notification 13.11.2025, registration 18.11.2025, camera-ready 27.11.2025 and the 21.11.2025 workshop day are retained from the earlier pass; the current page no longer shows that block. ADDED the contact, which was blank. 8th workshop, Kryvyi Rih, CEUR proceedings. No fee published. | AG57: 44402
A58: 57 | B58: AdvAIT | C58: 2025 | D58: 2nd | E58: 2nd International Workshop on Advanced Applied Information Technologies | F58: Conference + Workshop | G58: Finished | H58: =IF($G58="High",1,IF($G58="Mediocre",2,3)) -> 3 | I58: CEUR.org | J58: Scopus & DBLP (planned) | K58: Free — "Participation and publication are free of charge" | L58: 0 | M58: — | O58: 45956 | P58: 45985 | Q58: 45992 | S58: 05 Dec 2025 | T58: 45996 | U58: 45996 | V58: Khmelnytskyi, Ukraine & Zilina, Slovakia | W58: Not stated | X58: =IF(O58="","",INT(O58)-TODAY()) -> -313 | Y58: =IF($G58="Finished","Expired",IF(AND(O58<>"",INT(O58)>=TODAY()),IF(INT(O58)-TODAY()<=30,"Open - closing soon","Open"),IF(AND(T58<>"",U58<>"",INT(T58)<=TODAY(),INT(U58)>=TODAY()),"Event in progress",IF(AND(O58="",R58<>"",INT(R58)>=TODAY()),"Registration due",IF(AND(O58="",U58<>"",INT(U58)>=TODAY()),"Deadline not published",IF(AND(O58<>"",Q58<>"",INT(Q58)>=TODAY()),"Camera-ready due",IF(AND(O58<>"",R58<>"",INT(R58)>=TODAY()),"Registration due",IF(AND(U58<>"",INT(U58)>=TODAY()),"Submissions closed - event ahead","Expired")))))))) -> Expired | Z58: Not stated | AA58: Regular 10–20 or short 5–9 pages, English | AB58: http://kiis.khmnu.edu.ua/advait-2025/ | AC58: Website | AD58: advapplit@gmail.com; pavlovao@khmnu.edu.ua | AE58: 46269 | AF58: ARCHIVED, ALL DATES CONFIRMED verbatim: "Paper submission deadline: October 26, 2025 (the deadline is final, no extension of submission is planned)", "Notification of acceptance: November 24, 2025", "Camera-ready submission deadline: December 1, 2025"; workshop 05.12.2025. ADDED both contact addresses, which were blank. Free, Khmelnytskyi National University with Zilina, Slovakia; CEUR proceedings. No registration deadline published. | AG58: 45548
A59: 58 | B59: ESS | C59: 2026 | D59: 9th | E59: IEEE 9th International Conference on Energy Smart Systems | F59: Conference | G59: Finished | H59: =IF($G59="High",1,IF($G59="Mediocre",2,3)) -> 3 | I59: IEEE.org | J59: IEEE | K59: Not published (a Participation fee and payment details page is linked) | O59: 45991 | P59: 46103 | S59: 21–24 Apr 2026 | T59: 46133 | U59: 46136 | V59: Igor Sikorsky Kyiv Polytechnic Institute, Kyiv, Ukraine | W59: Not stated | X59: =IF(O59="","",INT(O59)-TODAY()) -> -278 | Y59: =IF($G59="Finished","Expired",IF(AND(O59<>"",INT(O59)>=TODAY()),IF(INT(O59)-TODAY()<=30,"Open - closing soon","Open"),IF(AND(T59<>"",U59<>"",INT(T59)<=TODAY(),INT(U59)>=TODAY()),"Event in progress",IF(AND(O59="",R59<>"",INT(R59)>=TODAY()),"Registration due",IF(AND(O59="",U59<>"",INT(U59)>=TODAY()),"Deadline not published",IF(AND(O59<>"",Q59<>"",INT(Q59)>=TODAY()),"Camera-ready due",IF(AND(O59<>"",R59<>"",INT(R59)>=TODAY()),"Registration due",IF(AND(U59<>"",INT(U59)>=TODAY()),"Submissions closed - event ahead","Expired")))))))) -> Expired | Z59: Microsoft CMT (the live link still points at cmt3.research.microsoft.com/ESS2024) | AA59: Not published on the site | AB59: https://ess.ieee.org.ua/ | AC59: Website | AD59: Not published on the site | AE59: 46269 | AF59: ARCHIVED. VENUE CORRECTED from "Not stated" - the site names Igor Sikorsky Kyiv Polytechnic Institute as host. Dates confirmed: full-paper submission 30.11.2025, notification of acceptance 22.03.2026, conference 21-24.04.2026. SUBMISSION SYSTEM ADDED as Microsoft CMT, but note the link on the page still carries the 2024 slug (cmt3.research.microsoft.com/ESS2024). The site also leaves a stale "Pre-Conference Workshop: October 29-31, 2024" block in place. No camera-ready date, registration deadline, fee, page limit or contact e-mail is published; the participation-fee page does not resolve. 9th edition. | AG59: 44730
A60: 59 | B60: TCSET | C60: 2026 | D60: 18th | E60: IEEE 18th International Conference on Advanced Trends in Radioelectronics, Telecommunications and Computer Engineering | F60: Conference | G60: Finished | H60: =IF($G60="High",1,IF($G60="Mediocre",2,3)) -> 3 | I60: IEEE.org | J60: IEEE | K60: Not published (a Conference Fee page is linked) | O60: 45991 | P60: 46034 | Q60: 46036 | R60: 46043 | S60: 17–21 Feb 2026 | T60: 46070 | U60: 46074 | V60: Lviv, Ukraine | W60: Hybrid | X60: =IF(O60="","",INT(O60)-TODAY()) -> -278 | Y60: =IF($G60="Finished","Expired",IF(AND(O60<>"",INT(O60)>=TODAY()),IF(INT(O60)-TODAY()<=30,"Open - closing soon","Open"),IF(AND(T60<>"",U60<>"",INT(T60)<=TODAY(),INT(U60)>=TODAY()),"Event in progress",IF(AND(O60="",R60<>"",INT(R60)>=TODAY()),"Registration due",IF(AND(O60="",U60<>"",INT(U60)>=TODAY()),"Deadline not published",IF(AND(O60<>"",Q60<>"",INT(Q60)>=TODAY()),"Camera-ready due",IF(AND(O60<>"",R60<>"",INT(R60)>=TODAY()),"Registration due",IF(AND(U60<>"",INT(U60)>=TODAY()),"Submissions closed - event ahead","Expired")))))))) -> Expired | Z60: Not stated | AA60: Not published on the site | AB60: https://tcset.ieee.org.ua/ | AC60: Website | AD60: Not published on the site | AE60: 46269 | AF60: ARCHIVED, ALL DATES CONFIRMED verbatim: 30.11.2025 paper submission, 12.01.2026 acceptance notification, 14.01.2026 final revision submission, 21.01.2026 payment of fees; the programme was announced 16.01.2026 and the conference ran 17-21.02.2026 in Lviv in hybrid format, inside the IEEE Lviv Polytechnic Winter Week. IEEE Conference Valid Registration #65181. The fee page is linked but publishes no amounts, and no submission-system URL, page limit or contact e-mail appears on the site. 18th edition. | AG60: 43964
A61: 60 | B61: ELNANO | C61: 2026 | D61: — | E61: IEEE International Conference on Electronics and Nanotechnology (ELNANO) | F61: Conference | G61: Finished | H61: =IF($G61="High",1,IF($G61="Mediocre",2,3)) -> 3 | I61: IEEE.org | J61: IEEE Xplore Digital Library (Scopus and Web of Science indexation) | K61: 240 EUR IEEE member, 290 EUR non-member, 145 EUR IEEE student, 190 EUR student non-member (VAT incl.) | L61: 145 | M61: EUR | O61: 46006 | P61: 46082 | Q61: 46068 | R61: 46086 | S61: 27–30 Apr 2026 | T61: 46139 | U61: 46142 | V61: Igor Sikorsky Kyiv Polytechnic Institute, Kyiv, Ukraine | W61: Not stated | X61: =IF(O61="","",INT(O61)-TODAY()) -> -263 | Y61: =IF($G61="Finished","Expired",IF(AND(O61<>"",INT(O61)>=TODAY()),IF(INT(O61)-TODAY()<=30,"Open - closing soon","Open"),IF(AND(T61<>"",U61<>"",INT(T61)<=TODAY(),INT(U61)>=TODAY()),"Event in progress",IF(AND(O61="",R61<>"",INT(R61)>=TODAY()),"Registration due",IF(AND(O61="",U61<>"",INT(U61)>=TODAY()),"Deadline not published",IF(AND(O61<>"",Q61<>"",INT(Q61)>=TODAY()),"Camera-ready due",IF(AND(O61<>"",R61<>"",INT(R61)>=TODAY()),"Registration due",IF(AND(U61<>"",INT(U61)>=TODAY()),"Submissions closed - event ahead","Expired")))))))) -> Expired | Z61: Microsoft CMT (cmt3.research.microsoft.com/ELNANO2026) | AA61: 4 to 6 A4 pages fully filled with text, IEEE Proceedings format | AB61: https://elnano.ieee.org.ua/for-authors/ | AC61: Website | AD61: Not published on the site | AE61: 46269 | AF61: ARCHIVED. Dates confirmed and the odd ordering is the organisers' own: paper submission was EXTENDED to 15.12.2025; reviewer response 01.02.2026; camera-ready papers 15.02.2026; FINAL acceptance notification 01.03.2026; final registration 05.03.2026. Camera-ready therefore precedes final acceptance because authors with positive reviews submit camera-ready first and acceptance is confirmed afterwards - not a transcription error. Event 27-30.04.2026, Igor Sikorsky KPI, Kyiv. ADDED the Microsoft CMT URL, the 4-6 page IEEE-format specification and the Scopus/WoS indexation detail. Fees confirmed: 240 EUR IEEE member, 290 EUR non-member, 145 EUR IEEE student, 190 EUR student non-member, VAT included. No contact e-mail published. | AG61: 44730
A62: 61 | B62: ICon-MaSTEd | C62: 2026 | D62: XVIII | E62: XVIII International Conference on Mathematics, Science and Technology Education | F62: Conference | G62: Finished | H62: =IF($G62="High",1,IF($G62="Mediocre",2,3)) -> 3 | I62: IOP Publishing | J62: Journal of Physics: Conference Series | K62: Free for Ukrainian corresponding authors at Ukrainian institutions (waived by IOP); 95 GBP for international authors; audience free | L62: 0 | M62: — | O62: 46032 | P62: 46102 | Q62: 46123 | R62: 46143 | S62: 13–15 May 2026 (workshop day 13 May, main conference 14–15 May) | T62: 46155 | U62: 46157 | V62: Kryvyi Rih, Ukraine | W62: Hybrid (remote participation via Zoom) | X62: =IF(O62="","",INT(O62)-TODAY()) -> -237 | Y62: =IF($G62="Finished","Expired",IF(AND(O62<>"",INT(O62)>=TODAY()),IF(INT(O62)-TODAY()<=30,"Open - closing soon","Open"),IF(AND(T62<>"",U62<>"",INT(T62)<=TODAY(),INT(U62)>=TODAY()),"Event in progress",IF(AND(O62="",R62<>"",INT(R62)>=TODAY()),"Registration due",IF(AND(O62="",U62<>"",INT(U62)>=TODAY()),"Deadline not published",IF(AND(O62<>"",Q62<>"",INT(Q62)>=TODAY()),"Camera-ready due",IF(AND(O62<>"",R62<>"",INT(R62)>=TODAY()),"Registration due",IF(AND(U62<>"",INT(U62)>=TODAY()),"Submissions closed - event ahead","Expired")))))))) -> Expired | Z62: Morressier (morressier.com/call-for-papers/68a727782047348dd5a2bec2) | AA62: At least 6 pages, no stated maximum; double-blind review | AB62: https://icon-masted.easyscience.education/2026/ | AC62: Website | AD62: irina.mintiy@gmail.com, +380983516035 (Iryna Mintii); semerikov@gmail.com (Serhiy Semerikov) | AE62: 46269 | AF62: ARCHIVED, ALL DATES CONFIRMED: paper submission 10.01.2026, notification 21.03.2026, final submission 11.04.2026, registration 01.05.2026; workshop day 13.05.2026 and main conference 14-15.05.2026, Kryvyi Rih. Edition confirmed as XVIII by the site's own title and its history list (XVII was 2025). ADDED the hybrid/Zoom format, the Morressier submission URL, the 6-page minimum and two organiser contacts - all blank before. Fee confirmed: no fee for corresponding authors in Ukraine or at a Ukrainian institution and none for audience participants, 95 GBP otherwise. Published in the Journal of Physics: Conference Series (IOP Publishing). Note its co-located STE(A)M workshop page still calls this conference "XVII" - the conference's own title is authoritative. | AG62: 44730
A63: 62 | B63: STE(A)M | C63: 2026 | D63: 5th | E63: 5th Yurii Ramskyi STE(A)M Workshop | F63: Workshop | G63: Finished | H63: =IF($G63="High",1,IF($G63="Mediocre",2,3)) -> 3 | I63: CEUR.org | J63: Not stated | K63: Free | L63: 0 | M63: — | O63: 46032 | P63: 46102 | Q63: 46123 | R63: 46143 | S63: 13 May 2026 | T63: 46155 | U63: 46155 | V63: Ternopil, Ukraine | W63: Co-located with ICon-MaSTEd 2026 (which runs hybrid, remote participation via Zoom) | X63: =IF(O63="","",INT(O63)-TODAY()) -> -237 | Y63: =IF($G63="Finished","Expired",IF(AND(O63<>"",INT(O63)>=TODAY()),IF(INT(O63)-TODAY()<=30,"Open - closing soon","Open"),IF(AND(T63<>"",U63<>"",INT(T63)<=TODAY(),INT(U63)>=TODAY()),"Event in progress",IF(AND(O63="",R63<>"",INT(R63)>=TODAY()),"Registration due",IF(AND(O63="",U63<>"",INT(U63)>=TODAY()),"Deadline not published",IF(AND(O63<>"",Q63<>"",INT(Q63)>=TODAY()),"Camera-ready due",IF(AND(O63<>"",R63<>"",INT(R63)>=TODAY()),"Registration due",IF(AND(U63<>"",INT(U63)>=TODAY()),"Submissions closed - event ahead","Expired")))))))) -> Expired | Z63: HotCRP (notso.easyscience.education/stem/2026/) | AA63: Full, original research papers of at least 6 pages, including surveys, tutorials and perspective/colloquia articles; peer-reviewed by two scholars, a third if needed (the publication section says three, a fourth if needed) | AB63: https://stem.easyscience.education/2026/ | AC63: Website | AD63: oleksyuk@fizmat.tnpu.edu.ua (Vasyl Oleksiuk, PC chair); tsidylo@tnpu.edu.ua, +380-67-281-8864 (Ivan Tsidylo) | AE63: 46269 | AF63: ARCHIVED. LOCATION CORRECTED from Kryvyi Rih to TERNOPIL - this was a real error. The workshop page header reads "May 13, 2026, Ternopil, Ukraine", ICon-MaSTEd's own co-located-workshop list says "5th Yurii Ramskyi STE(A)M Workshop (STEM@ICon-MaSTEd 2026) - Ternopil", and both programme-committee contacts sit at TNPU in Ternopil; only the parent conference is in Kryvyi Rih. Dates confirmed: submission 10.01.2026, notification 21.03.2026, final submission 11.04.2026, registration 01.05.2026, workshop 13.05.2026. ADDED the HotCRP URL, the 6-page minimum and both contacts. Accepted papers go to CEUR-WS. The page still describes the parent as the "XVII" conference, whereas ICon-MaSTEd 2026 is the XVIII edition. Honours the memory of Yurii S. Ramskyi (1942-2022). | AG63: 45713
A64: 63 | B64: MS-AMLV | C64: 2026 | D64: 7th | E64: 7th Masters Symposium on Advances in Data Mining, Machine Learning, and Computer Vision | F64: Conference | G64: Finished | H64: =IF($G64="High",1,IF($G64="Mediocre",2,3)) -> 3 | I64: Springer.org | J64: Not verified | K64: Free (tracker figure, not re-verified) | L64: 0 | M64: — | O64: 46052 | S64: 27–28 Mar 2026 | T64: 46108 | U64: 46109 | V64: Lviv, Ukraine (Ukrainian Catholic University) | W64: Not stated | X64: =IF(O64="","",INT(O64)-TODAY()) -> -217 | Y64: =IF($G64="Finished","Expired",IF(AND(O64<>"",INT(O64)>=TODAY()),IF(INT(O64)-TODAY()<=30,"Open - closing soon","Open"),IF(AND(T64<>"",U64<>"",INT(T64)<=TODAY(),INT(U64)>=TODAY()),"Event in progress",IF(AND(O64="",R64<>"",INT(R64)>=TODAY()),"Registration due",IF(AND(O64="",U64<>"",INT(U64)>=TODAY()),"Deadline not published",IF(AND(O64<>"",Q64<>"",INT(Q64)>=TODAY()),"Camera-ready due",IF(AND(O64<>"",R64<>"",INT(R64)>=TODAY()),"Registration due",IF(AND(U64<>"",INT(U64)>=TODAY()),"Submissions closed - event ahead","Expired")))))))) -> Expired | Z64: EasyChair (PDF submissions; 3-5 freely chosen key phrases required) | AA64: Not verified this pass; PDF via EasyChair, at least three and at most five key phrases | AB64: https://apps.ucu.edu.ua/en/ms-amlv-2026/ | AC64: Website | AD64: Not published on the site | AE64: 46269 | AF64: ARCHIVED and ONLY PARTLY VERIFIABLE: apps.ucu.edu.ua sits behind a Cloudflare bot check that will not serve the page, and the call-for-papers PDF returns HTTP 403. What could be confirmed from the public listing and the page title: 7th Masters Symposium, 27-28.03.2026, Lviv, Ukraine, submissions in PDF through EasyChair with 3-5 key phrases, accepted papers presented in person by the student author and published online in a proceedings volume after the symposium. The 30.01.2026 submission date is retained from the earlier pass and the notification, camera-ready and registration dates were never recorded - treat all of them as unconfirmed. The "Free" cost figure likewise comes from the tracker, not from the site. | AG64: 45713
A65: 64 | B65: DSMIE | C65: 2026 | D65: 9th | E65: 9th International Conference on Design, Simulation, Manufacturing: The Innovation Exchange | F65: Conference | G65: Finished | H65: =IF($G65="High",1,IF($G65="Mediocre",2,3)) -> 3 | I65: Springer.org | J65: Springer Lecture Notes in Mechanical Engineering | K65: Registration in EUR. Early-bird (before 15.04.2026) / regular (16-30.04.2026) / late (from 01.05.2026): full delegate one paper 600 / 650 / n-a; full delegate two papers 750 / 800 / n-a; co-author 500 / 500 / n-a; student 500 / 500 / n-a; full delegate without publication 500 / 500 / 500; accompanying person 400 / 400 / 400. Includes publication of one or two papers, all sessions, e-access to the proceedings for 4 weeks, lunches and the gala dinner, plus IATDI membership; 40% discount on the printed Springer proceedings | L65: 600 | M65: EUR | O65: 46053 | P65: 46096 | Q65: 46112 | R65: 46127 | S65: 02–05 Jun 2026 | T65: 46175 | U65: 46178 | V65: Rahat Palace Hotel, 29/6 Satpaev Str., Almaty, Kazakhstan | W65: In-person (conference bags only for in-person participants) | X65: =IF(O65="","",INT(O65)-TODAY()) -> -216 | Y65: =IF($G65="Finished","Expired",IF(AND(O65<>"",INT(O65)>=TODAY()),IF(INT(O65)-TODAY()<=30,"Open - closing soon","Open"),IF(AND(T65<>"",U65<>"",INT(T65)<=TODAY(),INT(U65)>=TODAY()),"Event in progress",IF(AND(O65="",R65<>"",INT(R65)>=TODAY()),"Registration due",IF(AND(O65="",U65<>"",INT(U65)>=TODAY()),"Deadline not published",IF(AND(O65<>"",Q65<>"",INT(Q65)>=TODAY()),"Camera-ready due",IF(AND(O65<>"",R65<>"",INT(R65)>=TODAY()),"Registration due",IF(AND(U65<>"",INT(U65)>=TODAY()),"Submissions closed - event ahead","Expired")))))))) -> Expired | Z65: EasyChair (easychair.org/conferences/?conf=dsmie2026) | AA65: Camera-ready due 2 weeks after acceptance notification | AB65: https://dsmie.sumdu.edu.ua/schedule/important-dates.html | AC65: Website | AD65: dsmie@teset.sumdu.edu.ua | AE65: 46269 | AF65: ARCHIVED, with two real corrections. CAMERA-READY ADDED as 31.03.2026: the Important Dates page only says "2 weeks after acceptance notification", but the home page prints the actual date. COST CORRECTED from "600 EUR (tracker figure; not restated on the current site)" - the Registration Fee page publishes the full three-tier table now recorded. Other dates confirmed: paper submission 31.01.2026, acceptance notification 15.03.2026, registration and fee payment 15.04.2026, conference 02-05.06.2026; all deadlines 23:59 Hawaii time. ADDED the venue (Rahat Palace Hotel, 29/6 Satpaev Str., Almaty), the EasyChair URL and the contact address. WORTH YOUR ATTENTION: the home page banner now advertises the next edition as "JUNE 8-11, 2027 | To be announced soon" with a countdown running to 07.06.2027, while the Important Dates block still shows the 2026 schedule - the series appears to have moved to June 2027. Hotel promo code DSMIE-2026 for bookings 25.05-10.06. | AG65: 44730
A66: 65 | B66: SMARTINDUSTRY | C66: 2026 | D66: 3rd | E66: 3rd International Conference on Smart Automation & Robotics for Future Industry | F66: Conference | G66: Finished | H66: =IF($G66="High",1,IF($G66="Mediocre",2,3)) -> 3 | I66: CEUR.org | J66: Not stated | K66: Free | L66: 0 | M66: — | O66: 46053 | P66: 46090 | Q66: 46097 | R66: 46107 | S66: 26–27 Mar 2026 | T66: 46107 | U66: 46108 | V66: Lviv Polytechnic National University, Lviv, Ukraine | W66: Not stated | X66: =IF(O66="","",INT(O66)-TODAY()) -> -216 | Y66: =IF($G66="Finished","Expired",IF(AND(O66<>"",INT(O66)>=TODAY()),IF(INT(O66)-TODAY()<=30,"Open - closing soon","Open"),IF(AND(T66<>"",U66<>"",INT(T66)<=TODAY(),INT(U66)>=TODAY()),"Event in progress",IF(AND(O66="",R66<>"",INT(R66)>=TODAY()),"Registration due",IF(AND(O66="",U66<>"",INT(U66)>=TODAY()),"Deadline not published",IF(AND(O66<>"",Q66<>"",INT(Q66)>=TODAY()),"Camera-ready due",IF(AND(O66<>"",R66<>"",INT(R66)>=TODAY()),"Registration due",IF(AND(U66<>"",INT(U66)>=TODAY()),"Submissions closed - event ahead","Expired")))))))) -> Expired | Z66: Site submission | AA66: Not published on the site | AB66: https://science.lpnu.ua/smartindustry-2026 | AC66: Website | AD66: smartindustry.conference@gmail.com | AE66: 46269 | AF66: ARCHIVED, ALL DATES CONFIRMED verbatim on the LPNU dates block: 31.01.2026 23:59 paper submission, 09.03.2026 23:59 notification of acceptance, 16.03.2026 23:59 camera-ready, 26.03.2026 10:00 opening; conference 26-27.03.2026 at Lviv Polytechnic. REGISTRATION DEADLINE ADDED as 26.03.2026 - the site ties the participation registration form to the opening day. ADDED the contact address, recovered from the page's obfuscated e-mail link. Free. Papers also accepted by e-mail. No page limit published. | AG66: 45463
A67: 66 | B67: CPITS | C67: 2026 | D67: — | E67: Cybersecurity Providing in Information and Telecommunication Systems | F67: Conference + Workshop | G67: Finished | H67: =IF($G67="High",1,IF($G67="Mediocre",2,3)) -> 3 | I67: CEUR.org | J67: Scopus, DBLP | K67: Free — "Registration fee: free" | L67: 0 | M67: — | O67: 46060 | P67: 46067 | Q67: 46074 | S67: 28 Feb 2026 | T67: 46081 | U67: 46081 | V67: Kyiv, Ukraine | W67: Not stated | X67: =IF(O67="","",INT(O67)-TODAY()) -> -209 | Y67: =IF($G67="Finished","Expired",IF(AND(O67<>"",INT(O67)>=TODAY()),IF(INT(O67)-TODAY()<=30,"Open - closing soon","Open"),IF(AND(T67<>"",U67<>"",INT(T67)<=TODAY(),INT(U67)>=TODAY()),"Event in progress",IF(AND(O67="",R67<>"",INT(R67)>=TODAY()),"Registration due",IF(AND(O67="",U67<>"",INT(U67)>=TODAY()),"Deadline not published",IF(AND(O67<>"",Q67<>"",INT(Q67)>=TODAY()),"Camera-ready due",IF(AND(O67<>"",R67<>"",INT(R67)>=TODAY()),"Registration due",IF(AND(U67<>"",INT(U67)>=TODAY()),"Submissions closed - event ahead","Expired")))))))) -> Expired | Z67: Not stated | AA67: Regular paper at least 10 CEUR-WS pages with an appropriate number of references; short paper 5-9 CEUR-WS pages including references; the CEURART one-column Word template is mandatory and other templates are rejected | AB67: https://cpits.kubg.edu.ua/ | AC67: Website | AD67: cpits@kubg.edu.ua | AE67: 46269 | AF67: ARCHIVED, ALL DATES CONFIRMED verbatim: "Paper submission deadline: February 7, 2026", "Notification of acceptance: February 14, 2026", "Camera-ready submission: February 21, 2026", "Workshop: February 28, 2026". "Registration fee: free" confirmed. ADDED the page limits, the mandatory CEURART one-column Word template and the contact address. The site keeps a full volume history, which fixes the series: Vol-3991 (28.02.2025), Vol-4145 (26.10.2025) and back to Vol-2746 (07.07.2020), each with URN, Scopus EID, DBLP key and TIB/NID identifiers. No registration deadline separate from the fee-free registration. | AG67: 45608
A68: 67 | B68: IST | C68: 2026 | D68: 3rd | E68: 3rd international scientific and practical conference «Information Systems and Technology: Results and Prospects» | F68: Conference | G68: Finished | H68: =IF($G68="High",1,IF($G68="Mediocre",2,3)) -> 3 | I68: Not specified | J68: Not stated | K68: Free — "PARTICIPATION IN THE CONFERENCE IS FREE OF CHARGE" | L68: 0 | M68: — | O68: 46086 | R68: 46086 | S68: 10 Mar 2026 | T68: 46091 | U68: 46091 | V68: Faculty of Information Technology, Taras Shevchenko National University of Kyiv, Ukraine | W68: Not stated | X68: =IF(O68="","",INT(O68)-TODAY()) -> -183 | Y68: =IF($G68="Finished","Expired",IF(AND(O68<>"",INT(O68)>=TODAY()),IF(INT(O68)-TODAY()<=30,"Open - closing soon","Open"),IF(AND(T68<>"",U68<>"",INT(T68)<=TODAY(),INT(U68)>=TODAY()),"Event in progress",IF(AND(O68="",R68<>"",INT(R68)>=TODAY()),"Registration due",IF(AND(O68="",U68<>"",INT(U68)>=TODAY()),"Deadline not published",IF(AND(O68<>"",Q68<>"",INT(Q68)>=TODAY()),"Camera-ready due",IF(AND(O68<>"",R68<>"",INT(R68)>=TODAY()),"Registration due",IF(AND(U68<>"",INT(U68)>=TODAY()),"Submissions closed - event ahead","Expired")))))))) -> Expired | Z68: E-mail application | AA68: Not published on the site | AB68: https://ist.fit.knu.ua/scientificconference/konf2026 | AC68: Website; CAP | AD68: istconference@fit.knu.ua; ist@fit.knu.ua; fit@knu.ua | AE68: 46269 | AF68: ARCHIVED. Dates confirmed verbatim: "Submission of applications and papers for publication: before March 5st, 2026" (the site's own typo for 5th) and "Work of the conference: March 10th, 2026". The 05.03.2026 date therefore serves as both the submission and the registration deadline, and no notification or camera-ready date was ever published - those cells are correctly empty. ADDED three contact addresses, which were blank. "PARTICIPATION IN THE CONFERENCE IS FREE OF CHARGE" confirmed. Faculty of Information Technology, Taras Shevchenko National University of Kyiv. 3rd edition. No page limit published. | AG68: 45683
A69: 68 | B69: UNLP | C69: 2026 | D69: 5th | E69: The Fifth Ukrainian Natural Language Processing Conference | F69: Conference + Workshop | G69: Finished | H69: =IF($G69="High",1,IF($G69="Mediocre",2,3)) -> 3 | I69: ACL Anthology | J69: ACL Anthology | K69: Free | L69: 0 | M69: — | O69: 46097 | P69: 46127 | Q69: 46138 | S69: 29–30 May 2026 | T69: 46171 | U69: 46172 | V69: Lviv, Ukraine (hosted by UCU Faculty of Applied Sciences) | W69: Hybrid | X69: =IF(O69="","",INT(O69)-TODAY()) -> -172 | Y69: =IF($G69="Finished","Expired",IF(AND(O69<>"",INT(O69)>=TODAY()),IF(INT(O69)-TODAY()<=30,"Open - closing soon","Open"),IF(AND(T69<>"",U69<>"",INT(T69)<=TODAY(),INT(U69)>=TODAY()),"Event in progress",IF(AND(O69="",R69<>"",INT(R69)>=TODAY()),"Registration due",IF(AND(O69="",U69<>"",INT(U69)>=TODAY()),"Deadline not published",IF(AND(O69<>"",Q69<>"",INT(Q69)>=TODAY()),"Camera-ready due",IF(AND(O69<>"",R69<>"",INT(R69)>=TODAY()),"Registration due",IF(AND(U69<>"",INT(U69)>=TODAY()),"Submissions closed - event ahead","Expired")))))))) -> Expired | Z69: Softconf (softconf.com/p/unlp2026) | AA69: ACL style template; dedicated Limitations and Ethical Considerations sections required | AB69: https://unlp.org.ua/call-for-papers/ | AC69: Website | AD69: Not published on the site | AE69: 46269 | AF69: ARCHIVED, ALL DATES CONFIRMED verbatim: "March 16 (11:59 PM UTC-12), 2026 - Paper submission deadline", "April 15, 2026 - Notification of acceptance", "April 26 (11:59 PM UTC-12), 2026 - Camera-ready papers due", "May 29-30, 2026 - Conference dates". THREE EARLIER MILESTONES now recorded: first call 02.11.2025, second call 15.12.2025, third call 30.01.2026. Deadlines are UTC-12, i.e. anywhere-on-earth. Hybrid, Lviv, with in-person and virtual presentation options. Free. Softconf submission. 5th edition. No registration deadline or contact address published. | AG69: 44294
A70: 69 | B70: CMIS | C70: 2026 | D70: 9th | E70: The Ninth International Workshop on Computer Modeling and Intelligent Systems | F70: Conference + Workshop | G70: Finished | H70: =IF($G70="High",1,IF($G70="Mediocre",2,3)) -> 3 | I70: CEUR.org | J70: CEUR Workshop Proceedings (ISSN 1613-0073), indexed by Scopus and DBLP; alternative route into the journal "Radio Electronics, Computer Science, Control" (Web of Science) | K70: Free | L70: 0 | M70: — | O70: 46103 | P70: 46124 | Q70: 46138 | S70: 05 May 2026 | T70: 46147 | U70: 46147 | V70: National University "Zaporizhzhia Polytechnic", Universytetska str. 64, Zaporizhzhia 69011, Ukraine | W70: In-person | X70: =IF(O70="","",INT(O70)-TODAY()) -> -166 | Y70: =IF($G70="Finished","Expired",IF(AND(O70<>"",INT(O70)>=TODAY()),IF(INT(O70)-TODAY()<=30,"Open - closing soon","Open"),IF(AND(T70<>"",U70<>"",INT(T70)<=TODAY(),INT(U70)>=TODAY()),"Event in progress",IF(AND(O70="",R70<>"",INT(R70)>=TODAY()),"Registration due",IF(AND(O70="",U70<>"",INT(U70)>=TODAY()),"Deadline not published",IF(AND(O70<>"",Q70<>"",INT(Q70)>=TODAY()),"Camera-ready due",IF(AND(O70<>"",R70<>"",INT(R70)>=TODAY()),"Registration due",IF(AND(U70<>"",INT(U70)>=TODAY()),"Submissions closed - event ahead","Expired")))))))) -> Expired | Z70: Google Form (forms.gle/bj8YaHBPoiJ3R8xPA) | AA70: 10-15 pages in the one-column CEUR format | AB70: https://pz.zp.ua/cmis/ | AC70: Website; Submission | AD70: subbotin@zp.edu.ua; subbotin.csit@gmail.com (Sergey Subbotin) | AE70: 46269 | AF70: ARCHIVED, ALL DATES CONFIRMED: paper submission 22.03.2026, acceptance notification 12.04.2026, camera-ready 26.04.2026, workshop 05.05.2026 at National University "Zaporizhzhia Polytechnic". ADDED the in-person format, the 10-15 page one-column CEUR specification, the Google Form submission URL and two contacts recovered from the page's obfuscated e-mail links; the indexing line now also names the Web of Science journal route ("Radio Electronics, Computer Science, Control"). Free. No registration deadline published. 9th edition. | AG70: 44208
A71: 70 | B71: AISD | C71: 2026 | D71: 3rd | E71: The Third International Workshop of Young Scientists on Artificial Intelligence for Sustainable Development | F71: Workshop | G71: Finished | H71: =IF($G71="High",1,IF($G71="Mediocre",2,3)) -> 3 | I71: CEUR.org | J71: CEUR (2nd edition published as Vol-3974) | K71: Not published | O71: 46108 | P71: 46129 | Q71: 46142 | S71: 07–08 May 2026 | T71: 46149 | U71: 46150 | V71: West Ukrainian National University, Ternopil, Ukraine | W71: Not stated | X71: =IF(O71="","",INT(O71)-TODAY()) -> -161 | Y71: =IF($G71="Finished","Expired",IF(AND(O71<>"",INT(O71)>=TODAY()),IF(INT(O71)-TODAY()<=30,"Open - closing soon","Open"),IF(AND(T71<>"",U71<>"",INT(T71)<=TODAY(),INT(U71)>=TODAY()),"Event in progress",IF(AND(O71="",R71<>"",INT(R71)>=TODAY()),"Registration due",IF(AND(O71="",U71<>"",INT(U71)>=TODAY()),"Deadline not published",IF(AND(O71<>"",Q71<>"",INT(Q71)>=TODAY()),"Camera-ready due",IF(AND(O71<>"",R71<>"",INT(R71)>=TODAY()),"Registration due",IF(AND(U71<>"",INT(U71)>=TODAY()),"Submissions closed - event ahead","Expired")))))))) -> Expired | Z71: Microsoft CMT | AA71: Springer LNCS template, 10–12 pages including references | AB71: https://aisd.wunu.edu.ua/ | AC71: Website | AD71: aisd_workshop@wunu.edu.ua | AE71: 46269 | AF71: ARCHIVED. Submission 27.03.2026, notification 17.04.2026 and camera-ready 30.04.2026 are retained from the earlier pass; the current page confirms the venue, the contact and the framing as the "2026 Conference of Young Scientists on Artificial Intelligence for Sustainable Development" but no longer shows the dates block. ADDED the contact address. West Ukrainian National University, Ternopil; event 07-08.05.2026; Microsoft CMT submission; CEUR proceedings. No fee or registration deadline published. 3rd edition. | AG71: 45608
A72: 71 | B72: ITEP | C72: 2026 | D72: 3rd | E72: 3rd International Conference on Information Technologies in the Environmental Protection | F72: Workshop | G72: Finished | H72: =IF($G72="High",1,IF($G72="Mediocre",2,3)) -> 3 | I72: Not specified | J72: Not stated | K72: Free — "Participation in the conference: free" | L72: 0 | M72: — | O72: 46143 | P72: 46150 | Q72: 46152 | R72: 46143 | S72: 14–15 May 2026 | T72: 46156 | U72: 46157 | V72: Lviv Polytechnic National University, Lviv, Ukraine | W72: Mixed | X72: =IF(O72="","",INT(O72)-TODAY()) -> -126 | Y72: =IF($G72="Finished","Expired",IF(AND(O72<>"",INT(O72)>=TODAY()),IF(INT(O72)-TODAY()<=30,"Open - closing soon","Open"),IF(AND(T72<>"",U72<>"",INT(T72)<=TODAY(),INT(U72)>=TODAY()),"Event in progress",IF(AND(O72="",R72<>"",INT(R72)>=TODAY()),"Registration due",IF(AND(O72="",U72<>"",INT(U72)>=TODAY()),"Deadline not published",IF(AND(O72<>"",Q72<>"",INT(Q72)>=TODAY()),"Camera-ready due",IF(AND(O72<>"",R72<>"",INT(R72)>=TODAY()),"Registration due",IF(AND(U72<>"",INT(U72)>=TODAY()),"Submissions closed - event ahead","Expired")))))))) -> Expired | Z72: Not stated | AA72: Not published on the site | AB72: https://science.lpnu.ua/itep-2026 | AC72: Website | AD72: itep.conference@gmail.com | AE72: 46269 | AF72: ARCHIVED, ALL DATES CONFIRMED verbatim on the LPNU dates block: 01.05.2026 18:00 deadline for registration AND submission of materials, 08.05.2026 18:00 notification of acceptance, 10.05.2026 18:00 camera-ready; conference 14-15.05.2026 at Lviv Polytechnic. That single 01.05.2026 date is why the submission and registration columns match. ADDED the contact address, recovered from the page's obfuscated e-mail link. "Participation in the conference: free" confirmed. Mixed format. No page limit is published. 3rd edition. | AG72: 45723
A73: 72 | B73: EXPLIMED | C73: 2026 | D73: 3rd | E73: EASi-EXPLIMED: Joint Workshop on Explainable AI in Space and Explainable AI for the Medical Domain | F73: Workshop | G73: Finished | H73: =IF($G73="High",1,IF($G73="Mediocre",2,3)) -> 3 | I73: CEUR.org | J73: Not stated | K73: Not published for the 2026 workshop | N73: 46153 | O73: 46157 | P73: 46181 | S73: 15-17 Aug 2026 (inside IJCAI-ECAI 2026, 15-21 Aug) | T73: 46249 | U73: 46251 | V73: Bremen, Germany | W73: In-person (each accepted paper gets an oral or a poster slot) | X73: =IF(O73="","",INT(O73)-TODAY()) -> -112 | Y73: =IF($G73="Finished","Expired",IF(AND(O73<>"",INT(O73)>=TODAY()),IF(INT(O73)-TODAY()<=30,"Open - closing soon","Open"),IF(AND(T73<>"",U73<>"",INT(T73)<=TODAY(),INT(U73)>=TODAY()),"Event in progress",IF(AND(O73="",R73<>"",INT(R73)>=TODAY()),"Registration due",IF(AND(O73="",U73<>"",INT(U73)>=TODAY()),"Deadline not published",IF(AND(O73<>"",Q73<>"",INT(Q73)>=TODAY()),"Camera-ready due",IF(AND(O73<>"",R73<>"",INT(R73)>=TODAY()),"Registration due",IF(AND(U73<>"",INT(U73)>=TODAY()),"Submissions closed - event ahead","Expired")))))))) -> Expired | Z73: EasyChair | AA73: Regular papers 10-20 pages, short/position/work-in-progress papers 5-9 pages; English, PDF only, double-blind and fully anonymised; CEUR one-column style, LaTeX template preferred, Word/LibreOffice acceptable with the Libertinus font | AB73: https://sites.google.com/view/easi-explimed/ | AC73: Website | AD73: Not published on the site | AE73: 46269 | AF73: ARCHIVED, with three corrections. SUBMISSION DEADLINE CORRECTED from 08.05.2026 to 15.05.2026 - the Important dates page shows "May 8, 2026 May 15, 2026", i.e. an extension (with a further extension to 01.06.2026 only for papers tied to the EASi AI Competition). ABSTRACT DEADLINE ADDED as 11.05.2026: a 100-300 word abstract with keywords and the author list was due "May 4 11 May, 2026" before the paper itself. EVENT DATES NARROWED from the whole IJCAI-ECAI window to 15-17.08.2026, the workshop's own days as printed in the mandatory CEUR footnote ("EXPLIMED 2026 - Third Workshop on Explainable Artificial Intelligence for the medical domain - 15-17 August 2026, Bremen, Germany"). Notification 08.06.2026 confirmed; camera-ready is still "To be announced". ADDED the in-person format, the EasyChair route and the full page limits. All dates are Anywhere on Earth. The co-hosted EASi half runs later: submission extended to 29.05.2026 and notification 12.06.2026. Workshop papers are reviewed separately from the main conference and do not appear in the IJCAI-ECAI proceedings. The 655 EUR cost figure is the parent conference's, not a workshop fee. | AG73: 45723
A74: 73 | B74: Synergy in Terra | C74: 2026 | D74: — | E74: International Conference “Synergy in Terra – 2026” | F74: Conference | G74: Finished | H74: =IF($G74="High",1,IF($G74="Mediocre",2,3)) -> 3 | I74: Academic Journal | J74: Conference proceedings | K74: Ukrainian scientists: 1000 UAH onsite / 500 UAH online. Foreign scientists: 100 USD onsite / 50 USD online. Accommodation and meals not included | L74: 500 | M74: UAH | N74: 46157 | O74: 46157 | R74: 46185 | S74: 12–13 Jun 2026 | T74: 46185 | U74: 46186 | V74: Recreation complex "The Bay of Vikings", Stare Selo, Lviv region, Ukraine | W74: Hybrid (onsite and online) | X74: =IF(O74="","",INT(O74)-TODAY()) -> -112 | Y74: =IF($G74="Finished","Expired",IF(AND(O74<>"",INT(O74)>=TODAY()),IF(INT(O74)-TODAY()<=30,"Open - closing soon","Open"),IF(AND(T74<>"",U74<>"",INT(T74)<=TODAY(),INT(U74)>=TODAY()),"Event in progress",IF(AND(O74="",R74<>"",INT(R74)>=TODAY()),"Registration due",IF(AND(O74="",U74<>"",INT(U74)>=TODAY()),"Deadline not published",IF(AND(O74<>"",Q74<>"",INT(Q74)>=TODAY()),"Camera-ready due",IF(AND(O74<>"",R74<>"",INT(R74)>=TODAY()),"Registration due",IF(AND(U74<>"",INT(U74)>=TODAY()),"Submissions closed - event ahead","Expired")))))))) -> Expired | Z74: Abstract template (.docx) submission | AA74: Extended abstracts | AB74: https://science.lpnu.ua/synergy-terra | AC74: Website | AD74: Via Lviv Polytechnic National University (no e-mail published on the conference page) | AE74: 46269 | AF74: ARCHIVED, ALL DATES CONFIRMED verbatim on the LPNU dates block: 15.05.2026 08:00 deadline for extended-abstract submission, 12.06.2026 11:00 deadline for registration; conference 12-13.06.2026 at the recreation complex "The Bay of Vikings", Stare Selo, Lviv region. No notification and no camera-ready date were ever published, so those cells are correctly empty. Fees: Ukrainian scientists 1000 UAH on site / 500 UAH online, foreign participants as stated on the Conference Fees page. Hybrid. Abstracts go in as a .docx template. | AG74: 45713
A75: 74 | B75: ICyberPhyS | C75: 2026 | D75: — | E75: Intelligent & CyberPhysical Systems | F75: Conference | G75: Finished | H75: =IF($G75="High",1,IF($G75="Mediocre",2,3)) -> 3 | I75: CEUR.org | J75: Scopus & DBLP (planned), ISSN 1613-0073 | K75: Free — "Participation and publication are free of charge" | L75: 0 | M75: — | O75: 46160 | P75: 46191 | Q75: 46196 | S75: 02 Jul 2026 | T75: 46205 | U75: 46205 | V75: Khmelnytskyi National University, Khmelnytskyi, Ukraine | W75: Not stated | X75: =IF(O75="","",INT(O75)-TODAY()) -> -109 | Y75: =IF($G75="Finished","Expired",IF(AND(O75<>"",INT(O75)>=TODAY()),IF(INT(O75)-TODAY()<=30,"Open - closing soon","Open"),IF(AND(T75<>"",U75<>"",INT(T75)<=TODAY(),INT(U75)>=TODAY()),"Event in progress",IF(AND(O75="",R75<>"",INT(R75)>=TODAY()),"Registration due",IF(AND(O75="",U75<>"",INT(U75)>=TODAY()),"Deadline not published",IF(AND(O75<>"",Q75<>"",INT(Q75)>=TODAY()),"Camera-ready due",IF(AND(O75<>"",R75<>"",INT(R75)>=TODAY()),"Registration due",IF(AND(U75<>"",INT(U75)>=TODAY()),"Submissions closed - event ahead","Expired")))))))) -> Expired | Z75: Not stated | AA75: Short 5–9 or regular 10–20 pages, English, CEUR-ART one-column; signed author agreement required | AB75: http://kiis.khmnu.edu.ua/icyberphys-2026/ | AC75: Website | AD75: icyberphys@gmail.com; pavlovao@khmnu.edu.ua | AE75: 46269 | AF75: ARCHIVED, ALL DATES CONFIRMED verbatim: "Paper submission deadline: May 18, 2026 (the deadline is final, no extension of submission is planned)", "Notification of acceptance: June 18, 2026", "Camera-ready submission deadline: June 23, 2026", "Workshop period: July 2, 2026". ADDED both contact addresses, which were blank. "Participation and publication are free of charge" confirmed. Khmelnytskyi National University; CEUR proceedings. No registration deadline published. | AG75: 45608
A76: 75 | B76: IntelITSIS | C76: 2026 | D76: 7th | E76: 7th International Workshop on Intelligent Information Technologies & Systems of Information Security | F76: Conference + Workshop | G76: Finished | H76: =IF($G76="High",1,IF($G76="Mediocre",2,3)) -> 3 | I76: CEUR.org | J76: Scopus & DBLP (planned) | K76: Free — "Participation and publication are free of charge" | L76: 0 | M76: — | O76: 46162 | P76: 46193 | Q76: 46200 | S76: 03 Jul 2026 | T76: 46206 | U76: 46206 | V76: Khmelnytskyi National University, Khmelnytskyi, Ukraine | W76: Not stated | X76: =IF(O76="","",INT(O76)-TODAY()) -> -107 | Y76: =IF($G76="Finished","Expired",IF(AND(O76<>"",INT(O76)>=TODAY()),IF(INT(O76)-TODAY()<=30,"Open - closing soon","Open"),IF(AND(T76<>"",U76<>"",INT(T76)<=TODAY(),INT(U76)>=TODAY()),"Event in progress",IF(AND(O76="",R76<>"",INT(R76)>=TODAY()),"Registration due",IF(AND(O76="",U76<>"",INT(U76)>=TODAY()),"Deadline not published",IF(AND(O76<>"",Q76<>"",INT(Q76)>=TODAY()),"Camera-ready due",IF(AND(O76<>"",R76<>"",INT(R76)>=TODAY()),"Registration due",IF(AND(U76<>"",INT(U76)>=TODAY()),"Submissions closed - event ahead","Expired")))))))) -> Expired | Z76: Not stated | AA76: Regular papers only, 10–20 pages, English, CEUR-ART one-column template | AB76: http://kiis.khmnu.edu.ua/intelitsis-2026/ | AC76: Website | AD76: IntelITSIS@gmail.com; pavlovao@khmnu.edu.ua | AE76: 46269 | AF76: ARCHIVED, ALL DATES CONFIRMED verbatim: "Paper submission deadline: May 20, 2026 (the deadline is final, no extension of submission is planned)", "Notification of acceptance: June 20, 2026", "Camera-ready submission deadline: June 27, 2026", "Workshop period: July 3, 2026". ADDED both contact addresses, which were blank. "Participation and publication are free of charge" confirmed. Khmelnytskyi National University; CEUR proceedings. 7th edition. No registration deadline published. | AG76: 44208
A77: 76 | B77: CH&CMiGIN | C77: 2026 | D77: 5th | E77: Fifth International Conference on Cyber Hygiene & Conflict Management in Global Information Networks | F77: Workshop | G77: Finished | H77: =IF($G77="High",1,IF($G77="Mediocre",2,3)) -> 3 | I77: CEUR.org | J77: Not stated | K77: Free — "Participation in the conference is free of charge" | L77: 0 | M77: — | O77: 46181 | P77: 46188 | Q77: 46193 | S77: 25–27 Jun 2026 | T77: 46198 | U77: 46200 | V77: University of the National Education Commission, Krakow, Poland | W77: Hybrid | X77: =IF(O77="","",INT(O77)-TODAY()) -> -88 | Y77: =IF($G77="Finished","Expired",IF(AND(O77<>"",INT(O77)>=TODAY()),IF(INT(O77)-TODAY()<=30,"Open - closing soon","Open"),IF(AND(T77<>"",U77<>"",INT(T77)<=TODAY(),INT(U77)>=TODAY()),"Event in progress",IF(AND(O77="",R77<>"",INT(R77)>=TODAY()),"Registration due",IF(AND(O77="",U77<>"",INT(U77)>=TODAY()),"Deadline not published",IF(AND(O77<>"",Q77<>"",INT(Q77)>=TODAY()),"Camera-ready due",IF(AND(O77<>"",R77<>"",INT(R77)>=TODAY()),"Registration due",IF(AND(U77<>"",INT(U77)>=TODAY()),"Submissions closed - event ahead","Expired")))))))) -> Expired | Z77: Electronic submission | AA77: English only; original unpublished work | AB77: http://cyberconf.kai.edu.ua/ | AC77: Website | AD77: Via the cyber-conference organising committee, Kharkiv Aviation Institute (no e-mail published on the page) | AE77: 46269 | AF77: ARCHIVED, ALL DATES CONFIRMED verbatim: "Paper submission deadline: before June 8, 2026", "Notification of acceptance: on June 15, 2026", "Camera-ready submission deadline: before June 20, 2026", "Conference period: June 25 - 27, 2026". "Participation in the conference is free of charge" confirmed. Hybrid; University of the National Education Commission, Krakow. 5th edition. No registration deadline or contact e-mail is published. | AG77: 45723
A78: 77 | B78: ProfIT AI | C78: 2026 | D78: 6th | E78: 6th International Conference of IT Professionals on Artificial Intelligence | F78: Workshop | G78: Finished | H78: =IF($G78="High",1,IF($G78="Mediocre",2,3)) -> 3 | I78: Springer.org | J78: Springer Communications in Computer and Information Science | K78: Free — "Participation in the conference is free of charge" | L78: 0 | M78: — | O78: 46198 | P78: 46204 | Q78: 46213 | S78: 15–17 Jul 2026 | T78: 46218 | U78: 46220 | V78: Coventry, UK & Kharkiv, Ukraine | W78: Online from Coventry | X78: =IF(O78="","",INT(O78)-TODAY()) -> -71 | Y78: =IF($G78="Finished","Expired",IF(AND(O78<>"",INT(O78)>=TODAY()),IF(INT(O78)-TODAY()<=30,"Open - closing soon","Open"),IF(AND(T78<>"",U78<>"",INT(T78)<=TODAY(),INT(U78)>=TODAY()),"Event in progress",IF(AND(O78="",R78<>"",INT(R78)>=TODAY()),"Registration due",IF(AND(O78="",U78<>"",INT(U78)>=TODAY()),"Deadline not published",IF(AND(O78<>"",Q78<>"",INT(Q78)>=TODAY()),"Camera-ready due",IF(AND(O78<>"",R78<>"",INT(R78)>=TODAY()),"Registration due",IF(AND(U78<>"",INT(U78)>=TODAY()),"Submissions closed - event ahead","Expired")))))))) -> Expired | Z78: Not stated | AA78: Regular 10–15 pp. or short 6–9 pp., English | AB78: https://khai.edu/en/international-workshop-of-it-professionals-on-artificial-intelligence-profit-ai | AC78: Website | AD78: Via the National Aerospace University "KhAI" organising committee (no e-mail published on the page) | AE78: 46269 | AF78: ARCHIVED, ALL DATES CONFIRMED, and the extension is visible on the page: "01.06.2026 25.06.2026 Paper submission deadline" - i.e. extended from 01.06 to 25.06.2026 - then "01.07.2026 Notification of acceptance" and "10.07.2026 Camera ready submission deadline"; event 15-17.07.2026. "Participation in the conference is free of charge" confirmed. Online from Coventry, UK, with Kharkiv, Ukraine. 6th edition. No registration deadline or contact e-mail published. | AG78: 45467
A79: 78 | B79: AI@DTESI | C79: 2025 | D79: — | E79: Workshop on Artificial Intelligence (at DTESI) | F79: Workshop | G79: Finished | H79: =IF($G79="High",1,IF($G79="Mediocre",2,3)) -> 3 | I79: CEUR.org | J79: CEUR Vol-4224 (ISSN 1613-0073, URN urn:nbn:de:0074-4224-x); 35 submissions, 23 papers published (18 regular, 5 short) | K79: Not published | S79: 19–20 Nov 2025 | T79: 45980 | U79: 45981 | V79: International Information Technology University, Almaty, Kazakhstan | W79: On-site (inside DTESI 2025, Almaty) | X79: =IF(O79="","",INT(O79)-TODAY()) | Y79: =IF($G79="Finished","Expired",IF(AND(O79<>"",INT(O79)>=TODAY()),IF(INT(O79)-TODAY()<=30,"Open - closing soon","Open"),IF(AND(T79<>"",U79<>"",INT(T79)<=TODAY(),INT(U79)>=TODAY()),"Event in progress",IF(AND(O79="",R79<>"",INT(R79)>=TODAY()),"Registration due",IF(AND(O79="",U79<>"",INT(U79)>=TODAY()),"Deadline not published",IF(AND(O79<>"",Q79<>"",INT(Q79)>=TODAY()),"Camera-ready due",IF(AND(O79<>"",R79<>"",INT(R79)>=TODAY()),"Registration due",IF(AND(U79<>"",INT(U79)>=TODAY()),"Submissions closed - event ahead","Expired")))))))) -> Expired | Z79: Not stated | AA79: Not stated - the source is a published CEUR volume, which carries no author guidelines (CEUR house style is CEURART one-column) | AB79: https://ceur-ws.org/Vol-4224/ | AC79: CEUR volume | AD79: Volume editors Kateryna Kolesnikova and Madina Ipalakova, International Information Technology University, Almaty, Kazakhstan | AE79: 46269 | AF79: ARCHIVED, VOLUME RE-READ. Vol-4224 states verbatim: "Proceedings of the Workshop on Artificial Intelligence 2025", "co-located with 10th International Conference on Digital Technologies in Education, Science and Industry (DTESI 2025)", "Almaty, Kazakhstan, November 19-20, 2025", edited by Kateryna Kolesnikova and Madina Ipalakova; published on CEUR-WS 16.07.2026. Event dates confirmed. This volume plus Vol-4180, Vol-4193 and Vol-4204 are the evidence that DTESI 2025 (the 10th edition) took place on 19-20.11.2025. No submission, notification, camera-ready or registration date is recoverable from a published volume, and no fee was published. | AG79: 46269
A80: 79 | B80: AIT | C80: 2025 | D80: 1st | E80: International Workshop on Application of Immersive Technology | F80: Workshop | G80: Finished | H80: =IF($G80="High",1,IF($G80="Mediocre",2,3)) -> 3 | I80: CEUR.org | J80: CEUR Vol-4014 (ISSN 1613-0073, URN urn:nbn:de:0074-4014-X); 13 papers published (4 regular, 9 short) | K80: Not published | S80: 05 Mar 2025 | T80: 45721 | U80: 45721 | V80: International Information Technology University, Almaty, Kazakhstan | W80: Not stated | X80: =IF(O80="","",INT(O80)-TODAY()) | Y80: =IF($G80="Finished","Expired",IF(AND(O80<>"",INT(O80)>=TODAY()),IF(INT(O80)-TODAY()<=30,"Open - closing soon","Open"),IF(AND(T80<>"",U80<>"",INT(T80)<=TODAY(),INT(U80)>=TODAY()),"Event in progress",IF(AND(O80="",R80<>"",INT(R80)>=TODAY()),"Registration due",IF(AND(O80="",U80<>"",INT(U80)>=TODAY()),"Deadline not published",IF(AND(O80<>"",Q80<>"",INT(Q80)>=TODAY()),"Camera-ready due",IF(AND(O80<>"",R80<>"",INT(R80)>=TODAY()),"Registration due",IF(AND(U80<>"",INT(U80)>=TODAY()),"Submissions closed - event ahead","Expired")))))))) -> Expired | Z80: Not stated | AA80: Not stated - the source is a published CEUR volume, which carries no author guidelines (CEUR house style is CEURART one-column) | AB80: https://ceur-ws.org/Vol-4014/ | AC80: CEUR volume | AD80: Volume editor Kateryna Kolesnikova, International Information Technology University, Almaty, Kazakhstan | AE80: 46269 | AF80: ARCHIVED, VOLUME RE-READ. Vol-4014 states verbatim: "Proceedings of the 1st International Workshop on Application of Immersive Technology (AIT 2025)", "Almaty, Kazakhstan, March 5, 2025", edited by Kateryna Kolesnikova; published on CEUR-WS 25.08.2025; 13 papers (4 regular, 9 short). Event date and the 1st-edition label confirmed. No parent conference is named in the volume, so this is a standalone workshop. No deadlines or fee are recoverable from a published volume. | AG80: 46269
A81: 80 | B81: AIT&AIS | C81: 2025 | D81: — | E81: International Scientific Workshop on Applied Information Technologies and Artificial Intelligence Systems | F81: Workshop | G81: Finished | H81: =IF($G81="High",1,IF($G81="Mediocre",2,3)) -> 3 | I81: CEUR.org | J81: CEUR Vol-4160 (ISSN 1613-0073, URN urn:nbn:de:0074-4160-x) | K81: Not published | R81: 45978 | S81: 18–19 Dec 2025 | T81: 46009 | U81: 46010 | V81: Yuriy Fedkovych Chernivtsi National University, Chernivtsi, Ukraine | W81: Hybrid (on-site plus an online video platform) | X81: =IF(O81="","",INT(O81)-TODAY()) | Y81: =IF($G81="Finished","Expired",IF(AND(O81<>"",INT(O81)>=TODAY()),IF(INT(O81)-TODAY()<=30,"Open - closing soon","Open"),IF(AND(T81<>"",U81<>"",INT(T81)<=TODAY(),INT(U81)>=TODAY()),"Event in progress",IF(AND(O81="",R81<>"",INT(R81)>=TODAY()),"Registration due",IF(AND(O81="",U81<>"",INT(U81)>=TODAY()),"Deadline not published",IF(AND(O81<>"",Q81<>"",INT(Q81)>=TODAY()),"Camera-ready due",IF(AND(O81<>"",R81<>"",INT(R81)>=TODAY()),"Registration due",IF(AND(U81<>"",INT(U81)>=TODAY()),"Submissions closed - event ahead","Expired")))))))) -> Expired | Z81: Not stated | AA81: Not published on the site | AB81: https://kkn.chnu.edu.ua/en/aitais/ | AC81: Website; CEUR volume | AD81: kkn@chnu.edu.ua; volume editors Harrison Hao Yang, Christopher Kumar Anand and others | AE81: 46269 | AF81: ARCHIVED, VOLUME RE-READ. Vol-4160 states verbatim: "Proceedings of the International Scientific Workshop on Applied Information Technologies and Artificial Intelligence Systems (AIT&AIS 2025)", "Chernivtsi, Ukraine, December 18-19, 2025", edited by Harrison Hao Yang, Christopher Kumar Anand and others. Event dates and the 17.11.2025 registration deadline both stand. ADDED the department contact kkn@chnu.edu.ua from the host site. Hybrid, Yuriy Fedkovych Chernivtsi National University. No submission, notification or camera-ready date is published, and no fee. | AG81: 46269
A82: 81 | B82: CISN | C82: 2025 | D82: — | E82: Workshop on Cybersecurity, Infocommunication Systems and Networks (at DTESI) | F82: Workshop | G82: Finished | H82: =IF($G82="High",1,IF($G82="Mediocre",2,3)) -> 3 | I82: CEUR.org | J82: CEUR Vol-4180 (ISSN 1613-0073, URN urn:nbn:de:0074-4180-x); 13 of 23 submissions published | K82: Not published | S82: 19–20 Nov 2025 | T82: 45980 | U82: 45981 | V82: International Information Technology University, Almaty, Kazakhstan | W82: On-site (inside DTESI 2025, Almaty) | X82: =IF(O82="","",INT(O82)-TODAY()) | Y82: =IF($G82="Finished","Expired",IF(AND(O82<>"",INT(O82)>=TODAY()),IF(INT(O82)-TODAY()<=30,"Open - closing soon","Open"),IF(AND(T82<>"",U82<>"",INT(T82)<=TODAY(),INT(U82)>=TODAY()),"Event in progress",IF(AND(O82="",R82<>"",INT(R82)>=TODAY()),"Registration due",IF(AND(O82="",U82<>"",INT(U82)>=TODAY()),"Deadline not published",IF(AND(O82<>"",Q82<>"",INT(Q82)>=TODAY()),"Camera-ready due",IF(AND(O82<>"",R82<>"",INT(R82)>=TODAY()),"Registration due",IF(AND(U82<>"",INT(U82)>=TODAY()),"Submissions closed - event ahead","Expired")))))))) -> Expired | Z82: Not stated | AA82: Not stated - the source is a published CEUR volume, which carries no author guidelines (CEUR house style is CEURART one-column) | AB82: https://ceur-ws.org/Vol-4180/ | AC82: CEUR volume | AD82: Volume editors Kateryna Kolesnikova and Madina Ipalakova, International Information Technology University, Almaty, Kazakhstan | AE82: 46269 | AF82: ARCHIVED, VOLUME RE-READ. Vol-4180 states verbatim: "Proceedings of the Workshop on Cybersecurity, Infocommunication Systems and Networks 2025", "Almaty, Kazakhstan, November 19-20, 2025", edited by Kateryna Kolesnikova and Madina Ipalakova; published on CEUR-WS 10.03.2026; 13 of 23 peer-reviewed submissions accepted. Event dates confirmed. Held inside DTESI 2025. No deadlines or fee are recoverable from a published volume. | AG82: 46269
A83: 82 | B83: CLW-CoLInS | C83: 2025 | D83: — | E83: Computational Linguistics Workshop at CoLInS | F83: Workshop | G83: Finished | H83: =IF($G83="High",1,IF($G83="Mediocre",2,3)) -> 3 | I83: CEUR.org | J83: CEUR Vol-3976 (ISSN 1613-0073, URN urn:nbn:de:0074-3976-X); 16 of 36 submissions published | K83: Not published | S83: 15–16 May 2025 | T83: 45792 | U83: 45793 | V83: Kharkiv, Ukraine | W83: On-site (inside CoLInS 2025, Kharkiv) | X83: =IF(O83="","",INT(O83)-TODAY()) | Y83: =IF($G83="Finished","Expired",IF(AND(O83<>"",INT(O83)>=TODAY()),IF(INT(O83)-TODAY()<=30,"Open - closing soon","Open"),IF(AND(T83<>"",U83<>"",INT(T83)<=TODAY(),INT(U83)>=TODAY()),"Event in progress",IF(AND(O83="",R83<>"",INT(R83)>=TODAY()),"Registration due",IF(AND(O83="",U83<>"",INT(U83)>=TODAY()),"Deadline not published",IF(AND(O83<>"",Q83<>"",INT(Q83)>=TODAY()),"Camera-ready due",IF(AND(O83<>"",R83<>"",INT(R83)>=TODAY()),"Registration due",IF(AND(U83<>"",INT(U83)>=TODAY()),"Submissions closed - event ahead","Expired")))))))) -> Expired | Z83: Not stated | AA83: Not stated - the source is a published CEUR volume, which carries no author guidelines (CEUR house style is CEURART one-column) | AB83: https://ceur-ws.org/Vol-3976/ | AC83: CEUR volume | AD83: Volume editors Nina Khairova, Victoria Vysotska, Natalia Grabar, Thierry Hamon and Nina Rizun | AE83: 46269 | AF83: ARCHIVED, VOLUME RE-READ. Vol-3976 states verbatim: "Proceedings of the Computational Linguistics Workshop (CLW-CoLInS 2025) at the 9th International Conference on Computational Linguistics and Intelligent Systems (CoLInS 2025)", "Kharkiv, Ukraine, May 15-16, 2025", edited by Nina Khairova, Victoria Vysotska, Natalia Grabar, Thierry Hamon and Nina Rizun; published on CEUR-WS 13.06.2025; 16 regular papers accepted from 36 submissions. Event dates confirmed. No deadlines or fee are recoverable from a published volume. | AG83: 46269
A84: 83 | B84: CoLInS | C84: 2026 | D84: 10th | E84: 10th International Conference on Computational Linguistics and Intelligent Systems | F84: Conference + Workshop | G84: Finished | H84: =IF($G84="High",1,IF($G84="Mediocre",2,3)) -> 3 | I84: CEUR.org | J84: Not stated | K84: Not published | S84: Postponed indefinitely | V84: Not stated | W84: Not stated | X84: =IF(O84="","",INT(O84)-TODAY()) | Y84: =IF($G84="Finished","Expired",IF(AND(O84<>"",INT(O84)>=TODAY()),IF(INT(O84)-TODAY()<=30,"Open - closing soon","Open"),IF(AND(T84<>"",U84<>"",INT(T84)<=TODAY(),INT(U84)>=TODAY()),"Event in progress",IF(AND(O84="",R84<>"",INT(R84)>=TODAY()),"Registration due",IF(AND(O84="",U84<>"",INT(U84)>=TODAY()),"Deadline not published",IF(AND(O84<>"",Q84<>"",INT(Q84)>=TODAY()),"Camera-ready due",IF(AND(O84<>"",R84<>"",INT(R84)>=TODAY()),"Registration due",IF(AND(U84<>"",INT(U84)>=TODAY()),"Submissions closed - event ahead","Expired")))))))) -> Expired | Z84: Not stated | AA84: Not published on the site | AB84: http://colins.in.ua/ | AC84: Website | AD84: vasyl.v.lytvyn@lpnu.ua; nvsharonova@ukr.net; eugeniokuprianov@gmail.com | AE84: 46269 | AF84: POSTPONED INDEFINITELY - re-confirmed 04.09.2026. colins.in.ua still shows the "Submission date:" and "Acceptance notification:" labels with no values behind them, and no venue, so the 10th edition has no announced dates. ADDED the three organiser contacts, which were blank. The 9th edition ran in Kharkiv on 15-16.05.2025 and produced three CEUR volumes (Vol-3976 CLW, Vol-3983 ISW, Vol-4015 AICS), so the series itself is alive; watch the site for a 2027 call. | AG84: 44208
A85: 84 | B85: CPITS-II | C85: 2025 | D85: — | E85: Cybersecurity Providing in Information and Telecommunication Systems II | F85: Workshop | G85: Finished | H85: =IF($G85="High",1,IF($G85="Mediocre",2,3)) -> 3 | I85: CEUR.org | J85: Scopus (EID 2-s2.0-105037957767), DBLP (conf/cpits/cpits2025-2), TIB 1915196752; CEUR Vol-4145 published 26.10.2025 (URN urn:nbn:de:0074-4145-X); series back to Vol-2746 | K85: Free | L85: 0 | M85: — | S85: 26 Oct 2025 (online) | T85: 45956 | U85: 45956 | V85: Kyiv, Ukraine | W85: Online | X85: =IF(O85="","",INT(O85)-TODAY()) | Y85: =IF($G85="Finished","Expired",IF(AND(O85<>"",INT(O85)>=TODAY()),IF(INT(O85)-TODAY()<=30,"Open - closing soon","Open"),IF(AND(T85<>"",U85<>"",INT(T85)<=TODAY(),INT(U85)>=TODAY()),"Event in progress",IF(AND(O85="",R85<>"",INT(R85)>=TODAY()),"Registration due",IF(AND(O85="",U85<>"",INT(U85)>=TODAY()),"Deadline not published",IF(AND(O85<>"",Q85<>"",INT(Q85)>=TODAY()),"Camera-ready due",IF(AND(O85<>"",R85<>"",INT(R85)>=TODAY()),"Registration due",IF(AND(U85<>"",INT(U85)>=TODAY()),"Submissions closed - event ahead","Expired")))))))) -> Expired | Z85: Not stated | AA85: Regular paper at least 10 CEUR-WS pages with an appropriate number of references; short paper 5-9 CEUR-WS pages including references; the CEURART one-column Word template is mandatory and other templates are rejected | AB85: https://cpits.kubg.edu.ua/ | AC85: Website; CEUR volume | AD85: cpits@kubg.edu.ua | AE85: 46269 | AF85: ARCHIVED, RE-CONFIRMED. The host site's volume history pins this edition exactly: "CEUR-WS Vol. 4145, October 26, 2025 (URN: urn:nbn:de:0074-4145-X, EID: 2-s2.0-105037957767, DBLP: conf/cpits/cpits2025-2, TIB: 1915196752)", which matches the recorded 26.10.2025 online workshop day; the spring edition of the same year is Vol-3991 of 28.02.2025. ADDED the Scopus/DBLP identifiers, the page limits, the mandatory CEURART one-column Word template and the contact address. "Registration fee: free" confirmed. The site now leads with CPITS 2026 (07.02 / 14.02 / 21.02, workshop 28.02.2026), tracked separately. | AG85: 46269
A86: 85 | B86: CQPC | C86: 2025 | D86: — | E86: Workshop on Classic, Quantum, and Post-Quantum Cryptography (at PICST) | F86: Workshop | G86: Finished | H86: =IF($G86="High",1,IF($G86="Mediocre",2,3)) -> 3 | I86: CEUR.org | J86: CEUR Vol-4016 (ISSN 1613-0073, URN urn:nbn:de:0074-4016-X); 6 of 11 submissions published (5 regular, 1 short) | K86: Not published | S86: 05 Aug 2025 | T86: 45874 | U86: 45874 | V86: Kyiv, Ukraine | W86: On-site (inside PICST 2025, Kyiv) | X86: =IF(O86="","",INT(O86)-TODAY()) | Y86: =IF($G86="Finished","Expired",IF(AND(O86<>"",INT(O86)>=TODAY()),IF(INT(O86)-TODAY()<=30,"Open - closing soon","Open"),IF(AND(T86<>"",U86<>"",INT(T86)<=TODAY(),INT(U86)>=TODAY()),"Event in progress",IF(AND(O86="",R86<>"",INT(R86)>=TODAY()),"Registration due",IF(AND(O86="",U86<>"",INT(U86)>=TODAY()),"Deadline not published",IF(AND(O86<>"",Q86<>"",INT(Q86)>=TODAY()),"Camera-ready due",IF(AND(O86<>"",R86<>"",INT(R86)>=TODAY()),"Registration due",IF(AND(U86<>"",INT(U86)>=TODAY()),"Submissions closed - event ahead","Expired")))))))) -> Expired | Z86: Not stated | AA86: Not stated - the source is a published CEUR volume, which carries no author guidelines (CEUR house style is CEURART one-column) | AB86: https://ceur-ws.org/Vol-4016/ | AC86: CEUR volume | AD86: Volume editors Volodymyr Sokolov (Borys Grinchenko Kyiv Metropolitan University), Vasyl Ustimenko (Royal Holloway, University of London) and Mariya Nazarkevych (Lviv Polytechnic National University) | AE86: 46269 | AF86: ARCHIVED, VOLUME RE-READ. Vol-4016 states verbatim: "Proceedings of the Workshop Classic, Quantum, and Post-Quantum Cryptography", "co-located with International Conference on Problems of Infocommunications. Science and Technology (PICST 2025)", "Kyiv, Ukraine, August 5, 2025", edited by Volodymyr Sokolov, Vasyl Ustimenko and Mariya Nazarkevych; published on CEUR-WS 26.08.2025; 6 papers (5 regular, 1 short). Event date confirmed and the parent conference identified as PICST 2025. No deadlines or fee are recoverable from a published volume. | AG86: 46269
A87: 86 | B87: CTE | C87: 2025 | D87: 12th | E87: Workshop on Cloud Technologies in Education (at ICHTML) | F87: Workshop | G87: Finished | H87: =IF($G87="High",1,IF($G87="Mediocre",2,3)) -> 3 | I87: CEUR.org | J87: CEUR Vol-4043 (ISSN 1613-0073, URN urn:nbn:de:0074-4043-X); 17 papers published (15 regular, 2 short) | K87: Not published | S87: 12 May 2025 | T87: 45789 | U87: 45789 | V87: Kryvyi Rih, Ukraine | W87: On-site (inside ICHTML 2025, Kryvyi Rih) | X87: =IF(O87="","",INT(O87)-TODAY()) | Y87: =IF($G87="Finished","Expired",IF(AND(O87<>"",INT(O87)>=TODAY()),IF(INT(O87)-TODAY()<=30,"Open - closing soon","Open"),IF(AND(T87<>"",U87<>"",INT(T87)<=TODAY(),INT(U87)>=TODAY()),"Event in progress",IF(AND(O87="",R87<>"",INT(R87)>=TODAY()),"Registration due",IF(AND(O87="",U87<>"",INT(U87)>=TODAY()),"Deadline not published",IF(AND(O87<>"",Q87<>"",INT(Q87)>=TODAY()),"Camera-ready due",IF(AND(O87<>"",R87<>"",INT(R87)>=TODAY()),"Registration due",IF(AND(U87<>"",INT(U87)>=TODAY()),"Submissions closed - event ahead","Expired")))))))) -> Expired | Z87: Not stated | AA87: Not stated - the source is a published CEUR volume, which carries no author guidelines (CEUR house style is CEURART one-column) | AB87: https://ceur-ws.org/Vol-4043/ | AC87: CEUR volume | AD87: Volume editors Serhiy O. Semerikov, Andrii M. Striuk, Olha P. Pinchuk and Tetiana A. Vakaliuk | AE87: 46269 | AF87: ARCHIVED, VOLUME RE-READ, WITH A LABEL DISCREPANCY WORTH KNOWING. Vol-4043 is titled "Proceedings of the 12th Workshop on Cloud Technologies in Education (CTE 2024)" and its acronym line reads "CTE 2024" / "Cloud Technologies in Education 2024" - yet the same volume gives the event as "Kryvyi Rih, Ukraine, May 12, 2025", co-located with the 6th International Conference on History, Theory and Methodology of Learning (ICHTML 2025). So the workshop carries the 2024 label but ran on 12.05.2025; the Year column here holds the year it was held. Edited by Semerikov, Striuk, Pinchuk and Vakaliuk; published on CEUR-WS 25.09.2025; 17 papers (15 regular, 2 short). No deadlines or fee are recoverable from a published volume. | AG87: 46269
A88: 87 | B88: DTESI | C88: 2025 | D88: 10th | E88: International Conference on Digital Technologies in Education, Science and Industry | F88: Conference | G88: Finished | H88: =IF($G88="High",1,IF($G88="Mediocre",2,3)) -> 3 | I88: CEUR.org | J88: CEUR; the 9th edition (DTESI 2024) is Vol-3966; NO main volume for the 10th/2025 edition has appeared - its four co-located workshop volumes are Vol-4224, Vol-4180, Vol-4193 and Vol-4204 | K88: Not published | S88: 19–20 Nov 2025 | T88: 45980 | U88: 45981 | V88: International Information Technology University, Almaty, Kazakhstan | W88: Not stated | X88: =IF(O88="","",INT(O88)-TODAY()) | Y88: =IF($G88="Finished","Expired",IF(AND(O88<>"",INT(O88)>=TODAY()),IF(INT(O88)-TODAY()<=30,"Open - closing soon","Open"),IF(AND(T88<>"",U88<>"",INT(T88)<=TODAY(),INT(U88)>=TODAY()),"Event in progress",IF(AND(O88="",R88<>"",INT(R88)>=TODAY()),"Registration due",IF(AND(O88="",U88<>"",INT(U88)>=TODAY()),"Deadline not published",IF(AND(O88<>"",Q88<>"",INT(Q88)>=TODAY()),"Camera-ready due",IF(AND(O88<>"",R88<>"",INT(R88)>=TODAY()),"Registration due",IF(AND(U88<>"",INT(U88)>=TODAY()),"Submissions closed - event ahead","Expired")))))))) -> Expired | Z88: Not stated | AA88: Not stated - the source is a published CEUR volume, which carries no author guidelines (CEUR house style is CEURART one-column) | AB88: https://ceur-ws.org/Vol-3966/ | AC88: CEUR volume | AD88: Volume editors Assylbek Issakhov, Kateryna Kolesnikova and others, International Information Technology University, Almaty, Kazakhstan | AE88: 46269 | AF88: CORRECTED - THE RECORDED URL POINTS AT THE WRONG VOLUME. https://ceur-ws.org/Vol-3966/ is "Proceedings of the 9th International Conference on Digital Technologies in Education, Science and Industry 2024 (DTESI 2024), Almaty, Kazakhstan, October 16-17, 2024", edited by Assylbek Issakhov, Kateryna Kolesnikova and others - it is the 2024 edition, not 2025. A sweep of the whole CEUR index confirms the series stops at Vol-3966: earlier editions are Vol-3680 (DTESI 2023, Almaty, 06-07.12.2023) and Vol-3382 (DTESI 2022, Almaty, 20-21.10.2022), and there is NO published main volume for DTESI 2025. The 10th edition on 19-20.11.2025 in Almaty is nonetheless real: it is attested by its four co-located workshop volumes, Vol-4224 (AI), Vol-4180 (CISN), Vol-4193 (SNE) and Vol-4204 (STIoT), which all name "10th International Conference on Digital Technologies in Education, Science and Industry (DTESI 2025)" as their parent. The row therefore keeps the 2025 edition and its dates, but replace the URL with the 2025 main volume once CEUR publishes it. No deadlines or fee are recoverable. | AG88: 46269
A89: 88 | B89: HCI-SI | C89: 2025 | D89: 10th | E89: 10th Human-Computer Interaction Slovenia | F89: Conference | G89: Finished | H89: =IF($G89="High",1,IF($G89="Mediocre",2,3)) -> 3 | I89: CEUR.org | J89: Proceedings DOI 10.26493/978-961-293-559-7 | K89: Free to attend (participants cover their own travel) | L89: 0 | M89: — | O89: 45931 | P89: 45933 | S89: 13 Oct 2025 | T89: 45943 | U89: 45943 | V89: FAMNIT, University of Primorska, Koper, Slovenia | W89: In-person | X89: =IF(O89="","",INT(O89)-TODAY()) -> -338 | Y89: =IF($G89="Finished","Expired",IF(AND(O89<>"",INT(O89)>=TODAY()),IF(INT(O89)-TODAY()<=30,"Open - closing soon","Open"),IF(AND(T89<>"",U89<>"",INT(T89)<=TODAY(),INT(U89)>=TODAY()),"Event in progress",IF(AND(O89="",R89<>"",INT(R89)>=TODAY()),"Registration due",IF(AND(O89="",U89<>"",INT(U89)>=TODAY()),"Deadline not published",IF(AND(O89<>"",Q89<>"",INT(Q89)>=TODAY()),"Camera-ready due",IF(AND(O89<>"",R89<>"",INT(R89)>=TODAY()),"Registration due",IF(AND(U89<>"",INT(U89)>=TODAY()),"Submissions closed - event ahead","Expired")))))))) -> Expired | Z89: E-mail submission; attendance registration through a Google Form (forms.gle/GQaMUkYHEPpXyFaFA) | AA89: Not published on the site | AB89: https://hci.si/ | AC89: Website | AD89: Organising committee via hci.si (Matjaz Kljun, Ciril Bohak, Nilukshan Krishnaram) | AE89: 46269 | AF89: ARCHIVED. TWO DATES ADDED that were blank, and both were extended by the organisers: "Submission deadline: 25 September 2025 1 October 2025" and "Notification to authors: 2 October 2025 3 October 2025" - the later date in each pair is the one that applied. Conference date confirmed: "Monday, 13 October 2025", at FAMNIT, University of Primorska, Koper, Slovenia. "The conference is free to attend. Attendees cover their own expenses to reach the venue"; registration was nonetheless required through a Google Form. 10th edition. Proceedings DOI 10.26493/978-961-293-559-7. No camera-ready date or page limit published. | AG89: 45723
A90: 89 | B90: ISW-CoLInS | C90: 2025 | D90: — | E90: Intelligent Systems Workshop at CoLInS | F90: Workshop | G90: Finished | H90: =IF($G90="High",1,IF($G90="Mediocre",2,3)) -> 3 | I90: CEUR.org | J90: CEUR Vol-3983 (ISSN 1613-0073, URN urn:nbn:de:0074-3983-X) | K90: Not published | S90: 15–16 May 2025 | T90: 45792 | U90: 45793 | V90: Kharkiv, Ukraine | W90: On-site (inside CoLInS 2025, Kharkiv) | X90: =IF(O90="","",INT(O90)-TODAY()) | Y90: =IF($G90="Finished","Expired",IF(AND(O90<>"",INT(O90)>=TODAY()),IF(INT(O90)-TODAY()<=30,"Open - closing soon","Open"),IF(AND(T90<>"",U90<>"",INT(T90)<=TODAY(),INT(U90)>=TODAY()),"Event in progress",IF(AND(O90="",R90<>"",INT(R90)>=TODAY()),"Registration due",IF(AND(O90="",U90<>"",INT(U90)>=TODAY()),"Deadline not published",IF(AND(O90<>"",Q90<>"",INT(Q90)>=TODAY()),"Camera-ready due",IF(AND(O90<>"",R90<>"",INT(R90)>=TODAY()),"Registration due",IF(AND(U90<>"",INT(U90)>=TODAY()),"Submissions closed - event ahead","Expired")))))))) -> Expired | Z90: Not stated | AA90: Not stated - the source is a published CEUR volume, which carries no author guidelines (CEUR house style is CEURART one-column) | AB90: https://ceur-ws.org/Vol-3983/ | AC90: CEUR volume | AD90: Volume editors Olga Cherednichenko, Vasyl Lytvyn and others | AE90: 46269 | AF90: ACRONYM CORRECTED from IS-CoLInS to ISW-CoLInS, which is the acronym the volume itself uses. Vol-3983 states verbatim: "ISW-CoLInS 2025", "Intelligent Systems Workshop at CoLInS 2025", "Proceedings of the Intelligent Systems Workshop at 9th International Conference on Computational Linguistics and Intelligent Systems (CoLInS-2025)", "Kharkiv, Ukraine, May 15-16, 2025", edited by Olga Cherednichenko, Vasyl Lytvyn and others. Event dates confirmed. No deadlines or fee are recoverable from a published volume. | AG90: 46269
A91: 90 | B91: IT&I-WS: AITDS | C91: 2025 | D91: — | E91: IT&I Workshop: Artificial Intelligence Technologies and Data Science | F91: Workshop | G91: Finished | H91: =IF($G91="High",1,IF($G91="Mediocre",2,3)) -> 3 | I91: CEUR.org | J91: CEUR Vol-4158 (ISSN 1613-0073, URN urn:nbn:de:0074-4158-x); 26 papers submitted | K91: Not published | S91: 20–21 Nov 2025 | T91: 45981 | U91: 45982 | V91: Taras Shevchenko National University of Kyiv, Ukraine | W91: Not stated | X91: =IF(O91="","",INT(O91)-TODAY()) | Y91: =IF($G91="Finished","Expired",IF(AND(O91<>"",INT(O91)>=TODAY()),IF(INT(O91)-TODAY()<=30,"Open - closing soon","Open"),IF(AND(T91<>"",U91<>"",INT(T91)<=TODAY(),INT(U91)>=TODAY()),"Event in progress",IF(AND(O91="",R91<>"",INT(R91)>=TODAY()),"Registration due",IF(AND(O91="",U91<>"",INT(U91)>=TODAY()),"Deadline not published",IF(AND(O91<>"",Q91<>"",INT(Q91)>=TODAY()),"Camera-ready due",IF(AND(O91<>"",R91<>"",INT(R91)>=TODAY()),"Registration due",IF(AND(U91<>"",INT(U91)>=TODAY()),"Submissions closed - event ahead","Expired")))))))) -> Expired | Z91: Not stated | AA91: Not stated - the source is a published CEUR volume, which carries no author guidelines (CEUR house style is CEURART one-column) | AB91: http://iti.fit.univ.kiev.ua/en/workshops/ | AC91: Website; CEUR volume | AD91: iti.fit@knu.ua; +380 44 4814407 (Faculty of Information Technology, Taras Shevchenko NU of Kyiv) | AE91: 46269 | AF91: ARCHIVED, VOLUME RE-READ. Vol-4158 states verbatim: "Proceedings of the Information Technology and Implementation (IT&I) Workshop: Artificial Intelligence Technologies and Data Science (IT&I-WS: AITDS 2025), Kyiv, Ukraine, November 20 - 21, 2025", edited by Vitaliy Snytyuk, Lyudmyla Kirichenko, Oksana Mulesa and Serhii Lupenko; published on CEUR-WS 07.02.2026. Event dates confirmed. ADDED the conference contact block. NOTE the recorded /en/workshops/ page currently reads only "Will be soon..." - it carries no workshop details at all, so the volume is the only usable source for this row. | AG91: 46269
A92: 91 | B92: IT&I-WS: ISICP | C92: 2025 | D92: — | E92: IT&I Workshop: Information Systems And Intelligent Cyber Protection | F92: Workshop | G92: Finished | H92: =IF($G92="High",1,IF($G92="Mediocre",2,3)) -> 3 | I92: CEUR.org | J92: CEUR Vol-4170 (ISSN 1613-0073, URN urn:nbn:de:0074-4170-x); 27 papers submitted | K92: Not published | S92: 20–21 Nov 2025 | T92: 45981 | U92: 45982 | V92: Taras Shevchenko National University of Kyiv, Ukraine | W92: Not stated | X92: =IF(O92="","",INT(O92)-TODAY()) | Y92: =IF($G92="Finished","Expired",IF(AND(O92<>"",INT(O92)>=TODAY()),IF(INT(O92)-TODAY()<=30,"Open - closing soon","Open"),IF(AND(T92<>"",U92<>"",INT(T92)<=TODAY(),INT(U92)>=TODAY()),"Event in progress",IF(AND(O92="",R92<>"",INT(R92)>=TODAY()),"Registration due",IF(AND(O92="",U92<>"",INT(U92)>=TODAY()),"Deadline not published",IF(AND(O92<>"",Q92<>"",INT(Q92)>=TODAY()),"Camera-ready due",IF(AND(O92<>"",R92<>"",INT(R92)>=TODAY()),"Registration due",IF(AND(U92<>"",INT(U92)>=TODAY()),"Submissions closed - event ahead","Expired")))))))) -> Expired | Z92: Not stated | AA92: Not stated - the source is a published CEUR volume, which carries no author guidelines (CEUR house style is CEURART one-column) | AB92: http://iti.fit.univ.kiev.ua/en/workshops/ | AC92: Website; CEUR volume | AD92: iti.fit@knu.ua; +380 44 4814407 (Faculty of Information Technology, Taras Shevchenko NU of Kyiv) | AE92: 46269 | AF92: ARCHIVED, VOLUME RE-READ. Vol-4170 states verbatim: "Proceedings of the Information Technology and Implementation (IT&I) Workshop: Information Systems And Intelligent Cyber Protection (IT&I-WS: ISICP 2025), Kyiv, Ukraine, November 20 - 21, 2025", edited by Serhii Toliupa, Dmytro Lande, Iurii Krak and Sergiy Yakovlev; published on CEUR-WS 20.02.2026. Event dates confirmed. ADDED the conference contact block. NOTE the recorded /en/workshops/ page currently reads only "Will be soon...". | AG92: 46269
A93: 92 | B93: IT&I-WS: ITIAS | C93: 2024 | D93: — | E93: IT&I Workshop: IT Infrastructure and Applied Solutions | F93: Workshop | G93: Finished | H93: =IF($G93="High",1,IF($G93="Mediocre",2,3)) -> 3 | I93: CEUR.org | J93: CEUR Vol-3955 (ISSN 1613-0073, URN urn:nbn:de:0074-3955-X); series lineage back to Vol-2833 | K93: Not published | S93: 20–21 Nov 2024 | T93: 45616 | U93: 45617 | V93: Taras Shevchenko National University of Kyiv, Ukraine | W93: Not stated | X93: =IF(O93="","",INT(O93)-TODAY()) | Y93: =IF($G93="Finished","Expired",IF(AND(O93<>"",INT(O93)>=TODAY()),IF(INT(O93)-TODAY()<=30,"Open - closing soon","Open"),IF(AND(T93<>"",U93<>"",INT(T93)<=TODAY(),INT(U93)>=TODAY()),"Event in progress",IF(AND(O93="",R93<>"",INT(R93)>=TODAY()),"Registration due",IF(AND(O93="",U93<>"",INT(U93)>=TODAY()),"Deadline not published",IF(AND(O93<>"",Q93<>"",INT(Q93)>=TODAY()),"Camera-ready due",IF(AND(O93<>"",R93<>"",INT(R93)>=TODAY()),"Registration due",IF(AND(U93<>"",INT(U93)>=TODAY()),"Submissions closed - event ahead","Expired")))))))) -> Expired | Z93: Not stated | AA93: Not stated - the source is a published CEUR volume, which carries no author guidelines (CEUR house style is CEURART one-column) | AB93: http://iti.fit.univ.kiev.ua/en/workshops/ | AC93: Website; CEUR volume | AD93: iti.fit@knu.ua; +380 44 4814407 (Faculty of Information Technology, Taras Shevchenko NU of Kyiv) | AE93: 46269 | AF93: ARCHIVED, VOLUME RE-READ, AND ONE VOLUME NUMBER REMOVED. Vol-3955 states verbatim: "Proceedings of the Information Technology and Implementation (IT&I) Workshop: IT Infrastructure and Applied Solutions (IT&I-WS 2024: ITIAS), Kyiv, Ukraine, November 20 - 21, 2024", edited by Vitaliy Snytyuk, Lyudmyla Kirichenko, Oksana Mulesa and Serhii Lupenko. The indexing cell previously listed Vol-3933 alongside it, but Vol-3933 is a DIFFERENT workshop from the same conference - "Intelligent Systems and Security 2024 (IT&I-WS 2024: ISS)" - and appears on Vol-3955 only as a "see also" series pointer. The IT&I 2024 main conference proceedings are Vol-3909 ("Selected Papers of the XI International Scientific Conference Information Technology and Implementation (IT&I 2024), Kyiv, Ukraine, November 20-21, 2024"). Event dates confirmed. ADDED the conference contact block. | AG93: 46269
A94: 93 | B94: ITPM | C94: 2025 | D94: 6th | E94: International Workshop on IT Project Management | F94: Workshop | G94: Finished | H94: =IF($G94="High",1,IF($G94="Mediocre",2,3)) -> 3 | I94: CEUR.org | J94: CEUR Vol-4023 (ISSN 1613-0073, URN urn:nbn:de:0074-4023-X); 33 papers submitted | K94: Not published | S94: 22 May 2025 | T94: 45799 | U94: 45799 | V94: Kyiv, Ukraine | W94: Not stated | X94: =IF(O94="","",INT(O94)-TODAY()) | Y94: =IF($G94="Finished","Expired",IF(AND(O94<>"",INT(O94)>=TODAY()),IF(INT(O94)-TODAY()<=30,"Open - closing soon","Open"),IF(AND(T94<>"",U94<>"",INT(T94)<=TODAY(),INT(U94)>=TODAY()),"Event in progress",IF(AND(O94="",R94<>"",INT(R94)>=TODAY()),"Registration due",IF(AND(O94="",U94<>"",INT(U94)>=TODAY()),"Deadline not published",IF(AND(O94<>"",Q94<>"",INT(Q94)>=TODAY()),"Camera-ready due",IF(AND(O94<>"",R94<>"",INT(R94)>=TODAY()),"Registration due",IF(AND(U94<>"",INT(U94)>=TODAY()),"Submissions closed - event ahead","Expired")))))))) -> Expired | Z94: Not stated | AA94: Not stated - the source is a published CEUR volume, which carries no author guidelines (CEUR house style is CEURART one-column) | AB94: https://ceur-ws.org/Vol-4023/ | AC94: CEUR volume | AD94: Volume editors Sergey Bushuyev (Ukrainian Project Management Association), Nataliia Kunanets, Volodymyr Pasichnyk and Nataliia Veretennikova (Lviv Polytechnic National University) | AE94: 46269 | AF94: ARCHIVED, VOLUME RE-READ. Vol-4023 states verbatim: "Proceedings of the 6th International Workshop IT Project Management (ITPM 2025), Kyiv, Ukraine, May 22, 2025", edited by Sergey Bushuyev, Nataliia Kunanets, Volodymyr Pasichnyk and Nataliia Veretennikova. Event date and the 6th-edition label confirmed; no parent conference is named. No deadlines or fee are recoverable from a published volume. | AG94: 46269
A95: 94 | B95: ITS | C95: 2025 | D95: XXV | E95: XXV International Scientific and Practical Conference “Information Technologies and Security” | F95: Workshop | G95: Finished | H95: =IF($G95="High",1,IF($G95="Mediocre",2,3)) -> 3 | I95: CEUR.org | J95: CEUR-WS (selected papers); the most recent published volume is Vol-4068 = ITS 2024, the XXIV conference, Kyiv, 19.12.2024 - no XXV/2025 volume has appeared yet | K95: Not published | S95: 11 Dec 2025 | T95: 46002 | U95: 46002 | V95: Institute for Information Recording, NAS of Ukraine, 2 M. Shpak str., Kyiv, Ukraine | W95: Two parallel sessions plus workshops | X95: =IF(O95="","",INT(O95)-TODAY()) | Y95: =IF($G95="Finished","Expired",IF(AND(O95<>"",INT(O95)>=TODAY()),IF(INT(O95)-TODAY()<=30,"Open - closing soon","Open"),IF(AND(T95<>"",U95<>"",INT(T95)<=TODAY(),INT(U95)>=TODAY()),"Event in progress",IF(AND(O95="",R95<>"",INT(R95)>=TODAY()),"Registration due",IF(AND(O95="",U95<>"",INT(U95)>=TODAY()),"Deadline not published",IF(AND(O95<>"",Q95<>"",INT(Q95)>=TODAY()),"Camera-ready due",IF(AND(O95<>"",R95<>"",INT(R95)>=TODAY()),"Registration due",IF(AND(U95<>"",INT(U95)>=TODAY()),"Submissions closed - event ahead","Expired")))))))) -> Expired | Z95: Not stated | AA95: Not published on the site | AB95: https://its.ipri.kiev.ua/ | AC95: Website | AD95: Institute for Information Recording, NAS of Ukraine (no e-mail published on the conference page) | AE95: 46269 | AF95: ARCHIVED. Event date re-confirmed on the conference site: "11 December 2025", with participants' registration and two parallel sessions, and the site now reads "Registration Closed!". No submission, notification, camera-ready or registration deadline was ever published, and no fee. INDEXING made precise: the latest ITS volume on CEUR is Vol-4068, "Selected Papers of the XXIV International Scientific and Practical Conference Information Technologies and Security (ITS 2024), Kyiv, Ukraine, December 19, 2024", edited by Oleksandr Dodonov and others; the XXV/2025 volume has not been published, so its indexing is expected rather than confirmed. | AG95: 45674
A96: 95 | B96: IWSCI | C96: 2025 | D96: — | E96: International Workshop on Computational Intelligence (at IntSol) | F96: Workshop | G96: Finished | H96: =IF($G96="High",1,IF($G96="Mediocre",2,3)) -> 3 | I96: CEUR.org | J96: CEUR Vol-4035 (ISSN 1613-0073, URN urn:nbn:de:0074-4035-X) | K96: Not published | S96: 01–05 May 2025 | T96: 45778 | U96: 45782 | V96: Kyiv–Uzhhorod, Ukraine | W96: On-site (inside IntSol 2025, Kyiv-Uzhhorod) | X96: =IF(O96="","",INT(O96)-TODAY()) | Y96: =IF($G96="Finished","Expired",IF(AND(O96<>"",INT(O96)>=TODAY()),IF(INT(O96)-TODAY()<=30,"Open - closing soon","Open"),IF(AND(T96<>"",U96<>"",INT(T96)<=TODAY(),INT(U96)>=TODAY()),"Event in progress",IF(AND(O96="",R96<>"",INT(R96)>=TODAY()),"Registration due",IF(AND(O96="",U96<>"",INT(U96)>=TODAY()),"Deadline not published",IF(AND(O96<>"",Q96<>"",INT(Q96)>=TODAY()),"Camera-ready due",IF(AND(O96<>"",R96<>"",INT(R96)>=TODAY()),"Registration due",IF(AND(U96<>"",INT(U96)>=TODAY()),"Submissions closed - event ahead","Expired")))))))) -> Expired | Z96: Not stated | AA96: Not stated - the source is a published CEUR volume, which carries no author guidelines (CEUR house style is CEURART one-column) | AB96: https://ceur-ws.org/Vol-4035/ | AC96: CEUR volume | AD96: Volume editors as listed in CEUR Vol-4035 | AE96: 46269 | AF96: ARCHIVED, VOLUME RE-READ. Vol-4035 states verbatim: "Proceedings of the International Workshop on Computational Intelligence (IWSCI 2025)", "co-located with the IV International Scientific Symposium 'Intelligent Solutions' (IntSol 2025)", "Kyiv-Uzhhorod, Ukraine, May 01-05, 2025". Event dates confirmed, and this also fixes the parent symposium as the IV edition. No deadlines or fee are recoverable from a published volume. | AG96: 46269
A97: 96 | B97: MoDaST | C97: 2025 | D97: — | E97: Modern Data Science Technologies Doctoral Consortium | F97: Workshop | G97: Finished | H97: =IF($G97="High",1,IF($G97="Mediocre",2,3)) -> 3 | I97: CEUR.org | J97: CEUR Vol-4005 (ISSN 1613-0073, URN urn:nbn:de:0074-4005-X) | K97: Not published | S97: 15–16 Jun 2025 | T97: 45823 | U97: 45824 | V97: Lviv, Ukraine | W97: Not stated | X97: =IF(O97="","",INT(O97)-TODAY()) | Y97: =IF($G97="Finished","Expired",IF(AND(O97<>"",INT(O97)>=TODAY()),IF(INT(O97)-TODAY()<=30,"Open - closing soon","Open"),IF(AND(T97<>"",U97<>"",INT(T97)<=TODAY(),INT(U97)>=TODAY()),"Event in progress",IF(AND(O97="",R97<>"",INT(R97)>=TODAY()),"Registration due",IF(AND(O97="",U97<>"",INT(U97)>=TODAY()),"Deadline not published",IF(AND(O97<>"",Q97<>"",INT(Q97)>=TODAY()),"Camera-ready due",IF(AND(O97<>"",R97<>"",INT(R97)>=TODAY()),"Registration due",IF(AND(U97<>"",INT(U97)>=TODAY()),"Submissions closed - event ahead","Expired")))))))) -> Expired | Z97: Not stated | AA97: Not stated - the source is a published CEUR volume, which carries no author guidelines (CEUR house style is CEURART one-column) | AB97: https://ceur-ws.org/Vol-4005/ | AC97: CEUR volume | AD97: Volume editors Vasyl Lytvyn (Lviv Polytechnic National University), Agnieszka Kowalska-Styczen and Lyubomyr Chyrun | AE97: 46269 | AF97: ARCHIVED, VOLUME RE-READ. Vol-4005 states verbatim: "Proceedings of the Modern Data Science Technologies Doctoral Consortium (MoDaST 2025)", "Lviv, Ukraine, June 15-16, 2025", edited by Vasyl Lytvyn, Agnieszka Kowalska-Styczen and Lyubomyr Chyrun. Event dates confirmed; the volume names no parent conference, though it runs in the same Lviv week as MoMLeT 2025 (14-15.06.2025, Vol-4004). No deadlines or fee are recoverable from a published volume. | AG97: 46269
